Workbook

Sheet Urban
A1: 0 | B1: CREDIT REALLOCATION | M1: LEAVE | AD1: LEAVE | AG1: LEAVE | AH1: LEAVE
A2: S/N | B2: Customer | C2: Area | D2: GBNL URN | E2: Initial Credit Value | F2: To be Utilized | G2: Balance | H2: New Credit Value | I2: Name | J2: Region | K2: AREA | L2: GBNL URN | M2: August '22 Target Value (₦) | N2: Current Target | O2: B & H Switch | P2: Rothmans Switch | Q2: Benson & Hedges Boost | R2: Benson & Hedges Demi-Slims | S2: Benson & Hedges Flavour | T2: Dunhill Switch | U2: ST Moritz By Dunhill | V2: Rothmans Menthol | W2: Pall Mall Filter | X2: Pall Mall Menthol | Y2: Rothmans Flavour | Z2: Royal Std Filter | AA2: Pall Mall - Excel Blend | AB2: Pall Mall Boost | AC2: New August Target Value | AD2: August '22 Initial Credit Deployment (₦) | AE2: August '22 Initial Credit Deployment (₦) BD View | AF2: BD Check | AG2: Extra Credit Request (₦) | AH2: Total Credit for Upload August '22 (₦) | AI2: % Credit Exposure vs Initial Target | AJ2: % Credit Exposure vs New expected volume | AK2: Justification
A3: 1 | I3: Alh. Idiat Olatunji - 2 | J3: SWR | K3: Agege | L3: LAC3712 | M3: =IFERROR(VLOOKUP($L3,[1]Consolidated!$C$9:$AC$341,27,0),0) -> 17643000 | N3: =IFERROR(VLOOKUP($L3,[1]Consolidated!$C$9:$AC$341,5,0),0) -> 80 | O3: 0 | X3: 0 | AC3: =(VLOOKUP($O$2,Prices!$E$3:$F$17,2,FALSE)*Urban!O3)+(VLOOKUP($P$2,Prices!$E$3:$F$17,2,FALSE)*Urban!P3)+(VLOOKUP($Q$2,Prices!$E$3:$F$17,2,FALSE)*Urban!Q3)+(VLOOKUP($R$2,Prices!$E$3:$F$17,2,FALSE)*Urban!R3)+(VLOOKUP($S$2,Prices!$E$3:$F$17,2,FALSE)*Urban!S3)+(VLOOKUP($T$2,Prices!$E$3:$F$17,2,FALSE)*Urban!T3)+(VLOOKUP($U$2,Prices!$E$3:$F$17,2,FALSE)*Urban!U3)+(VLOOKUP($V$2,Prices!$E$3:$F$17,2,FALSE)*Urban!V3)+(VLOOKUP($W$2,Prices!$E$3:$F$17,2,FALSE)*Urban!W3)+(VLOOKUP($X$2,Prices!$E$3:$F$17,2,FALSE)*Urban!X3)+(VLOOKUP($Y$2,Prices!$E$3:$F$17,2,FALSE)*Urban!Y3)+(VLOOKUP($Z$2,Prices!$E$3:$F$17,2,FALSE)*Urban!Z3)+(VLOOKUP($AA$2,Prices!$E$3:$F$17,2,FALSE)*Urban!AA3)+(VLOOKUP($AB$2,Prices!$E$3:$F$17,2,FALSE)*Urban!AB3)+M3 -> 17643000 | AD3: 6172650 | AF3: =AD3-AE3 -> 6172650 | AG3: 0 | AH3: =AD3+AG3 -> 6172650 | AI3: =AH3/M3 -> 0.34986397 | AJ3: =AH3/AC3 -> 0.34986397
A4: 2 | I4: Iya Tosin | J4: SWR | K4: Agege | L4: LAC2292 | M4: =IFERROR(VLOOKUP($L4,[1]Consolidated!$C$9:$AC$341,27,0),0) -> 19740000 | N4: =IFERROR(VLOOKUP($L4,[1]Consolidated!$C$9:$AC$341,5,0),0) -> 90 | AC4: =(VLOOKUP($O$2,Prices!$E$3:$F$17,2,FALSE)*Urban!O4)+(VLOOKUP($P$2,Prices!$E$3:$F$17,2,FALSE)*Urban!P4)+(VLOOKUP($Q$2,Prices!$E$3:$F$17,2,FALSE)*Urban!Q4)+(VLOOKUP($R$2,Prices!$E$3:$F$17,2,FALSE)*Urban!R4)+(VLOOKUP($S$2,Prices!$E$3:$F$17,2,FALSE)*Urban!S4)+(VLOOKUP($T$2,Prices!$E$3:$F$17,2,FALSE)*Urban!T4)+(VLOOKUP($U$2,Prices!$E$3:$F$17,2,FALSE)*Urban!U4)+(VLOOKUP($V$2,Prices!$E$3:$F$17,2,FALSE)*Urban!V4)+(VLOOKUP($W$2,Prices!$E$3:$F$17,2,FALSE)*Urban!W4)+(VLOOKUP($X$2,Prices!$E$3:$F$17,2,FALSE)*Urban!X4)+(VLOOKUP($Y$2,Prices!$E$3:$F$17,2,FALSE)*Urban!Y4)+(VLOOKUP($Z$2,Prices!$E$3:$F$17,2,FALSE)*Urban!Z4)+(VLOOKUP($AA$2,Prices!$E$3:$F$17,2,FALSE)*Urban!AA4)+(VLOOKUP($AB$2,Prices!$E$3:$F$17,2,FALSE)*Urban!AB4)+M4 -> 19740000 | AD4: 6908670 | AF4: =AD4-AE4 -> 6908670 | AH4: =AD4+AG4 -> 6908670 | AI4: =AH4/M4 -> 0.34998328 | AJ4: =AH4/AC4 -> 0.34998328
A5: 3 | I5: Iya Mohammed | J5: SWR | K5: Agege | L5: LAC0666 | M5: =IFERROR(VLOOKUP($L5,[1]Consolidated!$C$9:$AC$341,27,0),0) -> 18900000 | N5: =IFERROR(VLOOKUP($L5,[1]Consolidated!$C$9:$AC$341,5,0),0) -> 80 | AC5: =(VLOOKUP($O$2,Prices!$E$3:$F$17,2,FALSE)*Urban!O5)+(VLOOKUP($P$2,Prices!$E$3:$F$17,2,FALSE)*Urban!P5)+(VLOOKUP($Q$2,Prices!$E$3:$F$17,2,FALSE)*Urban!Q5)+(VLOOKUP($R$2,Prices!$E$3:$F$17,2,FALSE)*Urban!R5)+(VLOOKUP($S$2,Prices!$E$3:$F$17,2,FALSE)*Urban!S5)+(VLOOKUP($T$2,Prices!$E$3:$F$17,2,FALSE)*Urban!T5)+(VLOOKUP($U$2,Prices!$E$3:$F$17,2,FALSE)*Urban!U5)+(VLOOKUP($V$2,Prices!$E$3:$F$17,2,FALSE)*Urban!V5)+(VLOOKUP($W$2,Prices!$E$3:$F$17,2,FALSE)*Urban!W5)+(VLOOKUP($X$2,Prices!$E$3:$F$17,2,FALSE)*Urban!X5)+(VLOOKUP($Y$2,Prices!$E$3:$F$17,2,FALSE)*Urban!Y5)+(VLOOKUP($Z$2,Prices!$E$3:$F$17,2,FALSE)*Urban!Z5)+(VLOOKUP($AA$2,Prices!$E$3:$F$17,2,FALSE)*Urban!AA5)+(VLOOKUP($AB$2,Prices!$E$3:$F$17,2,FALSE)*Urban!AB5)+M5 -> 18900000 | AD5: 6613740 | AF5: =AD5-AE5 -> 6613740 | AH5: =AD5+AG5 -> 6613740 | AI5: =AH5/M5 -> 0.34993333 | AJ5: =AH5/AC5 -> 0.34993333
A6: 4 | I6: IYABO | J6: SWR | K6: Agege | L6: CTAK0007 | M6: =IFERROR(VLOOKUP($L6,[1]Consolidated!$C$9:$AC$341,27,0),0) -> 20470000 | N6: =IFERROR(VLOOKUP($L6,[1]Consolidated!$C$9:$AC$341,5,0),0) -> 90 | O6: 10 | AC6: =(VLOOKUP($O$2,Prices!$E$3:$F$17,2,FALSE)*Urban!O6)+(VLOOKUP($P$2,Prices!$E$3:$F$17,2,FALSE)*Urban!P6)+(VLOOKUP($Q$2,Prices!$E$3:$F$17,2,FALSE)*Urban!Q6)+(VLOOKUP($R$2,Prices!$E$3:$F$17,2,FALSE)*Urban!R6)+(VLOOKUP($S$2,Prices!$E$3:$F$17,2,FALSE)*Urban!S6)+(VLOOKUP($T$2,Prices!$E$3:$F$17,2,FALSE)*Urban!T6)+(VLOOKUP($U$2,Prices!$E$3:$F$17,2,FALSE)*Urban!U6)+(VLOOKUP($V$2,Prices!$E$3:$F$17,2,FALSE)*Urban!V6)+(VLOOKUP($W$2,Prices!$E$3:$F$17,2,FALSE)*Urban!W6)+(VLOOKUP($X$2,Prices!$E$3:$F$17,2,FALSE)*Urban!X6)+(VLOOKUP($Y$2,Prices!$E$3:$F$17,2,FALSE)*Urban!Y6)+(VLOOKUP($Z$2,Prices!$E$3:$F$17,2,FALSE)*Urban!Z6)+(VLOOKUP($AA$2,Prices!$E$3:$F$17,2,FALSE)*Urban!AA6)+(VLOOKUP($AB$2,Prices!$E$3:$F$17,2,FALSE)*Urban!AB6)+M6 -> 23080000 | AD6: 7073100 | AF6: =AD6-AE6 -> 7073100 | AG6: 9000000 | AH6: =AD6+AG6 -> 16073100 | AI6: =AH6/M6 -> 0.78520274 | AJ6: =AH6/AC6 -> 0.69640815 | AK6: She has cleared her July credit. Teller is attached
A7: 5 | I7: NDIGWE SAMUEL TOCHUKWU | J7: SWR | K7: Agege | L7: LAC2393 | M7: =IFERROR(VLOOKUP($L7,[1]Consolidated!$C$9:$AC$341,27,0),0) -> 19740000 | N7: =IFERROR(VLOOKUP($L7,[1]Consolidated!$C$9:$AC$341,5,0),0) -> 90 | AC7: =(VLOOKUP($O$2,Prices!$E$3:$F$17,2,FALSE)*Urban!O7)+(VLOOKUP($P$2,Prices!$E$3:$F$17,2,FALSE)*Urban!P7)+(VLOOKUP($Q$2,Prices!$E$3:$F$17,2,FALSE)*Urban!Q7)+(VLOOKUP($R$2,Prices!$E$3:$F$17,2,FALSE)*Urban!R7)+(VLOOKUP($S$2,Prices!$E$3:$F$17,2,FALSE)*Urban!S7)+(VLOOKUP($T$2,Prices!$E$3:$F$17,2,FALSE)*Urban!T7)+(VLOOKUP($U$2,Prices!$E$3:$F$17,2,FALSE)*Urban!U7)+(VLOOKUP($V$2,Prices!$E$3:$F$17,2,FALSE)*Urban!V7)+(VLOOKUP($W$2,Prices!$E$3:$F$17,2,FALSE)*Urban!W7)+(VLOOKUP($X$2,Prices!$E$3:$F$17,2,FALSE)*Urban!X7)+(VLOOKUP($Y$2,Prices!$E$3:$F$17,2,FALSE)*Urban!Y7)+(VLOOKUP($Z$2,Prices!$E$3:$F$17,2,FALSE)*Urban!Z7)+(VLOOKUP($AA$2,Prices!$E$3:$F$17,2,FALSE)*Urban!AA7)+(VLOOKUP($AB$2,Prices!$E$3:$F$17,2,FALSE)*Urban!AB7)+M7 -> 19740000 | AD7: 6908670 | AF7: =AD7-AE7 -> 6908670 | AH7: =AD7+AG7 -> 6908670 | AI7: =AH7/M7 -> 0.34998328 | AJ7: =AH7/AC7 -> 0.34998328
A8: 6 | I8: UGWU JONAS EMEKA | J8: SWR | K8: Agege | L8: LAC2392 | M8: =IFERROR(VLOOKUP($L8,[1]Consolidated!$C$9:$AC$341,27,0),0) -> 0 | N8: =IFERROR(VLOOKUP($L8,[1]Consolidated!$C$9:$AC$341,5,0),0) -> 0 | AC8: =(VLOOKUP($O$2,Prices!$E$3:$F$17,2,FALSE)*Urban!O8)+(VLOOKUP($P$2,Prices!$E$3:$F$17,2,FALSE)*Urban!P8)+(VLOOKUP($Q$2,Prices!$E$3:$F$17,2,FALSE)*Urban!Q8)+(VLOOKUP($R$2,Prices!$E$3:$F$17,2,FALSE)*Urban!R8)+(VLOOKUP($S$2,Prices!$E$3:$F$17,2,FALSE)*Urban!S8)+(VLOOKUP($T$2,Prices!$E$3:$F$17,2,FALSE)*Urban!T8)+(VLOOKUP($U$2,Prices!$E$3:$F$17,2,FALSE)*Urban!U8)+(VLOOKUP($V$2,Prices!$E$3:$F$17,2,FALSE)*Urban!V8)+(VLOOKUP($W$2,Prices!$E$3:$F$17,2,FALSE)*Urban!W8)+(VLOOKUP($X$2,Prices!$E$3:$F$17,2,FALSE)*Urban!X8)+(VLOOKUP($Y$2,Prices!$E$3:$F$17,2,FALSE)*Urban!Y8)+(VLOOKUP($Z$2,Prices!$E$3:$F$17,2,FALSE)*Urban!Z8)+(VLOOKUP($AA$2,Prices!$E$3:$F$17,2,FALSE)*Urban!AA8)+(VLOOKUP($AB$2,Prices!$E$3:$F$17,2,FALSE)*Urban!AB8)+M8 -> 0 | AD8: 0 | AF8: =AD8-AE8 -> 0 | AH8: =AD8+AG8 -> 0 | AI8: =AH8/M8 -> #DIV/0! | AJ8: =AH8/AC8 -> #DIV/0!
A9: 7 | I9: BABA SODIQ | J9: SWR | K9: Agege | L9: LAC0073 | M9: =IFERROR(VLOOKUP($L9,[1]Consolidated!$C$9:$AC$341,27,0),0) -> 0 | N9: =IFERROR(VLOOKUP($L9,[1]Consolidated!$C$9:$AC$341,5,0),0) -> 0 | AC9: =(VLOOKUP($O$2,Prices!$E$3:$F$17,2,FALSE)*Urban!O9)+(VLOOKUP($P$2,Prices!$E$3:$F$17,2,FALSE)*Urban!P9)+(VLOOKUP($Q$2,Prices!$E$3:$F$17,2,FALSE)*Urban!Q9)+(VLOOKUP($R$2,Prices!$E$3:$F$17,2,FALSE)*Urban!R9)+(VLOOKUP($S$2,Prices!$E$3:$F$17,2,FALSE)*Urban!S9)+(VLOOKUP($T$2,Prices!$E$3:$F$17,2,FALSE)*Urban!T9)+(VLOOKUP($U$2,Prices!$E$3:$F$17,2,FALSE)*Urban!U9)+(VLOOKUP($V$2,Prices!$E$3:$F$17,2,FALSE)*Urban!V9)+(VLOOKUP($W$2,Prices!$E$3:$F$17,2,FALSE)*Urban!W9)+(VLOOKUP($X$2,Prices!$E$3:$F$17,2,FALSE)*Urban!X9)+(VLOOKUP($Y$2,Prices!$E$3:$F$17,2,FALSE)*Urban!Y9)+(VLOOKUP($Z$2,Prices!$E$3:$F$17,2,FALSE)*Urban!Z9)+(VLOOKUP($AA$2,Prices!$E$3:$F$17,2,FALSE)*Urban!AA9)+(VLOOKUP($AB$2,Prices!$E$3:$F$17,2,FALSE)*Urban!AB9)+M9 -> 0 | AD9: 0 | AF9: =AD9-AE9 -> 0 | AH9: =AD9+AG9 -> 0 | AI9: =AH9/M9 -> #DIV/0! | AJ9: =AH9/AC9 -> #DIV/0!
A10: 8 | I10: ADEJOKE TIJANI | J10: SWR | K10: Agege | L10: CTAJ0007 | M10: =IFERROR(VLOOKUP($L10,[1]Consolidated!$C$9:$AC$341,27,0),0) -> 28200000 | N10: =IFERROR(VLOOKUP($L10,[1]Consolidated!$C$9:$AC$341,5,0),0) -> 120 | AC10: =(VLOOKUP($O$2,Prices!$E$3:$F$17,2,FALSE)*Urban!O10)+(VLOOKUP($P$2,Prices!$E$3:$F$17,2,FALSE)*Urban!P10)+(VLOOKUP($Q$2,Prices!$E$3:$F$17,2,FALSE)*Urban!Q10)+(VLOOKUP($R$2,Prices!$E$3:$F$17,2,FALSE)*Urban!R10)+(VLOOKUP($S$2,Prices!$E$3:$F$17,2,FALSE)*Urban!S10)+(VLOOKUP($T$2,Prices!$E$3:$F$17,2,FALSE)*Urban!T10)+(VLOOKUP($U$2,Prices!$E$3:$F$17,2,FALSE)*Urban!U10)+(VLOOKUP($V$2,Prices!$E$3:$F$17,2,FALSE)*Urban!V10)+(VLOOKUP($W$2,Prices!$E$3:$F$17,2,FALSE)*Urban!W10)+(VLOOKUP($X$2,Prices!$E$3:$F$17,2,FALSE)*Urban!X10)+(VLOOKUP($Y$2,Prices!$E$3:$F$17,2,FALSE)*Urban!Y10)+(VLOOKUP($Z$2,Prices!$E$3:$F$17,2,FALSE)*Urban!Z10)+(VLOOKUP($AA$2,Prices!$E$3:$F$17,2,FALSE)*Urban!AA10)+(VLOOKUP($AB$2,Prices!$E$3:$F$17,2,FALSE)*Urban!AB10)+M10 -> 28200000 | AD10: 9868410 | AF10: =AD10-AE10 -> 9868410 | AH10: =AD10+AG10 -> 9868410 | AI10: =AH10/M10 -> 0.34994362 | AJ10: =AH10/AC10 -> 0.34994362
A11: 9 | I11: MAMMAH ROSEMARY | J11: SWR | K11: Agege | L11: CTAJ0003 | M11: =IFERROR(VLOOKUP($L11,[1]Consolidated!$C$9:$AC$341,27,0),0) -> 17860000 | N11: =IFERROR(VLOOKUP($L11,[1]Consolidated!$C$9:$AC$341,5,0),0) -> 80 | AC11: =(VLOOKUP($O$2,Prices!$E$3:$F$17,2,FALSE)*Urban!O11)+(VLOOKUP($P$2,Prices!$E$3:$F$17,2,FALSE)*Urban!P11)+(VLOOKUP($Q$2,Prices!$E$3:$F$17,2,FALSE)*Urban!Q11)+(VLOOKUP($R$2,Prices!$E$3:$F$17,2,FALSE)*Urban!R11)+(VLOOKUP($S$2,Prices!$E$3:$F$17,2,FALSE)*Urban!S11)+(VLOOKUP($T$2,Prices!$E$3:$F$17,2,FALSE)*Urban!T11)+(VLOOKUP($U$2,Prices!$E$3:$F$17,2,FALSE)*Urban!U11)+(VLOOKUP($V$2,Prices!$E$3:$F$17,2,FALSE)*Urban!V11)+(VLOOKUP($W$2,Prices!$E$3:$F$17,2,FALSE)*Urban!W11)+(VLOOKUP($X$2,Prices!$E$3:$F$17,2,FALSE)*Urban!X11)+(VLOOKUP($Y$2,Prices!$E$3:$F$17,2,FALSE)*Urban!Y11)+(VLOOKUP($Z$2,Prices!$E$3:$F$17,2,FALSE)*Urban!Z11)+(VLOOKUP($AA$2,Prices!$E$3:$F$17,2,FALSE)*Urban!AA11)+(VLOOKUP($AB$2,Prices!$E$3:$F$17,2,FALSE)*Urban!AB11)+M11 -> 17860000 | AD11: 6237900 | AF11: =AD11-AE11 -> 6237900 | AH11: =AD11+AG11 -> 6237900 | AI11: =AH11/M11 -> 0.34926652 | AJ11: =AH11/AC11 -> 0.34926652
A12: 10 | I12: WONUJUWONLO VENTURE | J12: SWR | K12: Agege | L12: LAC2298 | M12: =IFERROR(VLOOKUP($L12,'[2]Top WH -National'!$D$9:$AC$124,26,0),0) -> 73428000 | N12: =IFERROR(VLOOKUP($L12,'[2]Top WH -National'!$D$9:$AC$124,4,0),0) -> 352 | AC12: =(VLOOKUP($O$2,Prices!$E$3:$F$17,2,FALSE)*Urban!O12)+(VLOOKUP($P$2,Prices!$E$3:$F$17,2,FALSE)*Urban!P12)+(VLOOKUP($Q$2,Prices!$E$3:$F$17,2,FALSE)*Urban!Q12)+(VLOOKUP($R$2,Prices!$E$3:$F$17,2,FALSE)*Urban!R12)+(VLOOKUP($S$2,Prices!$E$3:$F$17,2,FALSE)*Urban!S12)+(VLOOKUP($T$2,Prices!$E$3:$F$17,2,FALSE)*Urban!T12)+(VLOOKUP($U$2,Prices!$E$3:$F$17,2,FALSE)*Urban!U12)+(VLOOKUP($V$2,Prices!$E$3:$F$17,2,FALSE)*Urban!V12)+(VLOOKUP($W$2,Prices!$E$3:$F$17,2,FALSE)*Urban!W12)+(VLOOKUP($X$2,Prices!$E$3:$F$17,2,FALSE)*Urban!X12)+(VLOOKUP($Y$2,Prices!$E$3:$F$17,2,FALSE)*Urban!Y12)+(VLOOKUP($Z$2,Prices!$E$3:$F$17,2,FALSE)*Urban!Z12)+(VLOOKUP($AA$2,Prices!$E$3:$F$17,2,FALSE)*Urban!AA12)+(VLOOKUP($AB$2,Prices!$E$3:$F$17,2,FALSE)*Urban!AB12)+M12 -> 73428000 | AD12: 47840000 | AF12: =AD12-AE12 -> 47840000 | AH12: =AD12+AG12 -> 47840000 | AI12: =AH12/M12 -> 0.65152258 | AJ12: =AH12/AC12 -> 0.65152258
A13: 11 | I13: Iya Faidat Trading Stores | J13: SWR | K13: Agege | L13: LAC1605 | M13: =IFERROR(VLOOKUP($L13,[1]Consolidated!$C$9:$AC$341,27,0),0) -> 23290000 | N13: =IFERROR(VLOOKUP($L13,[1]Consolidated!$C$9:$AC$341,5,0),0) -> 100 | AC13: =(VLOOKUP($O$2,Prices!$E$3:$F$17,2,FALSE)*Urban!O13)+(VLOOKUP($P$2,Prices!$E$3:$F$17,2,FALSE)*Urban!P13)+(VLOOKUP($Q$2,Prices!$E$3:$F$17,2,FALSE)*Urban!Q13)+(VLOOKUP($R$2,Prices!$E$3:$F$17,2,FALSE)*Urban!R13)+(VLOOKUP($S$2,Prices!$E$3:$F$17,2,FALSE)*Urban!S13)+(VLOOKUP($T$2,Prices!$E$3:$F$17,2,FALSE)*Urban!T13)+(VLOOKUP($U$2,Prices!$E$3:$F$17,2,FALSE)*Urban!U13)+(VLOOKUP($V$2,Prices!$E$3:$F$17,2,FALSE)*Urban!V13)+(VLOOKUP($W$2,Prices!$E$3:$F$17,2,FALSE)*Urban!W13)+(VLOOKUP($X$2,Prices!$E$3:$F$17,2,FALSE)*Urban!X13)+(VLOOKUP($Y$2,Prices!$E$3:$F$17,2,FALSE)*Urban!Y13)+(VLOOKUP($Z$2,Prices!$E$3:$F$17,2,FALSE)*Urban!Z13)+(VLOOKUP($AA$2,Prices!$E$3:$F$17,2,FALSE)*Urban!AA13)+(VLOOKUP($AB$2,Prices!$E$3:$F$17,2,FALSE)*Urban!AB13)+M13 -> 23290000 | AD13: 8143200 | AF13: =AD13-AE13 -> 8143200 | AH13: =AD13+AG13 -> 8143200 | AI13: =AH13/M13 -> 0.34964362 | AJ13: =AH13/AC13 -> 0.34964362
A14: 12 | I14: Esther Jimoh | J14: SWR | K14: Agege | L14: LAC0281 | M14: =IFERROR(VLOOKUP($L14,[1]Consolidated!$C$9:$AC$341,27,0),0) -> 28200000 | N14: =IFERROR(VLOOKUP($L14,[1]Consolidated!$C$9:$AC$341,5,0),0) -> 120 | AC14: =(VLOOKUP($O$2,Prices!$E$3:$F$17,2,FALSE)*Urban!O14)+(VLOOKUP($P$2,Prices!$E$3:$F$17,2,FALSE)*Urban!P14)+(VLOOKUP($Q$2,Prices!$E$3:$F$17,2,FALSE)*Urban!Q14)+(VLOOKUP($R$2,Prices!$E$3:$F$17,2,FALSE)*Urban!R14)+(VLOOKUP($S$2,Prices!$E$3:$F$17,2,FALSE)*Urban!S14)+(VLOOKUP($T$2,Prices!$E$3:$F$17,2,FALSE)*Urban!T14)+(VLOOKUP($U$2,Prices!$E$3:$F$17,2,FALSE)*Urban!U14)+(VLOOKUP($V$2,Prices!$E$3:$F$17,2,FALSE)*Urban!V14)+(VLOOKUP($W$2,Prices!$E$3:$F$17,2,FALSE)*Urban!W14)+(VLOOKUP($X$2,Prices!$E$3:$F$17,2,FALSE)*Urban!X14)+(VLOOKUP($Y$2,Prices!$E$3:$F$17,2,FALSE)*Urban!Y14)+(VLOOKUP($Z$2,Prices!$E$3:$F$17,2,FALSE)*Urban!Z14)+(VLOOKUP($AA$2,Prices!$E$3:$F$17,2,FALSE)*Urban!AA14)+(VLOOKUP($AB$2,Prices!$E$3:$F$17,2,FALSE)*Urban!AB14)+M14 -> 28200000 | AD14: 9865800 | AF14: =AD14-AE14 -> 9865800 | AH14: =AD14+AG14 -> 9865800 | AI14: =AH14/M14 -> 0.34985106 | AJ14: =AH14/AC14 -> 0.34985106
A15: 13 | I15: IYA OPE | J15: SWR | K15: Agege | L15: CTAH0017 | M15: =IFERROR(VLOOKUP($L15,[1]Consolidated!$C$9:$AC$341,27,0),0) -> 18800000 | N15: =IFERROR(VLOOKUP($L15,[1]Consolidated!$C$9:$AC$341,5,0),0) -> 80 | AC15: =(VLOOKUP($O$2,Prices!$E$3:$F$17,2,FALSE)*Urban!O15)+(VLOOKUP($P$2,Prices!$E$3:$F$17,2,FALSE)*Urban!P15)+(VLOOKUP($Q$2,Prices!$E$3:$F$17,2,FALSE)*Urban!Q15)+(VLOOKUP($R$2,Prices!$E$3:$F$17,2,FALSE)*Urban!R15)+(VLOOKUP($S$2,Prices!$E$3:$F$17,2,FALSE)*Urban!S15)+(VLOOKUP($T$2,Prices!$E$3:$F$17,2,FALSE)*Urban!T15)+(VLOOKUP($U$2,Prices!$E$3:$F$17,2,FALSE)*Urban!U15)+(VLOOKUP($V$2,Prices!$E$3:$F$17,2,FALSE)*Urban!V15)+(VLOOKUP($W$2,Prices!$E$3:$F$17,2,FALSE)*Urban!W15)+(VLOOKUP($X$2,Prices!$E$3:$F$17,2,FALSE)*Urban!X15)+(VLOOKUP($Y$2,Prices!$E$3:$F$17,2,FALSE)*Urban!Y15)+(VLOOKUP($Z$2,Prices!$E$3:$F$17,2,FALSE)*Urban!Z15)+(VLOOKUP($AA$2,Prices!$E$3:$F$17,2,FALSE)*Urban!AA15)+(VLOOKUP($AB$2,Prices!$E$3:$F$17,2,FALSE)*Urban!AB15)+M15 -> 18800000 | AD15: 0 | AF15: =AD15-AE15 -> 0 | AH15: =AD15+AG15 -> 0 | AI15: =AH15/M15 -> 0 | AJ15: =AH15/AC15 -> 0
A16: 14 | I16: KEMI SOLOLA | J16: SWR | K16: Agege | L16: CTAH0003 | M16: =IFERROR(VLOOKUP($L16,'[2]Top WH -National'!$D$9:$AC$124,26,0),0) -> 274042000 | N16: =IFERROR(VLOOKUP($L16,'[2]Top WH -National'!$D$9:$AC$124,4,0),0) -> 1331 | AC16: =(VLOOKUP($O$2,Prices!$E$3:$F$17,2,FALSE)*Urban!O16)+(VLOOKUP($P$2,Prices!$E$3:$F$17,2,FALSE)*Urban!P16)+(VLOOKUP($Q$2,Prices!$E$3:$F$17,2,FALSE)*Urban!Q16)+(VLOOKUP($R$2,Prices!$E$3:$F$17,2,FALSE)*Urban!R16)+(VLOOKUP($S$2,Prices!$E$3:$F$17,2,FALSE)*Urban!S16)+(VLOOKUP($T$2,Prices!$E$3:$F$17,2,FALSE)*Urban!T16)+(VLOOKUP($U$2,Prices!$E$3:$F$17,2,FALSE)*Urban!U16)+(VLOOKUP($V$2,Prices!$E$3:$F$17,2,FALSE)*Urban!V16)+(VLOOKUP($W$2,Prices!$E$3:$F$17,2,FALSE)*Urban!W16)+(VLOOKUP($X$2,Prices!$E$3:$F$17,2,FALSE)*Urban!X16)+(VLOOKUP($Y$2,Prices!$E$3:$F$17,2,FALSE)*Urban!Y16)+(VLOOKUP($Z$2,Prices!$E$3:$F$17,2,FALSE)*Urban!Z16)+(VLOOKUP($AA$2,Prices!$E$3:$F$17,2,FALSE)*Urban!AA16)+(VLOOKUP($AB$2,Prices!$E$3:$F$17,2,FALSE)*Urban!AB16)+M16 -> 274042000 | AD16: 173420000 | AF16: =AD16-AE16 -> 173420000 | AH16: =AD16+AG16 -> 173420000 | AI16: =AH16/M16 -> 0.63282271 | AJ16: =AH16/AC16 -> 0.63282271
A17: 15 | I17: Solid Ventures | J17: SWR | K17: Agege | L17: LAC3860 | M17: =IFERROR(VLOOKUP($L17,[1]Consolidated!$C$9:$AC$341,27,0),0) -> 28930000 | N17: =IFERROR(VLOOKUP($L17,[1]Consolidated!$C$9:$AC$341,5,0),0) -> 120 | AC17: =(VLOOKUP($O$2,Prices!$E$3:$F$17,2,FALSE)*Urban!O17)+(VLOOKUP($P$2,Prices!$E$3:$F$17,2,FALSE)*Urban!P17)+(VLOOKUP($Q$2,Prices!$E$3:$F$17,2,FALSE)*Urban!Q17)+(VLOOKUP($R$2,Prices!$E$3:$F$17,2,FALSE)*Urban!R17)+(VLOOKUP($S$2,Prices!$E$3:$F$17,2,FALSE)*Urban!S17)+(VLOOKUP($T$2,Prices!$E$3:$F$17,2,FALSE)*Urban!T17)+(VLOOKUP($U$2,Prices!$E$3:$F$17,2,FALSE)*Urban!U17)+(VLOOKUP($V$2,Prices!$E$3:$F$17,2,FALSE)*Urban!V17)+(VLOOKUP($W$2,Prices!$E$3:$F$17,2,FALSE)*Urban!W17)+(VLOOKUP($X$2,Prices!$E$3:$F$17,2,FALSE)*Urban!X17)+(VLOOKUP($Y$2,Prices!$E$3:$F$17,2,FALSE)*Urban!Y17)+(VLOOKUP($Z$2,Prices!$E$3:$F$17,2,FALSE)*Urban!Z17)+(VLOOKUP($AA$2,Prices!$E$3:$F$17,2,FALSE)*Urban!AA17)+(VLOOKUP($AB$2,Prices!$E$3:$F$17,2,FALSE)*Urban!AB17)+M17 -> 28930000 | AD17: 10100700 | AF17: =AD17-AE17 -> 10100700 | AH17: =AD17+AG17 -> 10100700 | AI17: =AH17/M17 -> 0.34914276 | AJ17: =AH17/AC17 -> 0.34914276
A18: 16 | I18: Holy water Universal | J18: SWR | K18: Agege | L18: LAC3675 | M18: =IFERROR(VLOOKUP($L18,[1]Consolidated!$C$9:$AC$341,27,0),0) -> 18800000 | N18: =IFERROR(VLOOKUP($L18,[1]Consolidated!$C$9:$AC$341,5,0),0) -> 80 | AC18: =(VLOOKUP($O$2,Prices!$E$3:$F$17,2,FALSE)*Urban!O18)+(VLOOKUP($P$2,Prices!$E$3:$F$17,2,FALSE)*Urban!P18)+(VLOOKUP($Q$2,Prices!$E$3:$F$17,2,FALSE)*Urban!Q18)+(VLOOKUP($R$2,Prices!$E$3:$F$17,2,FALSE)*Urban!R18)+(VLOOKUP($S$2,Prices!$E$3:$F$17,2,FALSE)*Urban!S18)+(VLOOKUP($T$2,Prices!$E$3:$F$17,2,FALSE)*Urban!T18)+(VLOOKUP($U$2,Prices!$E$3:$F$17,2,FALSE)*Urban!U18)+(VLOOKUP($V$2,Prices!$E$3:$F$17,2,FALSE)*Urban!V18)+(VLOOKUP($W$2,Prices!$E$3:$F$17,2,FALSE)*Urban!W18)+(VLOOKUP($X$2,Prices!$E$3:$F$17,2,FALSE)*Urban!X18)+(VLOOKUP($Y$2,Prices!$E$3:$F$17,2,FALSE)*Urban!Y18)+(VLOOKUP($Z$2,Prices!$E$3:$F$17,2,FALSE)*Urban!Z18)+(VLOOKUP($AA$2,Prices!$E$3:$F$17,2,FALSE)*Urban!AA18)+(VLOOKUP($AB$2,Prices!$E$3:$F$17,2,FALSE)*Urban!AB18)+M18 -> 18800000 | AD18: 6577200 | AF18: =AD18-AE18 -> 6577200 | AH18: =AD18+AG18 -> 6577200 | AI18: =AH18/M18 -> 0.34985106 | AJ18: =AH18/AC18 -> 0.34985106
A19: 17 | I19: Modester Ube | J19: SWR | K19: Akure | L19: SWC2850 | M19: =IFERROR(VLOOKUP($L19,[1]Consolidated!$C$9:$AC$341,27,0),0) -> 0 | N19: =IFERROR(VLOOKUP($L19,[1]Consolidated!$C$9:$AC$341,5,0),0) -> 0 | AC19: =(VLOOKUP($O$2,Prices!$E$3:$F$17,2,FALSE)*Urban!O19)+(VLOOKUP($P$2,Prices!$E$3:$F$17,2,FALSE)*Urban!P19)+(VLOOKUP($Q$2,Prices!$E$3:$F$17,2,FALSE)*Urban!Q19)+(VLOOKUP($R$2,Prices!$E$3:$F$17,2,FALSE)*Urban!R19)+(VLOOKUP($S$2,Prices!$E$3:$F$17,2,FALSE)*Urban!S19)+(VLOOKUP($T$2,Prices!$E$3:$F$17,2,FALSE)*Urban!T19)+(VLOOKUP($U$2,Prices!$E$3:$F$17,2,FALSE)*Urban!U19)+(VLOOKUP($V$2,Prices!$E$3:$F$17,2,FALSE)*Urban!V19)+(VLOOKUP($W$2,Prices!$E$3:$F$17,2,FALSE)*Urban!W19)+(VLOOKUP($X$2,Prices!$E$3:$F$17,2,FALSE)*Urban!X19)+(VLOOKUP($Y$2,Prices!$E$3:$F$17,2,FALSE)*Urban!Y19)+(VLOOKUP($Z$2,Prices!$E$3:$F$17,2,FALSE)*Urban!Z19)+(VLOOKUP($AA$2,Prices!$E$3:$F$17,2,FALSE)*Urban!AA19)+(VLOOKUP($AB$2,Prices!$E$3:$F$17,2,FALSE)*Urban!AB19)+M19 -> 0 | AD19: 0 | AF19: =AD19-AE19 -> 0 | AH19: =AD19+AG19 -> 0 | AI19: =AH19/M19 -> #DIV/0! | AJ19: =AH19/AC19 -> #DIV/0!
A20: 18 | I20: Okafor Iloke | J20: SWR | K20: Akure | L20: SWC2335 | M20: =IFERROR(VLOOKUP($L20,[1]Consolidated!$C$9:$AC$341,27,0),0) -> 45120000 | N20: =IFERROR(VLOOKUP($L20,[1]Consolidated!$C$9:$AC$341,5,0),0) -> 180 | AC20: =(VLOOKUP($O$2,Prices!$E$3:$F$17,2,FALSE)*Urban!O20)+(VLOOKUP($P$2,Prices!$E$3:$F$17,2,FALSE)*Urban!P20)+(VLOOKUP($Q$2,Prices!$E$3:$F$17,2,FALSE)*Urban!Q20)+(VLOOKUP($R$2,Prices!$E$3:$F$17,2,FALSE)*Urban!R20)+(VLOOKUP($S$2,Prices!$E$3:$F$17,2,FALSE)*Urban!S20)+(VLOOKUP($T$2,Prices!$E$3:$F$17,2,FALSE)*Urban!T20)+(VLOOKUP($U$2,Prices!$E$3:$F$17,2,FALSE)*Urban!U20)+(VLOOKUP($V$2,Prices!$E$3:$F$17,2,FALSE)*Urban!V20)+(VLOOKUP($W$2,Prices!$E$3:$F$17,2,FALSE)*Urban!W20)+(VLOOKUP($X$2,Prices!$E$3:$F$17,2,FALSE)*Urban!X20)+(VLOOKUP($Y$2,Prices!$E$3:$F$17,2,FALSE)*Urban!Y20)+(VLOOKUP($Z$2,Prices!$E$3:$F$17,2,FALSE)*Urban!Z20)+(VLOOKUP($AA$2,Prices!$E$3:$F$17,2,FALSE)*Urban!AA20)+(VLOOKUP($AB$2,Prices!$E$3:$F$17,2,FALSE)*Urban!AB20)+M20 -> 45120000 | AD20: 14616000 | AF20: =AD20-AE20 -> 14616000 | AH20: =AD20+AG20 -> 14616000 | AI20: =AH20/M20 -> 0.32393617 | AJ20: =AH20/AC20 -> 0.32393617
A21: 19 | I21: St.Judes Stores | J21: SWR | K21: Akure | L21: WCFA000223 | M21: =IFERROR(VLOOKUP($L21,'[2]Top WH -National'!$D$9:$AC$124,26,0),0) -> 71364000 | N21: =IFERROR(VLOOKUP($L21,'[2]Top WH -National'!$D$9:$AC$124,4,0),0) -> 300 | AC21: =(VLOOKUP($O$2,Prices!$E$3:$F$17,2,FALSE)*Urban!O21)+(VLOOKUP($P$2,Prices!$E$3:$F$17,2,FALSE)*Urban!P21)+(VLOOKUP($Q$2,Prices!$E$3:$F$17,2,FALSE)*Urban!Q21)+(VLOOKUP($R$2,Prices!$E$3:$F$17,2,FALSE)*Urban!R21)+(VLOOKUP($S$2,Prices!$E$3:$F$17,2,FALSE)*Urban!S21)+(VLOOKUP($T$2,Prices!$E$3:$F$17,2,FALSE)*Urban!T21)+(VLOOKUP($U$2,Prices!$E$3:$F$17,2,FALSE)*Urban!U21)+(VLOOKUP($V$2,Prices!$E$3:$F$17,2,FALSE)*Urban!V21)+(VLOOKUP($W$2,Prices!$E$3:$F$17,2,FALSE)*Urban!W21)+(VLOOKUP($X$2,Prices!$E$3:$F$17,2,FALSE)*Urban!X21)+(VLOOKUP($Y$2,Prices!$E$3:$F$17,2,FALSE)*Urban!Y21)+(VLOOKUP($Z$2,Prices!$E$3:$F$17,2,FALSE)*Urban!Z21)+(VLOOKUP($AA$2,Prices!$E$3:$F$17,2,FALSE)*Urban!AA21)+(VLOOKUP($AB$2,Prices!$E$3:$F$17,2,FALSE)*Urban!AB21)+M21 -> 71364000 | AD21: 42543000 | AF21: =AD21-AE21 -> 42543000 | AH21: =AD21+AG21 -> 42543000 | AI21: =AH21/M21 -> 0.59614091 | AJ21: =AH21/AC21 -> 0.59614091
A22: 20 | I22: Mc Igwe | J22: SWR | K22: Akure | L22: WCFA000220 | M22: =IFERROR(VLOOKUP($L22,'[2]Top WH -National'!$D$9:$AC$124,26,0),0) -> 69891000 | N22: =IFERROR(VLOOKUP($L22,'[2]Top WH -National'!$D$9:$AC$124,4,0),0) -> 300 | AC22: =(VLOOKUP($O$2,Prices!$E$3:$F$17,2,FALSE)*Urban!O22)+(VLOOKUP($P$2,Prices!$E$3:$F$17,2,FALSE)*Urban!P22)+(VLOOKUP($Q$2,Prices!$E$3:$F$17,2,FALSE)*Urban!Q22)+(VLOOKUP($R$2,Prices!$E$3:$F$17,2,FALSE)*Urban!R22)+(VLOOKUP($S$2,Prices!$E$3:$F$17,2,FALSE)*Urban!S22)+(VLOOKUP($T$2,Prices!$E$3:$F$17,2,FALSE)*Urban!T22)+(VLOOKUP($U$2,Prices!$E$3:$F$17,2,FALSE)*Urban!U22)+(VLOOKUP($V$2,Prices!$E$3:$F$17,2,FALSE)*Urban!V22)+(VLOOKUP($W$2,Prices!$E$3:$F$17,2,FALSE)*Urban!W22)+(VLOOKUP($X$2,Prices!$E$3:$F$17,2,FALSE)*Urban!X22)+(VLOOKUP($Y$2,Prices!$E$3:$F$17,2,FALSE)*Urban!Y22)+(VLOOKUP($Z$2,Prices!$E$3:$F$17,2,FALSE)*Urban!Z22)+(VLOOKUP($AA$2,Prices!$E$3:$F$17,2,FALSE)*Urban!AA22)+(VLOOKUP($AB$2,Prices!$E$3:$F$17,2,FALSE)*Urban!AB22)+M22 -> 69891000 | AD22: 26100000 | AF22: =AD22-AE22 -> 26100000 | AH22: =AD22+AG22 -> 26100000 | AI22: =AH22/M22 -> 0.37343864 | AJ22: =AH22/AC22 -> 0.37343864
A23: 21 | I23: Kelechi Store | J23: SWR | K23: Akure | L23: WCFA000218 | M23: =IFERROR(VLOOKUP($L23,'[2]Top WH -National'!$D$9:$AC$124,26,0),0) -> 70624000 | N23: =IFERROR(VLOOKUP($L23,'[2]Top WH -National'!$D$9:$AC$124,4,0),0) -> 300 | AC23: =(VLOOKUP($O$2,Prices!$E$3:$F$17,2,FALSE)*Urban!O23)+(VLOOKUP($P$2,Prices!$E$3:$F$17,2,FALSE)*Urban!P23)+(VLOOKUP($Q$2,Prices!$E$3:$F$17,2,FALSE)*Urban!Q23)+(VLOOKUP($R$2,Prices!$E$3:$F$17,2,FALSE)*Urban!R23)+(VLOOKUP($S$2,Prices!$E$3:$F$17,2,FALSE)*Urban!S23)+(VLOOKUP($T$2,Prices!$E$3:$F$17,2,FALSE)*Urban!T23)+(VLOOKUP($U$2,Prices!$E$3:$F$17,2,FALSE)*Urban!U23)+(VLOOKUP($V$2,Prices!$E$3:$F$17,2,FALSE)*Urban!V23)+(VLOOKUP($W$2,Prices!$E$3:$F$17,2,FALSE)*Urban!W23)+(VLOOKUP($X$2,Prices!$E$3:$F$17,2,FALSE)*Urban!X23)+(VLOOKUP($Y$2,Prices!$E$3:$F$17,2,FALSE)*Urban!Y23)+(VLOOKUP($Z$2,Prices!$E$3:$F$17,2,FALSE)*Urban!Z23)+(VLOOKUP($AA$2,Prices!$E$3:$F$17,2,FALSE)*Urban!AA23)+(VLOOKUP($AB$2,Prices!$E$3:$F$17,2,FALSE)*Urban!AB23)+M23 -> 70624000 | AD23: 42282000 | AF23: =AD23-AE23 -> 42282000 | AH23: =AD23+AG23 -> 42282000 | AI23: =AH23/M23 -> 0.59869166 | AJ23: =AH23/AC23 -> 0.59869166
A24: 22 | I24: Alhaja Lateef Ayisat | J24: SWR | K24: Akure | L24: WCFA000208 | M24: =IFERROR(VLOOKUP($L24,'[2]Top WH -National'!$D$9:$AC$124,26,0),0) -> 229375000 | N24: =IFERROR(VLOOKUP($L24,'[2]Top WH -National'!$D$9:$AC$124,4,0),0) -> 1004 | AC24: =(VLOOKUP($O$2,Prices!$E$3:$F$17,2,FALSE)*Urban!O24)+(VLOOKUP($P$2,Prices!$E$3:$F$17,2,FALSE)*Urban!P24)+(VLOOKUP($Q$2,Prices!$E$3:$F$17,2,FALSE)*Urban!Q24)+(VLOOKUP($R$2,Prices!$E$3:$F$17,2,FALSE)*Urban!R24)+(VLOOKUP($S$2,Prices!$E$3:$F$17,2,FALSE)*Urban!S24)+(VLOOKUP($T$2,Prices!$E$3:$F$17,2,FALSE)*Urban!T24)+(VLOOKUP($U$2,Prices!$E$3:$F$17,2,FALSE)*Urban!U24)+(VLOOKUP($V$2,Prices!$E$3:$F$17,2,FALSE)*Urban!V24)+(VLOOKUP($W$2,Prices!$E$3:$F$17,2,FALSE)*Urban!W24)+(VLOOKUP($X$2,Prices!$E$3:$F$17,2,FALSE)*Urban!X24)+(VLOOKUP($Y$2,Prices!$E$3:$F$17,2,FALSE)*Urban!Y24)+(VLOOKUP($Z$2,Prices!$E$3:$F$17,2,FALSE)*Urban!Z24)+(VLOOKUP($AA$2,Prices!$E$3:$F$17,2,FALSE)*Urban!AA24)+(VLOOKUP($AB$2,Prices!$E$3:$F$17,2,FALSE)*Urban!AB24)+M24 -> 229375000 | AD24: 138330000 | AF24: =AD24-AE24 -> 138330000 | AH24: =AD24+AG24 -> 138330000 | AI24: =AH24/M24 -> 0.60307357 | AJ24: =AH24/AC24 -> 0.60307357
A25: 23 | I25: Samuel Ube | J25: SWR | K25: Akure | L25: WCFA000177 | M25: =IFERROR(VLOOKUP($L25,'[2]Top WH -National'!$D$9:$AC$124,26,0),0) -> 72774000 | N25: =IFERROR(VLOOKUP($L25,'[2]Top WH -National'!$D$9:$AC$124,4,0),0) -> 300 | AC25: =(VLOOKUP($O$2,Prices!$E$3:$F$17,2,FALSE)*Urban!O25)+(VLOOKUP($P$2,Prices!$E$3:$F$17,2,FALSE)*Urban!P25)+(VLOOKUP($Q$2,Prices!$E$3:$F$17,2,FALSE)*Urban!Q25)+(VLOOKUP($R$2,Prices!$E$3:$F$17,2,FALSE)*Urban!R25)+(VLOOKUP($S$2,Prices!$E$3:$F$17,2,FALSE)*Urban!S25)+(VLOOKUP($T$2,Prices!$E$3:$F$17,2,FALSE)*Urban!T25)+(VLOOKUP($U$2,Prices!$E$3:$F$17,2,FALSE)*Urban!U25)+(VLOOKUP($V$2,Prices!$E$3:$F$17,2,FALSE)*Urban!V25)+(VLOOKUP($W$2,Prices!$E$3:$F$17,2,FALSE)*Urban!W25)+(VLOOKUP($X$2,Prices!$E$3:$F$17,2,FALSE)*Urban!X25)+(VLOOKUP($Y$2,Prices!$E$3:$F$17,2,FALSE)*Urban!Y25)+(VLOOKUP($Z$2,Prices!$E$3:$F$17,2,FALSE)*Urban!Z25)+(VLOOKUP($AA$2,Prices!$E$3:$F$17,2,FALSE)*Urban!AA25)+(VLOOKUP($AB$2,Prices!$E$3:$F$17,2,FALSE)*Urban!AB25)+M25 -> 72774000 | AD25: 39150000 | AF25: =AD25-AE25 -> 39150000 | AH25: =AD25+AG25 -> 39150000 | AI25: =AH25/M25 -> 0.53796686 | AJ25: =AH25/AC25 -> 0.53796686
A26: 24 | I26: Selfas Merchandise Ent. | J26: SWR | K26: Akure | L26: SWC1390 | M26: =IFERROR(VLOOKUP($L26,[1]Consolidated!$C$9:$AC$341,27,0),0) -> 33620000 | N26: =IFERROR(VLOOKUP($L26,[1]Consolidated!$C$9:$AC$341,5,0),0) -> 130 | AC26: =(VLOOKUP($O$2,Prices!$E$3:$F$17,2,FALSE)*Urban!O26)+(VLOOKUP($P$2,Prices!$E$3:$F$17,2,FALSE)*Urban!P26)+(VLOOKUP($Q$2,Prices!$E$3:$F$17,2,FALSE)*Urban!Q26)+(VLOOKUP($R$2,Prices!$E$3:$F$17,2,FALSE)*Urban!R26)+(VLOOKUP($S$2,Prices!$E$3:$F$17,2,FALSE)*Urban!S26)+(VLOOKUP($T$2,Prices!$E$3:$F$17,2,FALSE)*Urban!T26)+(VLOOKUP($U$2,Prices!$E$3:$F$17,2,FALSE)*Urban!U26)+(VLOOKUP($V$2,Prices!$E$3:$F$17,2,FALSE)*Urban!V26)+(VLOOKUP($W$2,Prices!$E$3:$F$17,2,FALSE)*Urban!W26)+(VLOOKUP($X$2,Prices!$E$3:$F$17,2,FALSE)*Urban!X26)+(VLOOKUP($Y$2,Prices!$E$3:$F$17,2,FALSE)*Urban!Y26)+(VLOOKUP($Z$2,Prices!$E$3:$F$17,2,FALSE)*Urban!Z26)+(VLOOKUP($AA$2,Prices!$E$3:$F$17,2,FALSE)*Urban!AA26)+(VLOOKUP($AB$2,Prices!$E$3:$F$17,2,FALSE)*Urban!AB26)+M26 -> 33620000 | AD26: 0 | AF26: =AD26-AE26 -> 0 | AH26: =AD26+AG26 -> 0 | AI26: =AH26/M26 -> 0 | AJ26: =AH26/AC26 -> 0
A27: 25 | I27: Forza Buffalo Investment | J27: SWR | K27: Akure | L27: SWC3412 | M27: =IFERROR(VLOOKUP($L27,[1]Consolidated!$C$9:$AC$341,27,0),0) -> 0 | N27: =IFERROR(VLOOKUP($L27,[1]Consolidated!$C$9:$AC$341,5,0),0) -> 0 | AC27: =(VLOOKUP($O$2,Prices!$E$3:$F$17,2,FALSE)*Urban!O27)+(VLOOKUP($P$2,Prices!$E$3:$F$17,2,FALSE)*Urban!P27)+(VLOOKUP($Q$2,Prices!$E$3:$F$17,2,FALSE)*Urban!Q27)+(VLOOKUP($R$2,Prices!$E$3:$F$17,2,FALSE)*Urban!R27)+(VLOOKUP($S$2,Prices!$E$3:$F$17,2,FALSE)*Urban!S27)+(VLOOKUP($T$2,Prices!$E$3:$F$17,2,FALSE)*Urban!T27)+(VLOOKUP($U$2,Prices!$E$3:$F$17,2,FALSE)*Urban!U27)+(VLOOKUP($V$2,Prices!$E$3:$F$17,2,FALSE)*Urban!V27)+(VLOOKUP($W$2,Prices!$E$3:$F$17,2,FALSE)*Urban!W27)+(VLOOKUP($X$2,Prices!$E$3:$F$17,2,FALSE)*Urban!X27)+(VLOOKUP($Y$2,Prices!$E$3:$F$17,2,FALSE)*Urban!Y27)+(VLOOKUP($Z$2,Prices!$E$3:$F$17,2,FALSE)*Urban!Z27)+(VLOOKUP($AA$2,Prices!$E$3:$F$17,2,FALSE)*Urban!AA27)+(VLOOKUP($AB$2,Prices!$E$3:$F$17,2,FALSE)*Urban!AB27)+M27 -> 0 | AD27: 0 | AF27: =AD27-AE27 -> 0 | AH27: =AD27+AG27 -> 0 | AI27: =AH27/M27 -> #DIV/0! | AJ27: =AH27/AC27 -> #DIV/0!
A28: 26 | I28: IYA KOKORO | J28: SWR | K28: Festac | L28: LAC3572 | M28: =IFERROR(VLOOKUP($L28,[1]Consolidated!$C$9:$AC$341,27,0),0) -> 16242000 | N28: =IFERROR(VLOOKUP($L28,[1]Consolidated!$C$9:$AC$341,5,0),0) -> 75 | AC28: =(VLOOKUP($O$2,Prices!$E$3:$F$17,2,FALSE)*Urban!O28)+(VLOOKUP($P$2,Prices!$E$3:$F$17,2,FALSE)*Urban!P28)+(VLOOKUP($Q$2,Prices!$E$3:$F$17,2,FALSE)*Urban!Q28)+(VLOOKUP($R$2,Prices!$E$3:$F$17,2,FALSE)*Urban!R28)+(VLOOKUP($S$2,Prices!$E$3:$F$17,2,FALSE)*Urban!S28)+(VLOOKUP($T$2,Prices!$E$3:$F$17,2,FALSE)*Urban!T28)+(VLOOKUP($U$2,Prices!$E$3:$F$17,2,FALSE)*Urban!U28)+(VLOOKUP($V$2,Prices!$E$3:$F$17,2,FALSE)*Urban!V28)+(VLOOKUP($W$2,Prices!$E$3:$F$17,2,FALSE)*Urban!W28)+(VLOOKUP($X$2,Prices!$E$3:$F$17,2,FALSE)*Urban!X28)+(VLOOKUP($Y$2,Prices!$E$3:$F$17,2,FALSE)*Urban!Y28)+(VLOOKUP($Z$2,Prices!$E$3:$F$17,2,FALSE)*Urban!Z28)+(VLOOKUP($AA$2,Prices!$E$3:$F$17,2,FALSE)*Urban!AA28)+(VLOOKUP($AB$2,Prices!$E$3:$F$17,2,FALSE)*Urban!AB28)+M28 -> 16242000 | AD28: 3461000 | AF28: =AD28-AE28 -> 3461000 | AH28: =AD28+AG28 -> 3461000 | AI28: =AH28/M28 -> 0.21308952 | AJ28: =AH28/AC28 -> 0.21308952
A29: 27 | I29: T.H. NIG. Enterprises | J29: SWR | K29: Festac | L29: LAC3519 | M29: =IFERROR(VLOOKUP($L29,[1]Consolidated!$C$9:$AC$341,27,0),0) -> 14424000 | N29: =IFERROR(VLOOKUP($L29,[1]Consolidated!$C$9:$AC$341,5,0),0) -> 70 | AC29: =(VLOOKUP($O$2,Prices!$E$3:$F$17,2,FALSE)*Urban!O29)+(VLOOKUP($P$2,Prices!$E$3:$F$17,2,FALSE)*Urban!P29)+(VLOOKUP($Q$2,Prices!$E$3:$F$17,2,FALSE)*Urban!Q29)+(VLOOKUP($R$2,Prices!$E$3:$F$17,2,FALSE)*Urban!R29)+(VLOOKUP($S$2,Prices!$E$3:$F$17,2,FALSE)*Urban!S29)+(VLOOKUP($T$2,Prices!$E$3:$F$17,2,FALSE)*Urban!T29)+(VLOOKUP($U$2,Prices!$E$3:$F$17,2,FALSE)*Urban!U29)+(VLOOKUP($V$2,Prices!$E$3:$F$17,2,FALSE)*Urban!V29)+(VLOOKUP($W$2,Prices!$E$3:$F$17,2,FALSE)*Urban!W29)+(VLOOKUP($X$2,Prices!$E$3:$F$17,2,FALSE)*Urban!X29)+(VLOOKUP($Y$2,Prices!$E$3:$F$17,2,FALSE)*Urban!Y29)+(VLOOKUP($Z$2,Prices!$E$3:$F$17,2,FALSE)*Urban!Z29)+(VLOOKUP($AA$2,Prices!$E$3:$F$17,2,FALSE)*Urban!AA29)+(VLOOKUP($AB$2,Prices!$E$3:$F$17,2,FALSE)*Urban!AB29)+M29 -> 14424000 | AD29: 0 | AF29: =AD29-AE29 -> 0 | AH29: =AD29+AG29 -> 0 | AI29: =AH29/M29 -> 0 | AJ29: =AH29/AC29 -> 0
A30: 28 | I30: CHUKWU EMERIE Stores Limited | J30: SWR | K30: Festac | L30: LAC3531 | M30: =IFERROR(VLOOKUP($L30,'[2]Top WH -National'!$D$9:$AC$124,26,0),0) -> 61481000 | N30: =IFERROR(VLOOKUP($L30,'[2]Top WH -National'!$D$9:$AC$124,4,0),0) -> 300 | AC30: =(VLOOKUP($O$2,Prices!$E$3:$F$17,2,FALSE)*Urban!O30)+(VLOOKUP($P$2,Prices!$E$3:$F$17,2,FALSE)*Urban!P30)+(VLOOKUP($Q$2,Prices!$E$3:$F$17,2,FALSE)*Urban!Q30)+(VLOOKUP($R$2,Prices!$E$3:$F$17,2,FALSE)*Urban!R30)+(VLOOKUP($S$2,Prices!$E$3:$F$17,2,FALSE)*Urban!S30)+(VLOOKUP($T$2,Prices!$E$3:$F$17,2,FALSE)*Urban!T30)+(VLOOKUP($U$2,Prices!$E$3:$F$17,2,FALSE)*Urban!U30)+(VLOOKUP($V$2,Prices!$E$3:$F$17,2,FALSE)*Urban!V30)+(VLOOKUP($W$2,Prices!$E$3:$F$17,2,FALSE)*Urban!W30)+(VLOOKUP($X$2,Prices!$E$3:$F$17,2,FALSE)*Urban!X30)+(VLOOKUP($Y$2,Prices!$E$3:$F$17,2,FALSE)*Urban!Y30)+(VLOOKUP($Z$2,Prices!$E$3:$F$17,2,FALSE)*Urban!Z30)+(VLOOKUP($AA$2,Prices!$E$3:$F$17,2,FALSE)*Urban!AA30)+(VLOOKUP($AB$2,Prices!$E$3:$F$17,2,FALSE)*Urban!AB30)+M30 -> 61481000 | AD30: 37116000 | AF30: =AD30-AE30 -> 37116000 | AH30: =AD30+AG30 -> 37116000 | AI30: =AH30/M30 -> 0.6036987 | AJ30: =AH30/AC30 -> 0.6036987
A31: 29 | G31: =SUM(G3:G30) -> 0 | I31: FLORENCE AGBOOLA | J31: SWR | K31: Festac | L31: LAC3368 | M31: =IFERROR(VLOOKUP($L31,[1]Consolidated!$C$9:$AC$341,27,0),0) -> 14994000 | N31: =IFERROR(VLOOKUP($L31,[1]Consolidated!$C$9:$AC$341,5,0),0) -> 70 | AC31: =(VLOOKUP($O$2,Prices!$E$3:$F$17,2,FALSE)*Urban!O31)+(VLOOKUP($P$2,Prices!$E$3:$F$17,2,FALSE)*Urban!P31)+(VLOOKUP($Q$2,Prices!$E$3:$F$17,2,FALSE)*Urban!Q31)+(VLOOKUP($R$2,Prices!$E$3:$F$17,2,FALSE)*Urban!R31)+(VLOOKUP($S$2,Prices!$E$3:$F$17,2,FALSE)*Urban!S31)+(VLOOKUP($T$2,Prices!$E$3:$F$17,2,FALSE)*Urban!T31)+(VLOOKUP($U$2,Prices!$E$3:$F$17,2,FALSE)*Urban!U31)+(VLOOKUP($V$2,Prices!$E$3:$F$17,2,FALSE)*Urban!V31)+(VLOOKUP($W$2,Prices!$E$3:$F$17,2,FALSE)*Urban!W31)+(VLOOKUP($X$2,Prices!$E$3:$F$17,2,FALSE)*Urban!X31)+(VLOOKUP($Y$2,Prices!$E$3:$F$17,2,FALSE)*Urban!Y31)+(VLOOKUP($Z$2,Prices!$E$3:$F$17,2,FALSE)*Urban!Z31)+(VLOOKUP($AA$2,Prices!$E$3:$F$17,2,FALSE)*Urban!AA31)+(VLOOKUP($AB$2,Prices!$E$3:$F$17,2,FALSE)*Urban!AB31)+M31 -> 14994000 | AD31: 3706000 | AF31: =AD31-AE31 -> 3706000 | AH31: =AD31+AG31 -> 3706000 | AI31: =AH31/M31 -> 0.24716553 | AJ31: =AH31/AC31 -> 0.24716553
A32: 30 | I32: Ibrahim Yahaya | J32: SWR | K32: Festac | L32: LAC2268 | M32: =IFERROR(VLOOKUP($L32,[1]Consolidated!$C$9:$AC$341,27,0),0) -> 31011000 | N32: =IFERROR(VLOOKUP($L32,[1]Consolidated!$C$9:$AC$341,5,0),0) -> 145 | AC32: =(VLOOKUP($O$2,Prices!$E$3:$F$17,2,FALSE)*Urban!O32)+(VLOOKUP($P$2,Prices!$E$3:$F$17,2,FALSE)*Urban!P32)+(VLOOKUP($Q$2,Prices!$E$3:$F$17,2,FALSE)*Urban!Q32)+(VLOOKUP($R$2,Prices!$E$3:$F$17,2,FALSE)*Urban!R32)+(VLOOKUP($S$2,Prices!$E$3:$F$17,2,FALSE)*Urban!S32)+(VLOOKUP($T$2,Prices!$E$3:$F$17,2,FALSE)*Urban!T32)+(VLOOKUP($U$2,Prices!$E$3:$F$17,2,FALSE)*Urban!U32)+(VLOOKUP($V$2,Prices!$E$3:$F$17,2,FALSE)*Urban!V32)+(VLOOKUP($W$2,Prices!$E$3:$F$17,2,FALSE)*Urban!W32)+(VLOOKUP($X$2,Prices!$E$3:$F$17,2,FALSE)*Urban!X32)+(VLOOKUP($Y$2,Prices!$E$3:$F$17,2,FALSE)*Urban!Y32)+(VLOOKUP($Z$2,Prices!$E$3:$F$17,2,FALSE)*Urban!Z32)+(VLOOKUP($AA$2,Prices!$E$3:$F$17,2,FALSE)*Urban!AA32)+(VLOOKUP($AB$2,Prices!$E$3:$F$17,2,FALSE)*Urban!AB32)+M32 -> 31011000 | AD32: 0 | AF32: =AD32-AE32 -> 0 | AH32: =AD32+AG32 -> 0 | AI32: =AH32/M32 -> 0 | AJ32: =AH32/AC32 -> 0
A33: 31 | I33: MOHAMED ALI | J33: SWR | K33: Festac | L33: LAC2259 | M33: =IFERROR(VLOOKUP($L33,[1]Consolidated!$C$9:$AC$341,27,0),0) -> 28831000 | N33: =IFERROR(VLOOKUP($L33,[1]Consolidated!$C$9:$AC$341,5,0),0) -> 135 | AC33: =(VLOOKUP($O$2,Prices!$E$3:$F$17,2,FALSE)*Urban!O33)+(VLOOKUP($P$2,Prices!$E$3:$F$17,2,FALSE)*Urban!P33)+(VLOOKUP($Q$2,Prices!$E$3:$F$17,2,FALSE)*Urban!Q33)+(VLOOKUP($R$2,Prices!$E$3:$F$17,2,FALSE)*Urban!R33)+(VLOOKUP($S$2,Prices!$E$3:$F$17,2,FALSE)*Urban!S33)+(VLOOKUP($T$2,Prices!$E$3:$F$17,2,FALSE)*Urban!T33)+(VLOOKUP($U$2,Prices!$E$3:$F$17,2,FALSE)*Urban!U33)+(VLOOKUP($V$2,Prices!$E$3:$F$17,2,FALSE)*Urban!V33)+(VLOOKUP($W$2,Prices!$E$3:$F$17,2,FALSE)*Urban!W33)+(VLOOKUP($X$2,Prices!$E$3:$F$17,2,FALSE)*Urban!X33)+(VLOOKUP($Y$2,Prices!$E$3:$F$17,2,FALSE)*Urban!Y33)+(VLOOKUP($Z$2,Prices!$E$3:$F$17,2,FALSE)*Urban!Z33)+(VLOOKUP($AA$2,Prices!$E$3:$F$17,2,FALSE)*Urban!AA33)+(VLOOKUP($AB$2,Prices!$E$3:$F$17,2,FALSE)*Urban!AB33)+M33 -> 28831000 | AD33: 6738500 | AF33: =AD33-AE33 -> 6738500 | AH33: =AD33+AG33 -> 6738500 | AI33: =AH33/M33 -> 0.23372412 | AJ33: =AH33/AC33 -> 0.23372412
A34: 32 | I34: IYA AHMED FALY | J34: SWR | K34: Festac | L34: LAC2258 | M34: =IFERROR(VLOOKUP($L34,[1]Consolidated!$C$9:$AC$341,27,0),0) -> 14235000 | N34: =IFERROR(VLOOKUP($L34,[1]Consolidated!$C$9:$AC$341,5,0),0) -> 70 | AC34: =(VLOOKUP($O$2,Prices!$E$3:$F$17,2,FALSE)*Urban!O34)+(VLOOKUP($P$2,Prices!$E$3:$F$17,2,FALSE)*Urban!P34)+(VLOOKUP($Q$2,Prices!$E$3:$F$17,2,FALSE)*Urban!Q34)+(VLOOKUP($R$2,Prices!$E$3:$F$17,2,FALSE)*Urban!R34)+(VLOOKUP($S$2,Prices!$E$3:$F$17,2,FALSE)*Urban!S34)+(VLOOKUP($T$2,Prices!$E$3:$F$17,2,FALSE)*Urban!T34)+(VLOOKUP($U$2,Prices!$E$3:$F$17,2,FALSE)*Urban!U34)+(VLOOKUP($V$2,Prices!$E$3:$F$17,2,FALSE)*Urban!V34)+(VLOOKUP($W$2,Prices!$E$3:$F$17,2,FALSE)*Urban!W34)+(VLOOKUP($X$2,Prices!$E$3:$F$17,2,FALSE)*Urban!X34)+(VLOOKUP($Y$2,Prices!$E$3:$F$17,2,FALSE)*Urban!Y34)+(VLOOKUP($Z$2,Prices!$E$3:$F$17,2,FALSE)*Urban!Z34)+(VLOOKUP($AA$2,Prices!$E$3:$F$17,2,FALSE)*Urban!AA34)+(VLOOKUP($AB$2,Prices!$E$3:$F$17,2,FALSE)*Urban!AB34)+M34 -> 14235000 | AD34: 3691000 | AF34: =AD34-AE34 -> 3691000 | AH34: =AD34+AG34 -> 3691000 | AI34: =AH34/M34 -> 0.25929048 | AJ34: =AH34/AC34 -> 0.25929048
A35: 33 | I35: GEOMAN OKUMA (GM) | J35: SWR | K35: Festac | L35: LAC2254 | M35: =IFERROR(VLOOKUP($L35,[1]Consolidated!$C$9:$AC$341,27,0),0) -> 26559000 | N35: =IFERROR(VLOOKUP($L35,[1]Consolidated!$C$9:$AC$341,5,0),0) -> 130 | AC35: =(VLOOKUP($O$2,Prices!$E$3:$F$17,2,FALSE)*Urban!O35)+(VLOOKUP($P$2,Prices!$E$3:$F$17,2,FALSE)*Urban!P35)+(VLOOKUP($Q$2,Prices!$E$3:$F$17,2,FALSE)*Urban!Q35)+(VLOOKUP($R$2,Prices!$E$3:$F$17,2,FALSE)*Urban!R35)+(VLOOKUP($S$2,Prices!$E$3:$F$17,2,FALSE)*Urban!S35)+(VLOOKUP($T$2,Prices!$E$3:$F$17,2,FALSE)*Urban!T35)+(VLOOKUP($U$2,Prices!$E$3:$F$17,2,FALSE)*Urban!U35)+(VLOOKUP($V$2,Prices!$E$3:$F$17,2,FALSE)*Urban!V35)+(VLOOKUP($W$2,Prices!$E$3:$F$17,2,FALSE)*Urban!W35)+(VLOOKUP($X$2,Prices!$E$3:$F$17,2,FALSE)*Urban!X35)+(VLOOKUP($Y$2,Prices!$E$3:$F$17,2,FALSE)*Urban!Y35)+(VLOOKUP($Z$2,Prices!$E$3:$F$17,2,FALSE)*Urban!Z35)+(VLOOKUP($AA$2,Prices!$E$3:$F$17,2,FALSE)*Urban!AA35)+(VLOOKUP($AB$2,Prices!$E$3:$F$17,2,FALSE)*Urban!AB35)+M35 -> 26559000 | AD35: 6569000 | AF35: =AD35-AE35 -> 6569000 | AH35: =AD35+AG35 -> 6569000 | AI35: =AH35/M35 -> 0.24733612 | AJ35: =AH35/AC35 -> 0.24733612
A36: 34 | I36: EDWIN ONWUAMAIZU | J36: SWR | K36: Festac | L36: LAC2253 | M36: =IFERROR(VLOOKUP($L36,[1]Consolidated!$C$9:$AC$341,27,0),0) -> 27831000 | N36: =IFERROR(VLOOKUP($L36,[1]Consolidated!$C$9:$AC$341,5,0),0) -> 130 | AC36: =(VLOOKUP($O$2,Prices!$E$3:$F$17,2,FALSE)*Urban!O36)+(VLOOKUP($P$2,Prices!$E$3:$F$17,2,FALSE)*Urban!P36)+(VLOOKUP($Q$2,Prices!$E$3:$F$17,2,FALSE)*Urban!Q36)+(VLOOKUP($R$2,Prices!$E$3:$F$17,2,FALSE)*Urban!R36)+(VLOOKUP($S$2,Prices!$E$3:$F$17,2,FALSE)*Urban!S36)+(VLOOKUP($T$2,Prices!$E$3:$F$17,2,FALSE)*Urban!T36)+(VLOOKUP($U$2,Prices!$E$3:$F$17,2,FALSE)*Urban!U36)+(VLOOKUP($V$2,Prices!$E$3:$F$17,2,FALSE)*Urban!V36)+(VLOOKUP($W$2,Prices!$E$3:$F$17,2,FALSE)*Urban!W36)+(VLOOKUP($X$2,Prices!$E$3:$F$17,2,FALSE)*Urban!X36)+(VLOOKUP($Y$2,Prices!$E$3:$F$17,2,FALSE)*Urban!Y36)+(VLOOKUP($Z$2,Prices!$E$3:$F$17,2,FALSE)*Urban!Z36)+(VLOOKUP($AA$2,Prices!$E$3:$F$17,2,FALSE)*Urban!AA36)+(VLOOKUP($AB$2,Prices!$E$3:$F$17,2,FALSE)*Urban!AB36)+M36 -> 27831000 | AD36: 0 | AF36: =AD36-AE36 -> 0 | AH36: =AD36+AG36 -> 0 | AI36: =AH36/M36 -> 0 | AJ36: =AH36/AC36 -> 0
A37: 35 | I37: IYA PETER (MRS AFOLABI) | J37: SWR | K37: Festac | L37: LAC2143 | M37: =IFERROR(VLOOKUP($L37,[1]Consolidated!$C$9:$AC$341,27,0),0) -> 16115000 | N37: =IFERROR(VLOOKUP($L37,[1]Consolidated!$C$9:$AC$341,5,0),0) -> 75 | AC37: =(VLOOKUP($O$2,Prices!$E$3:$F$17,2,FALSE)*Urban!O37)+(VLOOKUP($P$2,Prices!$E$3:$F$17,2,FALSE)*Urban!P37)+(VLOOKUP($Q$2,Prices!$E$3:$F$17,2,FALSE)*Urban!Q37)+(VLOOKUP($R$2,Prices!$E$3:$F$17,2,FALSE)*Urban!R37)+(VLOOKUP($S$2,Prices!$E$3:$F$17,2,FALSE)*Urban!S37)+(VLOOKUP($T$2,Prices!$E$3:$F$17,2,FALSE)*Urban!T37)+(VLOOKUP($U$2,Prices!$E$3:$F$17,2,FALSE)*Urban!U37)+(VLOOKUP($V$2,Prices!$E$3:$F$17,2,FALSE)*Urban!V37)+(VLOOKUP($W$2,Prices!$E$3:$F$17,2,FALSE)*Urban!W37)+(VLOOKUP($X$2,Prices!$E$3:$F$17,2,FALSE)*Urban!X37)+(VLOOKUP($Y$2,Prices!$E$3:$F$17,2,FALSE)*Urban!Y37)+(VLOOKUP($Z$2,Prices!$E$3:$F$17,2,FALSE)*Urban!Z37)+(VLOOKUP($AA$2,Prices!$E$3:$F$17,2,FALSE)*Urban!AA37)+(VLOOKUP($AB$2,Prices!$E$3:$F$17,2,FALSE)*Urban!AB37)+M37 -> 16115000 | AD37: 4383000 | AF37: =AD37-AE37 -> 4383000 | AH37: =AD37+AG37 -> 4383000 | AI37: =AH37/M37 -> 0.27198262 | AJ37: =AH37/AC37 -> 0.27198262
A38: 36 | I38: IYA LATEFATH OLAITAN | J38: SWR | K38: Festac | L38: LAC2255 | M38: =IFERROR(VLOOKUP($L38,[1]Consolidated!$C$9:$AC$341,27,0),0) -> 24909000 | N38: =IFERROR(VLOOKUP($L38,[1]Consolidated!$C$9:$AC$341,5,0),0) -> 120 | AC38: =(VLOOKUP($O$2,Prices!$E$3:$F$17,2,FALSE)*Urban!O38)+(VLOOKUP($P$2,Prices!$E$3:$F$17,2,FALSE)*Urban!P38)+(VLOOKUP($Q$2,Prices!$E$3:$F$17,2,FALSE)*Urban!Q38)+(VLOOKUP($R$2,Prices!$E$3:$F$17,2,FALSE)*Urban!R38)+(VLOOKUP($S$2,Prices!$E$3:$F$17,2,FALSE)*Urban!S38)+(VLOOKUP($T$2,Prices!$E$3:$F$17,2,FALSE)*Urban!T38)+(VLOOKUP($U$2,Prices!$E$3:$F$17,2,FALSE)*Urban!U38)+(VLOOKUP($V$2,Prices!$E$3:$F$17,2,FALSE)*Urban!V38)+(VLOOKUP($W$2,Prices!$E$3:$F$17,2,FALSE)*Urban!W38)+(VLOOKUP($X$2,Prices!$E$3:$F$17,2,FALSE)*Urban!X38)+(VLOOKUP($Y$2,Prices!$E$3:$F$17,2,FALSE)*Urban!Y38)+(VLOOKUP($Z$2,Prices!$E$3:$F$17,2,FALSE)*Urban!Z38)+(VLOOKUP($AA$2,Prices!$E$3:$F$17,2,FALSE)*Urban!AA38)+(VLOOKUP($AB$2,Prices!$E$3:$F$17,2,FALSE)*Urban!AB38)+M38 -> 24909000 | AD38: 6152000 | AF38: =AD38-AE38 -> 6152000 | AH38: =AD38+AG38 -> 6152000 | AI38: =AH38/M38 -> 0.246979 | AJ38: =AH38/AC38 -> 0.246979
A39: 37 | I39: King Joe Incorporation | J39: SWR | K39: Festac | L39: LAC1472 | M39: =IFERROR(VLOOKUP($L39,[1]Consolidated!$C$9:$AC$341,27,0),0) -> 30860000 | N39: =IFERROR(VLOOKUP($L39,[1]Consolidated!$C$9:$AC$341,5,0),0) -> 145 | AC39: =(VLOOKUP($O$2,Prices!$E$3:$F$17,2,FALSE)*Urban!O39)+(VLOOKUP($P$2,Prices!$E$3:$F$17,2,FALSE)*Urban!P39)+(VLOOKUP($Q$2,Prices!$E$3:$F$17,2,FALSE)*Urban!Q39)+(VLOOKUP($R$2,Prices!$E$3:$F$17,2,FALSE)*Urban!R39)+(VLOOKUP($S$2,Prices!$E$3:$F$17,2,FALSE)*Urban!S39)+(VLOOKUP($T$2,Prices!$E$3:$F$17,2,FALSE)*Urban!T39)+(VLOOKUP($U$2,Prices!$E$3:$F$17,2,FALSE)*Urban!U39)+(VLOOKUP($V$2,Prices!$E$3:$F$17,2,FALSE)*Urban!V39)+(VLOOKUP($W$2,Prices!$E$3:$F$17,2,FALSE)*Urban!W39)+(VLOOKUP($X$2,Prices!$E$3:$F$17,2,FALSE)*Urban!X39)+(VLOOKUP($Y$2,Prices!$E$3:$F$17,2,FALSE)*Urban!Y39)+(VLOOKUP($Z$2,Prices!$E$3:$F$17,2,FALSE)*Urban!Z39)+(VLOOKUP($AA$2,Prices!$E$3:$F$17,2,FALSE)*Urban!AA39)+(VLOOKUP($AB$2,Prices!$E$3:$F$17,2,FALSE)*Urban!AB39)+M39 -> 30860000 | AD39: 8228000 | AF39: =AD39-AE39 -> 8228000 | AH39: =AD39+AG39 -> 8228000 | AI39: =AH39/M39 -> 0.26662346 | AJ39: =AH39/AC39 -> 0.26662346
A40: 38 | I40: RASHIDAT OLAJIDE (Fauzat) | J40: SWR | K40: Festac | L40: CTAN0012 | M40: =IFERROR(VLOOKUP($L40,[1]Consolidated!$C$9:$AC$341,27,0),0) -> 26111000 | N40: =IFERROR(VLOOKUP($L40,[1]Consolidated!$C$9:$AC$341,5,0),0) -> 120 | AC40: =(VLOOKUP($O$2,Prices!$E$3:$F$17,2,FALSE)*Urban!O40)+(VLOOKUP($P$2,Prices!$E$3:$F$17,2,FALSE)*Urban!P40)+(VLOOKUP($Q$2,Prices!$E$3:$F$17,2,FALSE)*Urban!Q40)+(VLOOKUP($R$2,Prices!$E$3:$F$17,2,FALSE)*Urban!R40)+(VLOOKUP($S$2,Prices!$E$3:$F$17,2,FALSE)*Urban!S40)+(VLOOKUP($T$2,Prices!$E$3:$F$17,2,FALSE)*Urban!T40)+(VLOOKUP($U$2,Prices!$E$3:$F$17,2,FALSE)*Urban!U40)+(VLOOKUP($V$2,Prices!$E$3:$F$17,2,FALSE)*Urban!V40)+(VLOOKUP($W$2,Prices!$E$3:$F$17,2,FALSE)*Urban!W40)+(VLOOKUP($X$2,Prices!$E$3:$F$17,2,FALSE)*Urban!X40)+(VLOOKUP($Y$2,Prices!$E$3:$F$17,2,FALSE)*Urban!Y40)+(VLOOKUP($Z$2,Prices!$E$3:$F$17,2,FALSE)*Urban!Z40)+(VLOOKUP($AA$2,Prices!$E$3:$F$17,2,FALSE)*Urban!AA40)+(VLOOKUP($AB$2,Prices!$E$3:$F$17,2,FALSE)*Urban!AB40)+M40 -> 26111000 | AD40: 0 | AF40: =AD40-AE40 -> 0 | AH40: =AD40+AG40 -> 0 | AI40: =AH40/M40 -> 0 | AJ40: =AH40/AC40 -> 0
A41: 39 | I41: NIKE OLADIPO | J41: SWR | K41: Festac | L41: CTAN0011 | M41: =IFERROR(VLOOKUP($L41,[1]Consolidated!$C$9:$AC$341,27,0),0) -> 26849000 | N41: =IFERROR(VLOOKUP($L41,[1]Consolidated!$C$9:$AC$341,5,0),0) -> 125 | AC41: =(VLOOKUP($O$2,Prices!$E$3:$F$17,2,FALSE)*Urban!O41)+(VLOOKUP($P$2,Prices!$E$3:$F$17,2,FALSE)*Urban!P41)+(VLOOKUP($Q$2,Prices!$E$3:$F$17,2,FALSE)*Urban!Q41)+(VLOOKUP($R$2,Prices!$E$3:$F$17,2,FALSE)*Urban!R41)+(VLOOKUP($S$2,Prices!$E$3:$F$17,2,FALSE)*Urban!S41)+(VLOOKUP($T$2,Prices!$E$3:$F$17,2,FALSE)*Urban!T41)+(VLOOKUP($U$2,Prices!$E$3:$F$17,2,FALSE)*Urban!U41)+(VLOOKUP($V$2,Prices!$E$3:$F$17,2,FALSE)*Urban!V41)+(VLOOKUP($W$2,Prices!$E$3:$F$17,2,FALSE)*Urban!W41)+(VLOOKUP($X$2,Prices!$E$3:$F$17,2,FALSE)*Urban!X41)+(VLOOKUP($Y$2,Prices!$E$3:$F$17,2,FALSE)*Urban!Y41)+(VLOOKUP($Z$2,Prices!$E$3:$F$17,2,FALSE)*Urban!Z41)+(VLOOKUP($AA$2,Prices!$E$3:$F$17,2,FALSE)*Urban!AA41)+(VLOOKUP($AB$2,Prices!$E$3:$F$17,2,FALSE)*Urban!AB41)+M41 -> 26849000 | AD41: 6342000 | AF41: =AD41-AE41 -> 6342000 | AH41: =AD41+AG41 -> 6342000 | AI41: =AH41/M41 -> 0.23620991 | AJ41: =AH41/AC41 -> 0.23620991
A42: 40 | I42: WASIU SILIFAT | J42: SWR | K42: Festac | L42: CTAN0008 | M42: =IFERROR(VLOOKUP($L42,[1]Consolidated!$C$9:$AC$341,27,0),0) -> 26981000 | N42: =IFERROR(VLOOKUP($L42,[1]Consolidated!$C$9:$AC$341,5,0),0) -> 125 | AC42: =(VLOOKUP($O$2,Prices!$E$3:$F$17,2,FALSE)*Urban!O42)+(VLOOKUP($P$2,Prices!$E$3:$F$17,2,FALSE)*Urban!P42)+(VLOOKUP($Q$2,Prices!$E$3:$F$17,2,FALSE)*Urban!Q42)+(VLOOKUP($R$2,Prices!$E$3:$F$17,2,FALSE)*Urban!R42)+(VLOOKUP($S$2,Prices!$E$3:$F$17,2,FALSE)*Urban!S42)+(VLOOKUP($T$2,Prices!$E$3:$F$17,2,FALSE)*Urban!T42)+(VLOOKUP($U$2,Prices!$E$3:$F$17,2,FALSE)*Urban!U42)+(VLOOKUP($V$2,Prices!$E$3:$F$17,2,FALSE)*Urban!V42)+(VLOOKUP($W$2,Prices!$E$3:$F$17,2,FALSE)*Urban!W42)+(VLOOKUP($X$2,Prices!$E$3:$F$17,2,FALSE)*Urban!X42)+(VLOOKUP($Y$2,Prices!$E$3:$F$17,2,FALSE)*Urban!Y42)+(VLOOKUP($Z$2,Prices!$E$3:$F$17,2,FALSE)*Urban!Z42)+(VLOOKUP($AA$2,Prices!$E$3:$F$17,2,FALSE)*Urban!AA42)+(VLOOKUP($AB$2,Prices!$E$3:$F$17,2,FALSE)*Urban!AB42)+M42 -> 26981000 | AD42: 6031000 | AF42: =AD42-AE42 -> 6031000 | AH42: =AD42+AG42 -> 6031000 | AI42: =AH42/M42 -> 0.22352767 | AJ42: =AH42/AC42 -> 0.22352767
A43: 41 | I43: OYEDIJO MIKAILA | J43: SWR | K43: Festac | L43: CTAN0007 | M43: =IFERROR(VLOOKUP($L43,[1]Consolidated!$C$9:$AC$341,27,0),0) -> 15333000 | N43: =IFERROR(VLOOKUP($L43,[1]Consolidated!$C$9:$AC$341,5,0),0) -> 70 | AC43: =(VLOOKUP($O$2,Prices!$E$3:$F$17,2,FALSE)*Urban!O43)+(VLOOKUP($P$2,Prices!$E$3:$F$17,2,FALSE)*Urban!P43)+(VLOOKUP($Q$2,Prices!$E$3:$F$17,2,FALSE)*Urban!Q43)+(VLOOKUP($R$2,Prices!$E$3:$F$17,2,FALSE)*Urban!R43)+(VLOOKUP($S$2,Prices!$E$3:$F$17,2,FALSE)*Urban!S43)+(VLOOKUP($T$2,Prices!$E$3:$F$17,2,FALSE)*Urban!T43)+(VLOOKUP($U$2,Prices!$E$3:$F$17,2,FALSE)*Urban!U43)+(VLOOKUP($V$2,Prices!$E$3:$F$17,2,FALSE)*Urban!V43)+(VLOOKUP($W$2,Prices!$E$3:$F$17,2,FALSE)*Urban!W43)+(VLOOKUP($X$2,Prices!$E$3:$F$17,2,FALSE)*Urban!X43)+(VLOOKUP($Y$2,Prices!$E$3:$F$17,2,FALSE)*Urban!Y43)+(VLOOKUP($Z$2,Prices!$E$3:$F$17,2,FALSE)*Urban!Z43)+(VLOOKUP($AA$2,Prices!$E$3:$F$17,2,FALSE)*Urban!AA43)+(VLOOKUP($AB$2,Prices!$E$3:$F$17,2,FALSE)*Urban!AB43)+M43 -> 15333000 | AD43: 3325000 | AF43: =AD43-AE43 -> 3325000 | AH43: =AD43+AG43 -> 3325000 | AI43: =AH43/M43 -> 0.21685254 | AJ43: =AH43/AC43 -> 0.21685254
... A52: 50 | I52: Gbotie Makinde | J52: SWR | K52: Ibadan | L52: WCFA000047 | M52: =IFERROR(VLOOKUP($L52,[1]Consolidated!$C$9:$AC$341,27,0),0) -> 0 | N52: =IFERROR(VLOOKUP($L52,[1]Consolidated!$C$9:$AC$341,5,0),0) -> 0 | AC52: =(VLOOKUP($O$2,Prices!$E$3:$F$17,2,FALSE)*Urban!O52)+(VLOOKUP($P$2,Prices!$E$3:$F$17,2,FALSE)*Urban!P52)+(VLOOKUP($Q$2,Prices!$E$3:$F$17,2,FALSE)*Urban!Q52)+(VLOOKUP($R$2,Prices!$E$3:$F$17,2,FALSE)*Urban!R52)+(VLOOKUP($S$2,Prices!$E$3:$F$17,2,FALSE)*Urban!S52)+(VLOOKUP($T$2,Prices!$E$3:$F$17,2,FALSE)*Urban!T52)+(VLOOKUP($U$2,Prices!$E$3:$F$17,2,FALSE)*Urban!U52)+(VLOOKUP($V$2,Prices!$E$3:$F$17,2,FALSE)*Urban!V52)+(VLOOKUP($W$2,Prices!$E$3:$F$17,2,FALSE)*Urban!W52)+(VLOOKUP($X$2,Prices!$E$3:$F$17,2,FALSE)*Urban!X52)+(VLOOKUP($Y$2,Prices!$E$3:$F$17,2,FALSE)*Urban!Y52)+(VLOOKUP($Z$2,Prices!$E$3:$F$17,2,FALSE)*Urban!Z52)+(VLOOKUP($AA$2,Prices!$E$3:$F$17,2,FALSE)*Urban!AA52)+(VLOOKUP($AB$2,Prices!$E$3:$F$17,2,FALSE)*Urban!AB52)+M52 -> 0 | AD52: 0 | AF52: =AD52-AE52 -> 0 | AH52: =AD52+AG52 -> 0 | AI52: =AH52/M52 -> #DIV/0! | AJ52: =AH52/AC52 -> #DIV/0!
A53: 51 | I53: Mavellous Store | J53: SWR | K53: Ibadan | L53: SWC2006 | M53: =IFERROR(VLOOKUP($L53,'[2]Top WH -National'!$D$9:$AC$124,26,0),0) -> 136983500 | N53: =IFERROR(VLOOKUP($L53,'[2]Top WH -National'!$D$9:$AC$124,4,0),0) -> 638 | O53: 150 | AC53: =(VLOOKUP($O$2,Prices!$E$3:$F$17,2,FALSE)*Urban!O53)+(VLOOKUP($P$2,Prices!$E$3:$F$17,2,FALSE)*Urban!P53)+(VLOOKUP($Q$2,Prices!$E$3:$F$17,2,FALSE)*Urban!Q53)+(VLOOKUP($R$2,Prices!$E$3:$F$17,2,FALSE)*Urban!R53)+(VLOOKUP($S$2,Prices!$E$3:$F$17,2,FALSE)*Urban!S53)+(VLOOKUP($T$2,Prices!$E$3:$F$17,2,FALSE)*Urban!T53)+(VLOOKUP($U$2,Prices!$E$3:$F$17,2,FALSE)*Urban!U53)+(VLOOKUP($V$2,Prices!$E$3:$F$17,2,FALSE)*Urban!V53)+(VLOOKUP($W$2,Prices!$E$3:$F$17,2,FALSE)*Urban!W53)+(VLOOKUP($X$2,Prices!$E$3:$F$17,2,FALSE)*Urban!X53)+(VLOOKUP($Y$2,Prices!$E$3:$F$17,2,FALSE)*Urban!Y53)+(VLOOKUP($Z$2,Prices!$E$3:$F$17,2,FALSE)*Urban!Z53)+(VLOOKUP($AA$2,Prices!$E$3:$F$17,2,FALSE)*Urban!AA53)+(VLOOKUP($AB$2,Prices!$E$3:$F$17,2,FALSE)*Urban!AB53)+M53 -> 176133500 | AD53: 95886180 | AF53: =AD53-AE53 -> 95886180 | AH53: =AD53+AG53 -> 95886180 | AI53: =AH53/M53 -> 0.69998343 | AJ53: =AH53/AC53 -> 0.54439491 | AK53: Additional credit required for extra volume
A54: 52 | I54: Olaide Oguniyi | J54: SWR | K54: Ibadan | L54: WCFA000004 | M54: =IFERROR(VLOOKUP($L54,[1]Consolidated!$C$9:$AC$341,27,0),0) -> 24402500 | N54: =IFERROR(VLOOKUP($L54,[1]Consolidated!$C$9:$AC$341,5,0),0) -> 130 | AC54: =(VLOOKUP($O$2,Prices!$E$3:$F$17,2,FALSE)*Urban!O54)+(VLOOKUP($P$2,Prices!$E$3:$F$17,2,FALSE)*Urban!P54)+(VLOOKUP($Q$2,Prices!$E$3:$F$17,2,FALSE)*Urban!Q54)+(VLOOKUP($R$2,Prices!$E$3:$F$17,2,FALSE)*Urban!R54)+(VLOOKUP($S$2,Prices!$E$3:$F$17,2,FALSE)*Urban!S54)+(VLOOKUP($T$2,Prices!$E$3:$F$17,2,FALSE)*Urban!T54)+(VLOOKUP($U$2,Prices!$E$3:$F$17,2,FALSE)*Urban!U54)+(VLOOKUP($V$2,Prices!$E$3:$F$17,2,FALSE)*Urban!V54)+(VLOOKUP($W$2,Prices!$E$3:$F$17,2,FALSE)*Urban!W54)+(VLOOKUP($X$2,Prices!$E$3:$F$17,2,FALSE)*Urban!X54)+(VLOOKUP($Y$2,Prices!$E$3:$F$17,2,FALSE)*Urban!Y54)+(VLOOKUP($Z$2,Prices!$E$3:$F$17,2,FALSE)*Urban!Z54)+(VLOOKUP($AA$2,Prices!$E$3:$F$17,2,FALSE)*Urban!AA54)+(VLOOKUP($AB$2,Prices!$E$3:$F$17,2,FALSE)*Urban!AB54)+M54 -> 24402500 | AD54: 5655084.1 | AF54: =AD54-AE54 -> 5655084.1 | AH54: =AD54+AG54 -> 5655084.1 | AI54: =AH54/M54 -> 0.231742 | AJ54: =AH54/AC54 -> 0.231742 | AK54: Additional credit required for extra volume
A55: 53 | I55: Agaga Olayinka | J55: SWR | K55: Ibadan | L55: WCFA000080 | M55: =IFERROR(VLOOKUP($L55,[1]Consolidated!$C$9:$AC$341,27,0),0) -> 0 | N55: =IFERROR(VLOOKUP($L55,[1]Consolidated!$C$9:$AC$341,5,0),0) -> 0 | AC55: =(VLOOKUP($O$2,Prices!$E$3:$F$17,2,FALSE)*Urban!O55)+(VLOOKUP($P$2,Prices!$E$3:$F$17,2,FALSE)*Urban!P55)+(VLOOKUP($Q$2,Prices!$E$3:$F$17,2,FALSE)*Urban!Q55)+(VLOOKUP($R$2,Prices!$E$3:$F$17,2,FALSE)*Urban!R55)+(VLOOKUP($S$2,Prices!$E$3:$F$17,2,FALSE)*Urban!S55)+(VLOOKUP($T$2,Prices!$E$3:$F$17,2,FALSE)*Urban!T55)+(VLOOKUP($U$2,Prices!$E$3:$F$17,2,FALSE)*Urban!U55)+(VLOOKUP($V$2,Prices!$E$3:$F$17,2,FALSE)*Urban!V55)+(VLOOKUP($W$2,Prices!$E$3:$F$17,2,FALSE)*Urban!W55)+(VLOOKUP($X$2,Prices!$E$3:$F$17,2,FALSE)*Urban!X55)+(VLOOKUP($Y$2,Prices!$E$3:$F$17,2,FALSE)*Urban!Y55)+(VLOOKUP($Z$2,Prices!$E$3:$F$17,2,FALSE)*Urban!Z55)+(VLOOKUP($AA$2,Prices!$E$3:$F$17,2,FALSE)*Urban!AA55)+(VLOOKUP($AB$2,Prices!$E$3:$F$17,2,FALSE)*Urban!AB55)+M55 -> 0 | AD55: 0 | AF55: =AD55-AE55 -> 0 | AH55: =AD55+AG55 -> 0 | AI55: =AH55/M55 -> #DIV/0! | AJ55: =AH55/AC55 -> #DIV/0! | AK55: Additional credit required for extra volume
A56: 54 | I56: Hammed Idowu | J56: SWR | K56: Ibadan | L56: WCFA000075 | M56: =IFERROR(VLOOKUP($L56,[1]Consolidated!$C$9:$AC$341,27,0),0) -> 13986000 | N56: =IFERROR(VLOOKUP($L56,[1]Consolidated!$C$9:$AC$341,5,0),0) -> 70 | AC56: =(VLOOKUP($O$2,Prices!$E$3:$F$17,2,FALSE)*Urban!O56)+(VLOOKUP($P$2,Prices!$E$3:$F$17,2,FALSE)*Urban!P56)+(VLOOKUP($Q$2,Prices!$E$3:$F$17,2,FALSE)*Urban!Q56)+(VLOOKUP($R$2,Prices!$E$3:$F$17,2,FALSE)*Urban!R56)+(VLOOKUP($S$2,Prices!$E$3:$F$17,2,FALSE)*Urban!S56)+(VLOOKUP($T$2,Prices!$E$3:$F$17,2,FALSE)*Urban!T56)+(VLOOKUP($U$2,Prices!$E$3:$F$17,2,FALSE)*Urban!U56)+(VLOOKUP($V$2,Prices!$E$3:$F$17,2,FALSE)*Urban!V56)+(VLOOKUP($W$2,Prices!$E$3:$F$17,2,FALSE)*Urban!W56)+(VLOOKUP($X$2,Prices!$E$3:$F$17,2,FALSE)*Urban!X56)+(VLOOKUP($Y$2,Prices!$E$3:$F$17,2,FALSE)*Urban!Y56)+(VLOOKUP($Z$2,Prices!$E$3:$F$17,2,FALSE)*Urban!Z56)+(VLOOKUP($AA$2,Prices!$E$3:$F$17,2,FALSE)*Urban!AA56)+(VLOOKUP($AB$2,Prices!$E$3:$F$17,2,FALSE)*Urban!AB56)+M56 -> 13986000 | AD56: 3241143.6 | AF56: =AD56-AE56 -> 3241143.6 | AH56: =AD56+AG56 -> 3241143.6 | AI56: =AH56/M56 -> 0.231742 | AJ56: =AH56/AC56 -> 0.231742 | AK56: Additional credit required for extra volume
A57: 55 | I57: Mutiyat Olawuwo | J57: SWR | K57: Ibadan | L57: WCFA000073 | M57: =IFERROR(VLOOKUP($L57,[1]Consolidated!$C$9:$AC$341,27,0),0) -> 17348000 | N57: =IFERROR(VLOOKUP($L57,[1]Consolidated!$C$9:$AC$341,5,0),0) -> 85 | AC57: =(VLOOKUP($O$2,Prices!$E$3:$F$17,2,FALSE)*Urban!O57)+(VLOOKUP($P$2,Prices!$E$3:$F$17,2,FALSE)*Urban!P57)+(VLOOKUP($Q$2,Prices!$E$3:$F$17,2,FALSE)*Urban!Q57)+(VLOOKUP($R$2,Prices!$E$3:$F$17,2,FALSE)*Urban!R57)+(VLOOKUP($S$2,Prices!$E$3:$F$17,2,FALSE)*Urban!S57)+(VLOOKUP($T$2,Prices!$E$3:$F$17,2,FALSE)*Urban!T57)+(VLOOKUP($U$2,Prices!$E$3:$F$17,2,FALSE)*Urban!U57)+(VLOOKUP($V$2,Prices!$E$3:$F$17,2,FALSE)*Urban!V57)+(VLOOKUP($W$2,Prices!$E$3:$F$17,2,FALSE)*Urban!W57)+(VLOOKUP($X$2,Prices!$E$3:$F$17,2,FALSE)*Urban!X57)+(VLOOKUP($Y$2,Prices!$E$3:$F$17,2,FALSE)*Urban!Y57)+(VLOOKUP($Z$2,Prices!$E$3:$F$17,2,FALSE)*Urban!Z57)+(VLOOKUP($AA$2,Prices!$E$3:$F$17,2,FALSE)*Urban!AA57)+(VLOOKUP($AB$2,Prices!$E$3:$F$17,2,FALSE)*Urban!AB57)+M57 -> 17348000 | AD57: 4020260.2 | AF57: =AD57-AE57 -> 4020260.2 | AH57: =AD57+AG57 -> 4020260.2 | AI57: =AH57/M57 -> 0.231742 | AJ57: =AH57/AC57 -> 0.231742
A58: 56 | I58: Eskay Tajudeen | J58: SWR | K58: Ibadan | L58: WCFA000071 | M58: =IFERROR(VLOOKUP($L58,[1]Consolidated!$C$9:$AC$341,27,0),0) -> 30683000 | N58: =IFERROR(VLOOKUP($L58,[1]Consolidated!$C$9:$AC$341,5,0),0) -> 150 | AC58: =(VLOOKUP($O$2,Prices!$E$3:$F$17,2,FALSE)*Urban!O58)+(VLOOKUP($P$2,Prices!$E$3:$F$17,2,FALSE)*Urban!P58)+(VLOOKUP($Q$2,Prices!$E$3:$F$17,2,FALSE)*Urban!Q58)+(VLOOKUP($R$2,Prices!$E$3:$F$17,2,FALSE)*Urban!R58)+(VLOOKUP($S$2,Prices!$E$3:$F$17,2,FALSE)*Urban!S58)+(VLOOKUP($T$2,Prices!$E$3:$F$17,2,FALSE)*Urban!T58)+(VLOOKUP($U$2,Prices!$E$3:$F$17,2,FALSE)*Urban!U58)+(VLOOKUP($V$2,Prices!$E$3:$F$17,2,FALSE)*Urban!V58)+(VLOOKUP($W$2,Prices!$E$3:$F$17,2,FALSE)*Urban!W58)+(VLOOKUP($X$2,Prices!$E$3:$F$17,2,FALSE)*Urban!X58)+(VLOOKUP($Y$2,Prices!$E$3:$F$17,2,FALSE)*Urban!Y58)+(VLOOKUP($Z$2,Prices!$E$3:$F$17,2,FALSE)*Urban!Z58)+(VLOOKUP($AA$2,Prices!$E$3:$F$17,2,FALSE)*Urban!AA58)+(VLOOKUP($AB$2,Prices!$E$3:$F$17,2,FALSE)*Urban!AB58)+M58 -> 30683000 | AD58: 7110539.8 | AF58: =AD58-AE58 -> 7110539.8 | AH58: =AD58+AG58 -> 7110539.8 | AI58: =AH58/M58 -> 0.231742 | AJ58: =AH58/AC58 -> 0.231742
A59: 57 | I59: Salewa Stores | J59: SWR | K59: Ibadan | L59: WCFA000061 | M59: =IFERROR(VLOOKUP($L59,[1]Consolidated!$C$9:$AC$341,27,0),0) -> 23402500 | N59: =IFERROR(VLOOKUP($L59,[1]Consolidated!$C$9:$AC$341,5,0),0) -> 120 | AC59: =(VLOOKUP($O$2,Prices!$E$3:$F$17,2,FALSE)*Urban!O59)+(VLOOKUP($P$2,Prices!$E$3:$F$17,2,FALSE)*Urban!P59)+(VLOOKUP($Q$2,Prices!$E$3:$F$17,2,FALSE)*Urban!Q59)+(VLOOKUP($R$2,Prices!$E$3:$F$17,2,FALSE)*Urban!R59)+(VLOOKUP($S$2,Prices!$E$3:$F$17,2,FALSE)*Urban!S59)+(VLOOKUP($T$2,Prices!$E$3:$F$17,2,FALSE)*Urban!T59)+(VLOOKUP($U$2,Prices!$E$3:$F$17,2,FALSE)*Urban!U59)+(VLOOKUP($V$2,Prices!$E$3:$F$17,2,FALSE)*Urban!V59)+(VLOOKUP($W$2,Prices!$E$3:$F$17,2,FALSE)*Urban!W59)+(VLOOKUP($X$2,Prices!$E$3:$F$17,2,FALSE)*Urban!X59)+(VLOOKUP($Y$2,Prices!$E$3:$F$17,2,FALSE)*Urban!Y59)+(VLOOKUP($Z$2,Prices!$E$3:$F$17,2,FALSE)*Urban!Z59)+(VLOOKUP($AA$2,Prices!$E$3:$F$17,2,FALSE)*Urban!AA59)+(VLOOKUP($AB$2,Prices!$E$3:$F$17,2,FALSE)*Urban!AB59)+M59 -> 23402500 | AD59: 5423342.1 | AF59: =AD59-AE59 -> 5423342.1 | AH59: =AD59+AG59 -> 5423342.1 | AI59: =AH59/M59 -> 0.231742 | AJ59: =AH59/AC59 -> 0.231742
A60: 58 | I60: Tawakali Olisa | J60: SWR | K60: Ibadan | L60: WCFA000057 | M60: =IFERROR(VLOOKUP($L60,[1]Consolidated!$C$9:$AC$341,27,0),0) -> 25152500 | N60: =IFERROR(VLOOKUP($L60,[1]Consolidated!$C$9:$AC$341,5,0),0) -> 130 | O60: 15 | AC60: =(VLOOKUP($O$2,Prices!$E$3:$F$17,2,FALSE)*Urban!O60)+(VLOOKUP($P$2,Prices!$E$3:$F$17,2,FALSE)*Urban!P60)+(VLOOKUP($Q$2,Prices!$E$3:$F$17,2,FALSE)*Urban!Q60)+(VLOOKUP($R$2,Prices!$E$3:$F$17,2,FALSE)*Urban!R60)+(VLOOKUP($S$2,Prices!$E$3:$F$17,2,FALSE)*Urban!S60)+(VLOOKUP($T$2,Prices!$E$3:$F$17,2,FALSE)*Urban!T60)+(VLOOKUP($U$2,Prices!$E$3:$F$17,2,FALSE)*Urban!U60)+(VLOOKUP($V$2,Prices!$E$3:$F$17,2,FALSE)*Urban!V60)+(VLOOKUP($W$2,Prices!$E$3:$F$17,2,FALSE)*Urban!W60)+(VLOOKUP($X$2,Prices!$E$3:$F$17,2,FALSE)*Urban!X60)+(VLOOKUP($Y$2,Prices!$E$3:$F$17,2,FALSE)*Urban!Y60)+(VLOOKUP($Z$2,Prices!$E$3:$F$17,2,FALSE)*Urban!Z60)+(VLOOKUP($AA$2,Prices!$E$3:$F$17,2,FALSE)*Urban!AA60)+(VLOOKUP($AB$2,Prices!$E$3:$F$17,2,FALSE)*Urban!AB60)+M60 -> 29067500 | AD60: 15091500 | AF60: =AD60-AE60 -> 15091500 | AG60: 5255750.4 | AH60: =AD60+AG60 -> 20347250 | AI60: =AH60/M60 -> 0.80895537 | AJ60: =AH60/AC60 -> 0.7 | AK60: Additional credit required for extra volume
A61: 59 | I61: Titi Alausa | J61: SWR | K61: Ibadan | L61: WCFA000055 | M61: =IFERROR(VLOOKUP($L61,[1]Consolidated!$C$9:$AC$341,27,0),0) -> 19790000 | N61: =IFERROR(VLOOKUP($L61,[1]Consolidated!$C$9:$AC$341,5,0),0) -> 100 | AC61: =(VLOOKUP($O$2,Prices!$E$3:$F$17,2,FALSE)*Urban!O61)+(VLOOKUP($P$2,Prices!$E$3:$F$17,2,FALSE)*Urban!P61)+(VLOOKUP($Q$2,Prices!$E$3:$F$17,2,FALSE)*Urban!Q61)+(VLOOKUP($R$2,Prices!$E$3:$F$17,2,FALSE)*Urban!R61)+(VLOOKUP($S$2,Prices!$E$3:$F$17,2,FALSE)*Urban!S61)+(VLOOKUP($T$2,Prices!$E$3:$F$17,2,FALSE)*Urban!T61)+(VLOOKUP($U$2,Prices!$E$3:$F$17,2,FALSE)*Urban!U61)+(VLOOKUP($V$2,Prices!$E$3:$F$17,2,FALSE)*Urban!V61)+(VLOOKUP($W$2,Prices!$E$3:$F$17,2,FALSE)*Urban!W61)+(VLOOKUP($X$2,Prices!$E$3:$F$17,2,FALSE)*Urban!X61)+(VLOOKUP($Y$2,Prices!$E$3:$F$17,2,FALSE)*Urban!Y61)+(VLOOKUP($Z$2,Prices!$E$3:$F$17,2,FALSE)*Urban!Z61)+(VLOOKUP($AA$2,Prices!$E$3:$F$17,2,FALSE)*Urban!AA61)+(VLOOKUP($AB$2,Prices!$E$3:$F$17,2,FALSE)*Urban!AB61)+M61 -> 19790000 | AD61: 4586174.2 | AF61: =AD61-AE61 -> 4586174.2 | AH61: =AD61+AG61 -> 4586174.2 | AI61: =AH61/M61 -> 0.231742 | AJ61: =AH61/AC61 -> 0.231742
A62: 60 | I62: Mrs. Ayinke Adebayo | J62: SWR | K62: Ibadan | L62: SWC1269 | M62: =IFERROR(VLOOKUP($L62,[1]Consolidated!$C$9:$AC$341,27,0),0) -> 19790000 | N62: =IFERROR(VLOOKUP($L62,[1]Consolidated!$C$9:$AC$341,5,0),0) -> 100 | AC62: =(VLOOKUP($O$2,Prices!$E$3:$F$17,2,FALSE)*Urban!O62)+(VLOOKUP($P$2,Prices!$E$3:$F$17,2,FALSE)*Urban!P62)+(VLOOKUP($Q$2,Prices!$E$3:$F$17,2,FALSE)*Urban!Q62)+(VLOOKUP($R$2,Prices!$E$3:$F$17,2,FALSE)*Urban!R62)+(VLOOKUP($S$2,Prices!$E$3:$F$17,2,FALSE)*Urban!S62)+(VLOOKUP($T$2,Prices!$E$3:$F$17,2,FALSE)*Urban!T62)+(VLOOKUP($U$2,Prices!$E$3:$F$17,2,FALSE)*Urban!U62)+(VLOOKUP($V$2,Prices!$E$3:$F$17,2,FALSE)*Urban!V62)+(VLOOKUP($W$2,Prices!$E$3:$F$17,2,FALSE)*Urban!W62)+(VLOOKUP($X$2,Prices!$E$3:$F$17,2,FALSE)*Urban!X62)+(VLOOKUP($Y$2,Prices!$E$3:$F$17,2,FALSE)*Urban!Y62)+(VLOOKUP($Z$2,Prices!$E$3:$F$17,2,FALSE)*Urban!Z62)+(VLOOKUP($AA$2,Prices!$E$3:$F$17,2,FALSE)*Urban!AA62)+(VLOOKUP($AB$2,Prices!$E$3:$F$17,2,FALSE)*Urban!AB62)+M62 -> 19790000 | AD62: 4586174.2 | AF62: =AD62-AE62 -> 4586174.2 | AH62: =AD62+AG62 -> 4586174.2 | AI62: =AH62/M62 -> 0.231742 | AJ62: =AH62/AC62 -> 0.231742
A63: 61 | I63: Mujidat Adepegba | J63: SWR | K63: Ibadan | L63: WCFA000052 | M63: =IFERROR(VLOOKUP($L63,[1]Consolidated!$C$9:$AC$341,27,0),0) -> 0 | N63: =IFERROR(VLOOKUP($L63,[1]Consolidated!$C$9:$AC$341,5,0),0) -> 0 | AC63: =(VLOOKUP($O$2,Prices!$E$3:$F$17,2,FALSE)*Urban!O63)+(VLOOKUP($P$2,Prices!$E$3:$F$17,2,FALSE)*Urban!P63)+(VLOOKUP($Q$2,Prices!$E$3:$F$17,2,FALSE)*Urban!Q63)+(VLOOKUP($R$2,Prices!$E$3:$F$17,2,FALSE)*Urban!R63)+(VLOOKUP($S$2,Prices!$E$3:$F$17,2,FALSE)*Urban!S63)+(VLOOKUP($T$2,Prices!$E$3:$F$17,2,FALSE)*Urban!T63)+(VLOOKUP($U$2,Prices!$E$3:$F$17,2,FALSE)*Urban!U63)+(VLOOKUP($V$2,Prices!$E$3:$F$17,2,FALSE)*Urban!V63)+(VLOOKUP($W$2,Prices!$E$3:$F$17,2,FALSE)*Urban!W63)+(VLOOKUP($X$2,Prices!$E$3:$F$17,2,FALSE)*Urban!X63)+(VLOOKUP($Y$2,Prices!$E$3:$F$17,2,FALSE)*Urban!Y63)+(VLOOKUP($Z$2,Prices!$E$3:$F$17,2,FALSE)*Urban!Z63)+(VLOOKUP($AA$2,Prices!$E$3:$F$17,2,FALSE)*Urban!AA63)+(VLOOKUP($AB$2,Prices!$E$3:$F$17,2,FALSE)*Urban!AB63)+M63 -> 0 | AD63: 0 | AF63: =AD63-AE63 -> 0 | AH63: =AD63+AG63 -> 0 | AI63: =AH63/M63 -> #DIV/0! | AJ63: =AH63/AC63 -> #DIV/0!
A64: 62 | I64: Tale Morufat (Iya) | J64: SWR | K64: Ibadan | L64: WCFA000046 | M64: =IFERROR(VLOOKUP($L64,[1]Consolidated!$C$9:$AC$341,27,0),0) -> 0 | N64: =IFERROR(VLOOKUP($L64,[1]Consolidated!$C$9:$AC$341,5,0),0) -> 0 | AC64: =(VLOOKUP($O$2,Prices!$E$3:$F$17,2,FALSE)*Urban!O64)+(VLOOKUP($P$2,Prices!$E$3:$F$17,2,FALSE)*Urban!P64)+(VLOOKUP($Q$2,Prices!$E$3:$F$17,2,FALSE)*Urban!Q64)+(VLOOKUP($R$2,Prices!$E$3:$F$17,2,FALSE)*Urban!R64)+(VLOOKUP($S$2,Prices!$E$3:$F$17,2,FALSE)*Urban!S64)+(VLOOKUP($T$2,Prices!$E$3:$F$17,2,FALSE)*Urban!T64)+(VLOOKUP($U$2,Prices!$E$3:$F$17,2,FALSE)*Urban!U64)+(VLOOKUP($V$2,Prices!$E$3:$F$17,2,FALSE)*Urban!V64)+(VLOOKUP($W$2,Prices!$E$3:$F$17,2,FALSE)*Urban!W64)+(VLOOKUP($X$2,Prices!$E$3:$F$17,2,FALSE)*Urban!X64)+(VLOOKUP($Y$2,Prices!$E$3:$F$17,2,FALSE)*Urban!Y64)+(VLOOKUP($Z$2,Prices!$E$3:$F$17,2,FALSE)*Urban!Z64)+(VLOOKUP($AA$2,Prices!$E$3:$F$17,2,FALSE)*Urban!AA64)+(VLOOKUP($AB$2,Prices!$E$3:$F$17,2,FALSE)*Urban!AB64)+M64 -> 0 | AD64: 0 | AF64: =AD64-AE64 -> 0 | AH64: =AD64+AG64 -> 0 | AI64: =AH64/M64 -> #DIV/0! | AJ64: =AH64/AC64 -> #DIV/0!
A65: 63 | I65: Saidat Omotayo(Iya) | J65: SWR | K65: Ibadan | L65: WCFA000045 | M65: =IFERROR(VLOOKUP($L65,[1]Consolidated!$C$9:$AC$341,27,0),0) -> 48400000 | N65: =IFERROR(VLOOKUP($L65,[1]Consolidated!$C$9:$AC$341,5,0),0) -> 250 | AC65: =(VLOOKUP($O$2,Prices!$E$3:$F$17,2,FALSE)*Urban!O65)+(VLOOKUP($P$2,Prices!$E$3:$F$17,2,FALSE)*Urban!P65)+(VLOOKUP($Q$2,Prices!$E$3:$F$17,2,FALSE)*Urban!Q65)+(VLOOKUP($R$2,Prices!$E$3:$F$17,2,FALSE)*Urban!R65)+(VLOOKUP($S$2,Prices!$E$3:$F$17,2,FALSE)*Urban!S65)+(VLOOKUP($T$2,Prices!$E$3:$F$17,2,FALSE)*Urban!T65)+(VLOOKUP($U$2,Prices!$E$3:$F$17,2,FALSE)*Urban!U65)+(VLOOKUP($V$2,Prices!$E$3:$F$17,2,FALSE)*Urban!V65)+(VLOOKUP($W$2,Prices!$E$3:$F$17,2,FALSE)*Urban!W65)+(VLOOKUP($X$2,Prices!$E$3:$F$17,2,FALSE)*Urban!X65)+(VLOOKUP($Y$2,Prices!$E$3:$F$17,2,FALSE)*Urban!Y65)+(VLOOKUP($Z$2,Prices!$E$3:$F$17,2,FALSE)*Urban!Z65)+(VLOOKUP($AA$2,Prices!$E$3:$F$17,2,FALSE)*Urban!AA65)+(VLOOKUP($AB$2,Prices!$E$3:$F$17,2,FALSE)*Urban!AB65)+M65 -> 48400000 | AD65: 11216313 | AF65: =AD65-AE65 -> 11216313 | AH65: =AD65+AG65 -> 11216313 | AI65: =AH65/M65 -> 0.231742 | AJ65: =AH65/AC65 -> 0.231742
A66: 64 | I66: Omolara Alamu | J66: SWR | K66: Ibadan | L66: WCFA000042 | M66: =IFERROR(VLOOKUP($L66,[1]Consolidated!$C$9:$AC$341,27,0),0) -> 24277500 | N66: =IFERROR(VLOOKUP($L66,[1]Consolidated!$C$9:$AC$341,5,0),0) -> 125 | AC66: =(VLOOKUP($O$2,Prices!$E$3:$F$17,2,FALSE)*Urban!O66)+(VLOOKUP($P$2,Prices!$E$3:$F$17,2,FALSE)*Urban!P66)+(VLOOKUP($Q$2,Prices!$E$3:$F$17,2,FALSE)*Urban!Q66)+(VLOOKUP($R$2,Prices!$E$3:$F$17,2,FALSE)*Urban!R66)+(VLOOKUP($S$2,Prices!$E$3:$F$17,2,FALSE)*Urban!S66)+(VLOOKUP($T$2,Prices!$E$3:$F$17,2,FALSE)*Urban!T66)+(VLOOKUP($U$2,Prices!$E$3:$F$17,2,FALSE)*Urban!U66)+(VLOOKUP($V$2,Prices!$E$3:$F$17,2,FALSE)*Urban!V66)+(VLOOKUP($W$2,Prices!$E$3:$F$17,2,FALSE)*Urban!W66)+(VLOOKUP($X$2,Prices!$E$3:$F$17,2,FALSE)*Urban!X66)+(VLOOKUP($Y$2,Prices!$E$3:$F$17,2,FALSE)*Urban!Y66)+(VLOOKUP($Z$2,Prices!$E$3:$F$17,2,FALSE)*Urban!Z66)+(VLOOKUP($AA$2,Prices!$E$3:$F$17,2,FALSE)*Urban!AA66)+(VLOOKUP($AB$2,Prices!$E$3:$F$17,2,FALSE)*Urban!AB66)+M66 -> 24277500 | AD66: 5626116.4 | AF66: =AD66-AE66 -> 5626116.4 | AH66: =AD66+AG66 -> 5626116.4 | AI66: =AH66/M66 -> 0.231742 | AJ66: =AH66/AC66 -> 0.231742
A67: 65 | I67: Fausat Adetunji | J67: SWR | K67: Ibadan | L67: WCFA000039 | M67: =IFERROR(VLOOKUP($L67,'[2]Top WH -National'!$D$9:$AC$124,26,0),0) -> 61328500 | N67: =IFERROR(VLOOKUP($L67,'[2]Top WH -National'!$D$9:$AC$124,4,0),0) -> 314 | AC67: =(VLOOKUP($O$2,Prices!$E$3:$F$17,2,FALSE)*Urban!O67)+(VLOOKUP($P$2,Prices!$E$3:$F$17,2,FALSE)*Urban!P67)+(VLOOKUP($Q$2,Prices!$E$3:$F$17,2,FALSE)*Urban!Q67)+(VLOOKUP($R$2,Prices!$E$3:$F$17,2,FALSE)*Urban!R67)+(VLOOKUP($S$2,Prices!$E$3:$F$17,2,FALSE)*Urban!S67)+(VLOOKUP($T$2,Prices!$E$3:$F$17,2,FALSE)*Urban!T67)+(VLOOKUP($U$2,Prices!$E$3:$F$17,2,FALSE)*Urban!U67)+(VLOOKUP($V$2,Prices!$E$3:$F$17,2,FALSE)*Urban!V67)+(VLOOKUP($W$2,Prices!$E$3:$F$17,2,FALSE)*Urban!W67)+(VLOOKUP($X$2,Prices!$E$3:$F$17,2,FALSE)*Urban!X67)+(VLOOKUP($Y$2,Prices!$E$3:$F$17,2,FALSE)*Urban!Y67)+(VLOOKUP($Z$2,Prices!$E$3:$F$17,2,FALSE)*Urban!Z67)+(VLOOKUP($AA$2,Prices!$E$3:$F$17,2,FALSE)*Urban!AA67)+(VLOOKUP($AB$2,Prices!$E$3:$F$17,2,FALSE)*Urban!AB67)+M67 -> 61328500 | AD67: 42929280 | AF67: =AD67-AE67 -> 42929280 | AH67: =AD67+AG67 -> 42929280 | AI67: =AH67/M67 -> 0.69998908 | AJ67: =AH67/AC67 -> 0.69998908
A68: 66 | I68: Mama Kemi Oluwalana | J68: SWR | K68: Ibadan | L68: WCFA000034 | M68: =IFERROR(VLOOKUP($L68,[1]Consolidated!$C$9:$AC$341,27,0),0) -> 15122500 | N68: =IFERROR(VLOOKUP($L68,[1]Consolidated!$C$9:$AC$341,5,0),0) -> 80 | AC68: =(VLOOKUP($O$2,Prices!$E$3:$F$17,2,FALSE)*Urban!O68)+(VLOOKUP($P$2,Prices!$E$3:$F$17,2,FALSE)*Urban!P68)+(VLOOKUP($Q$2,Prices!$E$3:$F$17,2,FALSE)*Urban!Q68)+(VLOOKUP($R$2,Prices!$E$3:$F$17,2,FALSE)*Urban!R68)+(VLOOKUP($S$2,Prices!$E$3:$F$17,2,FALSE)*Urban!S68)+(VLOOKUP($T$2,Prices!$E$3:$F$17,2,FALSE)*Urban!T68)+(VLOOKUP($U$2,Prices!$E$3:$F$17,2,FALSE)*Urban!U68)+(VLOOKUP($V$2,Prices!$E$3:$F$17,2,FALSE)*Urban!V68)+(VLOOKUP($W$2,Prices!$E$3:$F$17,2,FALSE)*Urban!W68)+(VLOOKUP($X$2,Prices!$E$3:$F$17,2,FALSE)*Urban!X68)+(VLOOKUP($Y$2,Prices!$E$3:$F$17,2,FALSE)*Urban!Y68)+(VLOOKUP($Z$2,Prices!$E$3:$F$17,2,FALSE)*Urban!Z68)+(VLOOKUP($AA$2,Prices!$E$3:$F$17,2,FALSE)*Urban!AA68)+(VLOOKUP($AB$2,Prices!$E$3:$F$17,2,FALSE)*Urban!AB68)+M68 -> 15122500 | AD68: 3504518.4 | AF68: =AD68-AE68 -> 3504518.4 | AH68: =AD68+AG68 -> 3504518.4 | AI68: =AH68/M68 -> 0.231742 | AJ68: =AH68/AC68 -> 0.231742
A69: 67 | I69: Abdul Ramon Mujidat | J69: SWR | K69: Ibadan | L69: WCFA000027 | M69: =IFERROR(VLOOKUP($L69,'[2]Top WH -National'!$D$9:$AC$124,26,0),0) -> 174169500 | N69: =IFERROR(VLOOKUP($L69,'[2]Top WH -National'!$D$9:$AC$124,4,0),0) -> 820 | AC69: =(VLOOKUP($O$2,Prices!$E$3:$F$17,2,FALSE)*Urban!O69)+(VLOOKUP($P$2,Prices!$E$3:$F$17,2,FALSE)*Urban!P69)+(VLOOKUP($Q$2,Prices!$E$3:$F$17,2,FALSE)*Urban!Q69)+(VLOOKUP($R$2,Prices!$E$3:$F$17,2,FALSE)*Urban!R69)+(VLOOKUP($S$2,Prices!$E$3:$F$17,2,FALSE)*Urban!S69)+(VLOOKUP($T$2,Prices!$E$3:$F$17,2,FALSE)*Urban!T69)+(VLOOKUP($U$2,Prices!$E$3:$F$17,2,FALSE)*Urban!U69)+(VLOOKUP($V$2,Prices!$E$3:$F$17,2,FALSE)*Urban!V69)+(VLOOKUP($W$2,Prices!$E$3:$F$17,2,FALSE)*Urban!W69)+(VLOOKUP($X$2,Prices!$E$3:$F$17,2,FALSE)*Urban!X69)+(VLOOKUP($Y$2,Prices!$E$3:$F$17,2,FALSE)*Urban!Y69)+(VLOOKUP($Z$2,Prices!$E$3:$F$17,2,FALSE)*Urban!Z69)+(VLOOKUP($AA$2,Prices!$E$3:$F$17,2,FALSE)*Urban!AA69)+(VLOOKUP($AB$2,Prices!$E$3:$F$17,2,FALSE)*Urban!AB69)+M69 -> 174169500 | AD69: 94941360 | AF69: =AD69-AE69 -> 94941360 | AH69: =AD69+AG69 -> 94941360 | AI69: =AH69/M69 -> 0.54510899 | AJ69: =AH69/AC69 -> 0.54510899
A70: 68 | I70: Latifat Ajiboye | J70: SWR | K70: Ibadan | L70: WCFA000026 | M70: =IFERROR(VLOOKUP($L70,[1]Consolidated!$C$9:$AC$341,27,0),0) -> 13617500 | N70: =IFERROR(VLOOKUP($L70,[1]Consolidated!$C$9:$AC$341,5,0),0) -> 70 | AC70: =(VLOOKUP($O$2,Prices!$E$3:$F$17,2,FALSE)*Urban!O70)+(VLOOKUP($P$2,Prices!$E$3:$F$17,2,FALSE)*Urban!P70)+(VLOOKUP($Q$2,Prices!$E$3:$F$17,2,FALSE)*Urban!Q70)+(VLOOKUP($R$2,Prices!$E$3:$F$17,2,FALSE)*Urban!R70)+(VLOOKUP($S$2,Prices!$E$3:$F$17,2,FALSE)*Urban!S70)+(VLOOKUP($T$2,Prices!$E$3:$F$17,2,FALSE)*Urban!T70)+(VLOOKUP($U$2,Prices!$E$3:$F$17,2,FALSE)*Urban!U70)+(VLOOKUP($V$2,Prices!$E$3:$F$17,2,FALSE)*Urban!V70)+(VLOOKUP($W$2,Prices!$E$3:$F$17,2,FALSE)*Urban!W70)+(VLOOKUP($X$2,Prices!$E$3:$F$17,2,FALSE)*Urban!X70)+(VLOOKUP($Y$2,Prices!$E$3:$F$17,2,FALSE)*Urban!Y70)+(VLOOKUP($Z$2,Prices!$E$3:$F$17,2,FALSE)*Urban!Z70)+(VLOOKUP($AA$2,Prices!$E$3:$F$17,2,FALSE)*Urban!AA70)+(VLOOKUP($AB$2,Prices!$E$3:$F$17,2,FALSE)*Urban!AB70)+M70 -> 13617500 | AD70: 0 | AF70: =AD70-AE70 -> 0 | AH70: =AD70+AG70 -> 0 | AI70: =AH70/M70 -> 0 | AJ70: =AH70/AC70 -> 0
A71: 69 | I71: Sadiq Sile (iya) | J71: SWR | K71: Ibadan | L71: WCFA000023 | M71: =IFERROR(VLOOKUP($L71,[1]Consolidated!$C$9:$AC$341,27,0),0) -> 0 | N71: 70 | O71: 15 | P71: 2 | Q71: 2 | S71: 25 | V71: 5 | Y71: 27 | Z71: 2 | AB71: 2 | AC71: =(VLOOKUP($O$2,Prices!$E$3:$F$17,2,FALSE)*Urban!O71)+(VLOOKUP($P$2,Prices!$E$3:$F$17,2,FALSE)*Urban!P71)+(VLOOKUP($Q$2,Prices!$E$3:$F$17,2,FALSE)*Urban!Q71)+(VLOOKUP($R$2,Prices!$E$3:$F$17,2,FALSE)*Urban!R71)+(VLOOKUP($S$2,Prices!$E$3:$F$17,2,FALSE)*Urban!S71)+(VLOOKUP($T$2,Prices!$E$3:$F$17,2,FALSE)*Urban!T71)+(VLOOKUP($U$2,Prices!$E$3:$F$17,2,FALSE)*Urban!U71)+(VLOOKUP($V$2,Prices!$E$3:$F$17,2,FALSE)*Urban!V71)+(VLOOKUP($W$2,Prices!$E$3:$F$17,2,FALSE)*Urban!W71)+(VLOOKUP($X$2,Prices!$E$3:$F$17,2,FALSE)*Urban!X71)+(VLOOKUP($Y$2,Prices!$E$3:$F$17,2,FALSE)*Urban!Y71)+(VLOOKUP($Z$2,Prices!$E$3:$F$17,2,FALSE)*Urban!Z71)+(VLOOKUP($AA$2,Prices!$E$3:$F$17,2,FALSE)*Urban!AA71)+(VLOOKUP($AB$2,Prices!$E$3:$F$17,2,FALSE)*Urban!AB71)+M71 -> 16596000 | AD71: 0 | AF71: =AD71-AE71 -> 0 | AG71: 11290300 | AH71: =AD71+AG71 -> 11290300 | AI71: =AH71/M71 -> #DIV/0! | AJ71: =AH71/AC71 -> 0.68030248 | AK71: Customer not targetted initially but has agreed to participate
A72: 70 | I72: Iya Ramon Isiaka | J72: SWR | K72: Ibadan | L72: WCFA000021 | M72: =IFERROR(VLOOKUP($L72,[1]Consolidated!$C$9:$AC$341,27,0),0) -> 34595000 | N72: =IFERROR(VLOOKUP($L72,[1]Consolidated!$C$9:$AC$341,5,0),0) -> 180 | AC72: =(VLOOKUP($O$2,Prices!$E$3:$F$17,2,FALSE)*Urban!O72)+(VLOOKUP($P$2,Prices!$E$3:$F$17,2,FALSE)*Urban!P72)+(VLOOKUP($Q$2,Prices!$E$3:$F$17,2,FALSE)*Urban!Q72)+(VLOOKUP($R$2,Prices!$E$3:$F$17,2,FALSE)*Urban!R72)+(VLOOKUP($S$2,Prices!$E$3:$F$17,2,FALSE)*Urban!S72)+(VLOOKUP($T$2,Prices!$E$3:$F$17,2,FALSE)*Urban!T72)+(VLOOKUP($U$2,Prices!$E$3:$F$17,2,FALSE)*Urban!U72)+(VLOOKUP($V$2,Prices!$E$3:$F$17,2,FALSE)*Urban!V72)+(VLOOKUP($W$2,Prices!$E$3:$F$17,2,FALSE)*Urban!W72)+(VLOOKUP($X$2,Prices!$E$3:$F$17,2,FALSE)*Urban!X72)+(VLOOKUP($Y$2,Prices!$E$3:$F$17,2,FALSE)*Urban!Y72)+(VLOOKUP($Z$2,Prices!$E$3:$F$17,2,FALSE)*Urban!Z72)+(VLOOKUP($AA$2,Prices!$E$3:$F$17,2,FALSE)*Urban!AA72)+(VLOOKUP($AB$2,Prices!$E$3:$F$17,2,FALSE)*Urban!AB72)+M72 -> 34595000 | AD72: 8017114.5 | AF72: =AD72-AE72 -> 8017114.5 | AH72: =AD72+AG72 -> 8017114.5 | AI72: =AH72/M72 -> 0.231742 | AJ72: =AH72/AC72 -> 0.231742
A73: 71 | I73: Anifat Ibikunle | J73: SWR | K73: Ibadan | L73: WCFA000018 | M73: =IFERROR(VLOOKUP($L73,'[2]Top WH -National'!$D$9:$AC$124,26,0),0) -> 177919500 | N73: =IFERROR(VLOOKUP($L73,'[2]Top WH -National'!$D$9:$AC$124,4,0),0) -> 820 | AC73: =(VLOOKUP($O$2,Prices!$E$3:$F$17,2,FALSE)*Urban!O73)+(VLOOKUP($P$2,Prices!$E$3:$F$17,2,FALSE)*Urban!P73)+(VLOOKUP($Q$2,Prices!$E$3:$F$17,2,FALSE)*Urban!Q73)+(VLOOKUP($R$2,Prices!$E$3:$F$17,2,FALSE)*Urban!R73)+(VLOOKUP($S$2,Prices!$E$3:$F$17,2,FALSE)*Urban!S73)+(VLOOKUP($T$2,Prices!$E$3:$F$17,2,FALSE)*Urban!T73)+(VLOOKUP($U$2,Prices!$E$3:$F$17,2,FALSE)*Urban!U73)+(VLOOKUP($V$2,Prices!$E$3:$F$17,2,FALSE)*Urban!V73)+(VLOOKUP($W$2,Prices!$E$3:$F$17,2,FALSE)*Urban!W73)+(VLOOKUP($X$2,Prices!$E$3:$F$17,2,FALSE)*Urban!X73)+(VLOOKUP($Y$2,Prices!$E$3:$F$17,2,FALSE)*Urban!Y73)+(VLOOKUP($Z$2,Prices!$E$3:$F$17,2,FALSE)*Urban!Z73)+(VLOOKUP($AA$2,Prices!$E$3:$F$17,2,FALSE)*Urban!AA73)+(VLOOKUP($AB$2,Prices!$E$3:$F$17,2,FALSE)*Urban!AB73)+M73 -> 177919500 | AD73: 95886180 | AF73: =AD73-AE73 -> 95886180 | AH73: =AD73+AG73 -> 95886180 | AI73: =AH73/M73 -> 0.53893013 | AJ73: =AH73/AC73 -> 0.53893013
A74: 72 | I74: Funmi Alira(Mrs) | J74: SWR | K74: Ibadan | L74: WCFA000008 | M74: =IFERROR(VLOOKUP($L74,[1]Consolidated!$C$9:$AC$341,27,0),0) -> 13617500 | N74: =IFERROR(VLOOKUP($L74,[1]Consolidated!$C$9:$AC$341,5,0),0) -> 70 | AC74: =(VLOOKUP($O$2,Prices!$E$3:$F$17,2,FALSE)*Urban!O74)+(VLOOKUP($P$2,Prices!$E$3:$F$17,2,FALSE)*Urban!P74)+(VLOOKUP($Q$2,Prices!$E$3:$F$17,2,FALSE)*Urban!Q74)+(VLOOKUP($R$2,Prices!$E$3:$F$17,2,FALSE)*Urban!R74)+(VLOOKUP($S$2,Prices!$E$3:$F$17,2,FALSE)*Urban!S74)+(VLOOKUP($T$2,Prices!$E$3:$F$17,2,FALSE)*Urban!T74)+(VLOOKUP($U$2,Prices!$E$3:$F$17,2,FALSE)*Urban!U74)+(VLOOKUP($V$2,Prices!$E$3:$F$17,2,FALSE)*Urban!V74)+(VLOOKUP($W$2,Prices!$E$3:$F$17,2,FALSE)*Urban!W74)+(VLOOKUP($X$2,Prices!$E$3:$F$17,2,FALSE)*Urban!X74)+(VLOOKUP($Y$2,Prices!$E$3:$F$17,2,FALSE)*Urban!Y74)+(VLOOKUP($Z$2,Prices!$E$3:$F$17,2,FALSE)*Urban!Z74)+(VLOOKUP($AA$2,Prices!$E$3:$F$17,2,FALSE)*Urban!AA74)+(VLOOKUP($AB$2,Prices!$E$3:$F$17,2,FALSE)*Urban!AB74)+M74 -> 13617500 | AD74: 3155746.7 | AF74: =AD74-AE74 -> 3155746.7 | AH74: =AD74+AG74 -> 3155746.7 | AI74: =AH74/M74 -> 0.231742 | AJ74: =AH74/AC74 -> 0.231742
A75: 73 | I75: Twins Sister | J75: SWR | K75: Ibadan | L75: WCFA000003 | M75: =IFERROR(VLOOKUP($L75,[1]Consolidated!$C$9:$AC$341,27,0),0) -> 26550500 | N75: =IFERROR(VLOOKUP($L75,[1]Consolidated!$C$9:$AC$341,5,0),0) -> 140 | AC75: =(VLOOKUP($O$2,Prices!$E$3:$F$17,2,FALSE)*Urban!O75)+(VLOOKUP($P$2,Prices!$E$3:$F$17,2,FALSE)*Urban!P75)+(VLOOKUP($Q$2,Prices!$E$3:$F$17,2,FALSE)*Urban!Q75)+(VLOOKUP($R$2,Prices!$E$3:$F$17,2,FALSE)*Urban!R75)+(VLOOKUP($S$2,Prices!$E$3:$F$17,2,FALSE)*Urban!S75)+(VLOOKUP($T$2,Prices!$E$3:$F$17,2,FALSE)*Urban!T75)+(VLOOKUP($U$2,Prices!$E$3:$F$17,2,FALSE)*Urban!U75)+(VLOOKUP($V$2,Prices!$E$3:$F$17,2,FALSE)*Urban!V75)+(VLOOKUP($W$2,Prices!$E$3:$F$17,2,FALSE)*Urban!W75)+(VLOOKUP($X$2,Prices!$E$3:$F$17,2,FALSE)*Urban!X75)+(VLOOKUP($Y$2,Prices!$E$3:$F$17,2,FALSE)*Urban!Y75)+(VLOOKUP($Z$2,Prices!$E$3:$F$17,2,FALSE)*Urban!Z75)+(VLOOKUP($AA$2,Prices!$E$3:$F$17,2,FALSE)*Urban!AA75)+(VLOOKUP($AB$2,Prices!$E$3:$F$17,2,FALSE)*Urban!AB75)+M75 -> 26550500 | AD75: 6152865.9 | AF75: =AD75-AE75 -> 6152865.9 | AH75: =AD75+AG75 -> 6152865.9 | AI75: =AH75/M75 -> 0.231742 | AJ75: =AH75/AC75 -> 0.231742
A76: 74 | I76: Mrs Dada Kolapo | J76: SWR | K76: Ibadan | L76: SWC0914 | M76: =IFERROR(VLOOKUP($L76,[1]Consolidated!$C$9:$AC$341,27,0),0) -> 0 | N76: 70 | O76: 15 | P76: 2 | Q76: 2 | S76: 25 | V76: 5 | Y76: 27 | Z76: 2 | AB76: 2 | AC76: =(VLOOKUP($O$2,Prices!$E$3:$F$17,2,FALSE)*Urban!O76)+(VLOOKUP($P$2,Prices!$E$3:$F$17,2,FALSE)*Urban!P76)+(VLOOKUP($Q$2,Prices!$E$3:$F$17,2,FALSE)*Urban!Q76)+(VLOOKUP($R$2,Prices!$E$3:$F$17,2,FALSE)*Urban!R76)+(VLOOKUP($S$2,Prices!$E$3:$F$17,2,FALSE)*Urban!S76)+(VLOOKUP($T$2,Prices!$E$3:$F$17,2,FALSE)*Urban!T76)+(VLOOKUP($U$2,Prices!$E$3:$F$17,2,FALSE)*Urban!U76)+(VLOOKUP($V$2,Prices!$E$3:$F$17,2,FALSE)*Urban!V76)+(VLOOKUP($W$2,Prices!$E$3:$F$17,2,FALSE)*Urban!W76)+(VLOOKUP($X$2,Prices!$E$3:$F$17,2,FALSE)*Urban!X76)+(VLOOKUP($Y$2,Prices!$E$3:$F$17,2,FALSE)*Urban!Y76)+(VLOOKUP($Z$2,Prices!$E$3:$F$17,2,FALSE)*Urban!Z76)+(VLOOKUP($AA$2,Prices!$E$3:$F$17,2,FALSE)*Urban!AA76)+(VLOOKUP($AB$2,Prices!$E$3:$F$17,2,FALSE)*Urban!AB76)+M76 -> 16596000 | AD76: 0 | AF76: =AD76-AE76 -> 0 | AG76: 11359250 | AH76: =AD76+AG76 -> 11359250 | AI76: =AH76/M76 -> #DIV/0! | AJ76: =AH76/AC76 -> 0.6844571 | AK76: Additional credit required for extra volume
A77: 75 | I77: Tajudeen Opeyemi (Iya Nofi) | J77: SWR | K77: Ilorin | L77: WCFA000672 | M77: =IFERROR(VLOOKUP($L77,[1]Consolidated!$C$9:$AC$341,27,0),0) -> 32579000 | N77: =IFERROR(VLOOKUP($L77,[1]Consolidated!$C$9:$AC$341,5,0),0) -> 150 | AC77: =(VLOOKUP($O$2,Prices!$E$3:$F$17,2,FALSE)*Urban!O77)+(VLOOKUP($P$2,Prices!$E$3:$F$17,2,FALSE)*Urban!P77)+(VLOOKUP($Q$2,Prices!$E$3:$F$17,2,FALSE)*Urban!Q77)+(VLOOKUP($R$2,Prices!$E$3:$F$17,2,FALSE)*Urban!R77)+(VLOOKUP($S$2,Prices!$E$3:$F$17,2,FALSE)*Urban!S77)+(VLOOKUP($T$2,Prices!$E$3:$F$17,2,FALSE)*Urban!T77)+(VLOOKUP($U$2,Prices!$E$3:$F$17,2,FALSE)*Urban!U77)+(VLOOKUP($V$2,Prices!$E$3:$F$17,2,FALSE)*Urban!V77)+(VLOOKUP($W$2,Prices!$E$3:$F$17,2,FALSE)*Urban!W77)+(VLOOKUP($X$2,Prices!$E$3:$F$17,2,FALSE)*Urban!X77)+(VLOOKUP($Y$2,Prices!$E$3:$F$17,2,FALSE)*Urban!Y77)+(VLOOKUP($Z$2,Prices!$E$3:$F$17,2,FALSE)*Urban!Z77)+(VLOOKUP($AA$2,Prices!$E$3:$F$17,2,FALSE)*Urban!AA77)+(VLOOKUP($AB$2,Prices!$E$3:$F$17,2,FALSE)*Urban!AB77)+M77 -> 32579000 | AD77: 2300000 | AF77: =AD77-AE77 -> 2300000 | AH77: =AD77+AG77 -> 2300000 | AI77: =AH77/M77 -> 0.070597624 | AJ77: =AH77/AC77 -> 0.070597624
A78: 76 | I78: Fausat Najeem | J78: SWR | K78: Ilorin | L78: WCFA000116 | M78: =IFERROR(VLOOKUP($L78,[1]Consolidated!$C$9:$AC$341,27,0),0) -> 20426000 | N78: =IFERROR(VLOOKUP($L78,[1]Consolidated!$C$9:$AC$341,5,0),0) -> 90 | AC78: =(VLOOKUP($O$2,Prices!$E$3:$F$17,2,FALSE)*Urban!O78)+(VLOOKUP($P$2,Prices!$E$3:$F$17,2,FALSE)*Urban!P78)+(VLOOKUP($Q$2,Prices!$E$3:$F$17,2,FALSE)*Urban!Q78)+(VLOOKUP($R$2,Prices!$E$3:$F$17,2,FALSE)*Urban!R78)+(VLOOKUP($S$2,Prices!$E$3:$F$17,2,FALSE)*Urban!S78)+(VLOOKUP($T$2,Prices!$E$3:$F$17,2,FALSE)*Urban!T78)+(VLOOKUP($U$2,Prices!$E$3:$F$17,2,FALSE)*Urban!U78)+(VLOOKUP($V$2,Prices!$E$3:$F$17,2,FALSE)*Urban!V78)+(VLOOKUP($W$2,Prices!$E$3:$F$17,2,FALSE)*Urban!W78)+(VLOOKUP($X$2,Prices!$E$3:$F$17,2,FALSE)*Urban!X78)+(VLOOKUP($Y$2,Prices!$E$3:$F$17,2,FALSE)*Urban!Y78)+(VLOOKUP($Z$2,Prices!$E$3:$F$17,2,FALSE)*Urban!Z78)+(VLOOKUP($AA$2,Prices!$E$3:$F$17,2,FALSE)*Urban!AA78)+(VLOOKUP($AB$2,Prices!$E$3:$F$17,2,FALSE)*Urban!AB78)+M78 -> 20426000 | AD78: 4600000 | AF78: =AD78-AE78 -> 4600000 | AH78: =AD78+AG78 -> 4600000 | AI78: =AH78/M78 -> 0.22520317 | AJ78: =AH78/AC78 -> 0.22520317
A79: 77 | I79: Zino Stores | J79: SWR | K79: Ilorin | L79: SWC1886 | M79: =IFERROR(VLOOKUP($L79,[1]Consolidated!$C$9:$AC$341,27,0),0) -> 15532500 | N79: =IFERROR(VLOOKUP($L79,[1]Consolidated!$C$9:$AC$341,5,0),0) -> 70 | AC79: =(VLOOKUP($O$2,Prices!$E$3:$F$17,2,FALSE)*Urban!O79)+(VLOOKUP($P$2,Prices!$E$3:$F$17,2,FALSE)*Urban!P79)+(VLOOKUP($Q$2,Prices!$E$3:$F$17,2,FALSE)*Urban!Q79)+(VLOOKUP($R$2,Prices!$E$3:$F$17,2,FALSE)*Urban!R79)+(VLOOKUP($S$2,Prices!$E$3:$F$17,2,FALSE)*Urban!S79)+(VLOOKUP($T$2,Prices!$E$3:$F$17,2,FALSE)*Urban!T79)+(VLOOKUP($U$2,Prices!$E$3:$F$17,2,FALSE)*Urban!U79)+(VLOOKUP($V$2,Prices!$E$3:$F$17,2,FALSE)*Urban!V79)+(VLOOKUP($W$2,Prices!$E$3:$F$17,2,FALSE)*Urban!W79)+(VLOOKUP($X$2,Prices!$E$3:$F$17,2,FALSE)*Urban!X79)+(VLOOKUP($Y$2,Prices!$E$3:$F$17,2,FALSE)*Urban!Y79)+(VLOOKUP($Z$2,Prices!$E$3:$F$17,2,FALSE)*Urban!Z79)+(VLOOKUP($AA$2,Prices!$E$3:$F$17,2,FALSE)*Urban!AA79)+(VLOOKUP($AB$2,Prices!$E$3:$F$17,2,FALSE)*Urban!AB79)+M79 -> 15532500 | AD79: 4600000 | AF79: =AD79-AE79 -> 4600000 | AH79: =AD79+AG79 -> 4600000 | AI79: =AH79/M79 -> 0.29615323 | AJ79: =AH79/AC79 -> 0.29615323
A80: 78 | I80: Mrs Balikis Oseni (Iya Malik) | J80: SWR | K80: Ilorin | L80: SWC0934 | M80: =IFERROR(VLOOKUP($L80,[1]Consolidated!$C$9:$AC$341,27,0),0) -> 26717500 | N80: =IFERROR(VLOOKUP($L80,[1]Consolidated!$C$9:$AC$341,5,0),0) -> 120 | AC80: =(VLOOKUP($O$2,Prices!$E$3:$F$17,2,FALSE)*Urban!O80)+(VLOOKUP($P$2,Prices!$E$3:$F$17,2,FALSE)*Urban!P80)+(VLOOKUP($Q$2,Prices!$E$3:$F$17,2,FALSE)*Urban!Q80)+(VLOOKUP($R$2,Prices!$E$3:$F$17,2,FALSE)*Urban!R80)+(VLOOKUP($S$2,Prices!$E$3:$F$17,2,FALSE)*Urban!S80)+(VLOOKUP($T$2,Prices!$E$3:$F$17,2,FALSE)*Urban!T80)+(VLOOKUP($U$2,Prices!$E$3:$F$17,2,FALSE)*Urban!U80)+(VLOOKUP($V$2,Prices!$E$3:$F$17,2,FALSE)*Urban!V80)+(VLOOKUP($W$2,Prices!$E$3:$F$17,2,FALSE)*Urban!W80)+(VLOOKUP($X$2,Prices!$E$3:$F$17,2,FALSE)*Urban!X80)+(VLOOKUP($Y$2,Prices!$E$3:$F$17,2,FALSE)*Urban!Y80)+(VLOOKUP($Z$2,Prices!$E$3:$F$17,2,FALSE)*Urban!Z80)+(VLOOKUP($AA$2,Prices!$E$3:$F$17,2,FALSE)*Urban!AA80)+(VLOOKUP($AB$2,Prices!$E$3:$F$17,2,FALSE)*Urban!AB80)+M80 -> 26717500 | AD80: 4600000 | AF80: =AD80-AE80 -> 4600000 | AH80: =AD80+AG80 -> 4600000 | AI80: =AH80/M80 -> 0.1721718 | AJ80: =AH80/AC80 -> 0.1721718
A81: 79 | I81: Arewa Toyin O. | J81: SWR | K81: Ilorin | L81: SWC0009 | M81: =IFERROR(VLOOKUP($L81,[1]Consolidated!$C$9:$AC$341,27,0),0) -> 0 | N81: =IFERROR(VLOOKUP($L81,[1]Consolidated!$C$9:$AC$341,5,0),0) -> 0 | AC81: =(VLOOKUP($O$2,Prices!$E$3:$F$17,2,FALSE)*Urban!O81)+(VLOOKUP($P$2,Prices!$E$3:$F$17,2,FALSE)*Urban!P81)+(VLOOKUP($Q$2,Prices!$E$3:$F$17,2,FALSE)*Urban!Q81)+(VLOOKUP($R$2,Prices!$E$3:$F$17,2,FALSE)*Urban!R81)+(VLOOKUP($S$2,Prices!$E$3:$F$17,2,FALSE)*Urban!S81)+(VLOOKUP($T$2,Prices!$E$3:$F$17,2,FALSE)*Urban!T81)+(VLOOKUP($U$2,Prices!$E$3:$F$17,2,FALSE)*Urban!U81)+(VLOOKUP($V$2,Prices!$E$3:$F$17,2,FALSE)*Urban!V81)+(VLOOKUP($W$2,Prices!$E$3:$F$17,2,FALSE)*Urban!W81)+(VLOOKUP($X$2,Prices!$E$3:$F$17,2,FALSE)*Urban!X81)+(VLOOKUP($Y$2,Prices!$E$3:$F$17,2,FALSE)*Urban!Y81)+(VLOOKUP($Z$2,Prices!$E$3:$F$17,2,FALSE)*Urban!Z81)+(VLOOKUP($AA$2,Prices!$E$3:$F$17,2,FALSE)*Urban!AA81)+(VLOOKUP($AB$2,Prices!$E$3:$F$17,2,FALSE)*Urban!AB81)+M81 -> 0 | AD81: 0 | AF81: =AD81-AE81 -> 0 | AH81: =AD81+AG81 -> 0 | AI81: =AH81/M81 -> #DIV/0! | AJ81: =AH81/AC81 -> #DIV/0!
A82: 80 | I82: Alh Hamsat Sabitiyu | J82: SWR | K82: Ilorin | L82: WCFA000113 | M82: =IFERROR(VLOOKUP($L82,[1]Consolidated!$C$9:$AC$341,27,0),0) -> 18080000 | N82: =IFERROR(VLOOKUP($L82,[1]Consolidated!$C$9:$AC$341,5,0),0) -> 80 | AC82: =(VLOOKUP($O$2,Prices!$E$3:$F$17,2,FALSE)*Urban!O82)+(VLOOKUP($P$2,Prices!$E$3:$F$17,2,FALSE)*Urban!P82)+(VLOOKUP($Q$2,Prices!$E$3:$F$17,2,FALSE)*Urban!Q82)+(VLOOKUP($R$2,Prices!$E$3:$F$17,2,FALSE)*Urban!R82)+(VLOOKUP($S$2,Prices!$E$3:$F$17,2,FALSE)*Urban!S82)+(VLOOKUP($T$2,Prices!$E$3:$F$17,2,FALSE)*Urban!T82)+(VLOOKUP($U$2,Prices!$E$3:$F$17,2,FALSE)*Urban!U82)+(VLOOKUP($V$2,Prices!$E$3:$F$17,2,FALSE)*Urban!V82)+(VLOOKUP($W$2,Prices!$E$3:$F$17,2,FALSE)*Urban!W82)+(VLOOKUP($X$2,Prices!$E$3:$F$17,2,FALSE)*Urban!X82)+(VLOOKUP($Y$2,Prices!$E$3:$F$17,2,FALSE)*Urban!Y82)+(VLOOKUP($Z$2,Prices!$E$3:$F$17,2,FALSE)*Urban!Z82)+(VLOOKUP($AA$2,Prices!$E$3:$F$17,2,FALSE)*Urban!AA82)+(VLOOKUP($AB$2,Prices!$E$3:$F$17,2,FALSE)*Urban!AB82)+M82 -> 18080000 | AD82: 4600000 | AF82: =AD82-AE82 -> 4600000 | AH82: =AD82+AG82 -> 4600000 | AI82: =AH82/M82 -> 0.25442478 | AJ82: =AH82/AC82 -> 0.25442478
A83: 81 | I83: Iya Sadiat | J83: SWR | K83: Ilorin | L83: WCFA000102 | M83: =IFERROR(VLOOKUP($L83,'[2]Top WH -National'!$D$9:$AC$124,26,0),0) -> 80613000 | N83: =IFERROR(VLOOKUP($L83,'[2]Top WH -National'!$D$9:$AC$124,4,0),0) -> 450 | AC83: =(VLOOKUP($O$2,Prices!$E$3:$F$17,2,FALSE)*Urban!O83)+(VLOOKUP($P$2,Prices!$E$3:$F$17,2,FALSE)*Urban!P83)+(VLOOKUP($Q$2,Prices!$E$3:$F$17,2,FALSE)*Urban!Q83)+(VLOOKUP($R$2,Prices!$E$3:$F$17,2,FALSE)*Urban!R83)+(VLOOKUP($S$2,Prices!$E$3:$F$17,2,FALSE)*Urban!S83)+(VLOOKUP($T$2,Prices!$E$3:$F$17,2,FALSE)*Urban!T83)+(VLOOKUP($U$2,Prices!$E$3:$F$17,2,FALSE)*Urban!U83)+(VLOOKUP($V$2,Prices!$E$3:$F$17,2,FALSE)*Urban!V83)+(VLOOKUP($W$2,Prices!$E$3:$F$17,2,FALSE)*Urban!W83)+(VLOOKUP($X$2,Prices!$E$3:$F$17,2,FALSE)*Urban!X83)+(VLOOKUP($Y$2,Prices!$E$3:$F$17,2,FALSE)*Urban!Y83)+(VLOOKUP($Z$2,Prices!$E$3:$F$17,2,FALSE)*Urban!Z83)+(VLOOKUP($AA$2,Prices!$E$3:$F$17,2,FALSE)*Urban!AA83)+(VLOOKUP($AB$2,Prices!$E$3:$F$17,2,FALSE)*Urban!AB83)+M83 -> 80613000 | AD83: 60400000 | AF83: =AD83-AE83 -> 60400000 | AH83: =AD83+AG83 -> 60400000 | AI83: =AH83/M83 -> 0.7492588 | AJ83: =AH83/AC83 -> 0.7492588
A84: 82 | I84: Rukayat Folorunsho | J84: SWR | K84: Ilorin | L84: WCFA000098 | M84: =IFERROR(VLOOKUP($L84,[1]Consolidated!$C$9:$AC$341,27,0),0) -> 37578000 | N84: =IFERROR(VLOOKUP($L84,[1]Consolidated!$C$9:$AC$341,5,0),0) -> 171 | O84: 10 | AC84: =(VLOOKUP($O$2,Prices!$E$3:$F$17,2,FALSE)*Urban!O84)+(VLOOKUP($P$2,Prices!$E$3:$F$17,2,FALSE)*Urban!P84)+(VLOOKUP($Q$2,Prices!$E$3:$F$17,2,FALSE)*Urban!Q84)+(VLOOKUP($R$2,Prices!$E$3:$F$17,2,FALSE)*Urban!R84)+(VLOOKUP($S$2,Prices!$E$3:$F$17,2,FALSE)*Urban!S84)+(VLOOKUP($T$2,Prices!$E$3:$F$17,2,FALSE)*Urban!T84)+(VLOOKUP($U$2,Prices!$E$3:$F$17,2,FALSE)*Urban!U84)+(VLOOKUP($V$2,Prices!$E$3:$F$17,2,FALSE)*Urban!V84)+(VLOOKUP($W$2,Prices!$E$3:$F$17,2,FALSE)*Urban!W84)+(VLOOKUP($X$2,Prices!$E$3:$F$17,2,FALSE)*Urban!X84)+(VLOOKUP($Y$2,Prices!$E$3:$F$17,2,FALSE)*Urban!Y84)+(VLOOKUP($Z$2,Prices!$E$3:$F$17,2,FALSE)*Urban!Z84)+(VLOOKUP($AA$2,Prices!$E$3:$F$17,2,FALSE)*Urban!AA84)+(VLOOKUP($AB$2,Prices!$E$3:$F$17,2,FALSE)*Urban!AB84)+M84 -> 40188000 | AD84: 23000000 | AF84: =AD84-AE84 -> 23000000 | AG84: 8680000 | AH84: =AD84+AG84 -> 31680000 | AI84: =AH84/M84 -> 0.84304646 | AJ84: =AH84/AC84 -> 0.78829501 | AK84: Additional credit required for extra volume
A85: 83 | I85: Kikelomo Iman | J85: SWR | K85: Ilorin | L85: WCFA000097 | M85: =IFERROR(VLOOKUP($L85,[1]Consolidated!$C$9:$AC$341,27,0),0) -> 37504500 | N85: =IFERROR(VLOOKUP($L85,[1]Consolidated!$C$9:$AC$341,5,0),0) -> 180 | AC85: =(VLOOKUP($O$2,Prices!$E$3:$F$17,2,FALSE)*Urban!O85)+(VLOOKUP($P$2,Prices!$E$3:$F$17,2,FALSE)*Urban!P85)+(VLOOKUP($Q$2,Prices!$E$3:$F$17,2,FALSE)*Urban!Q85)+(VLOOKUP($R$2,Prices!$E$3:$F$17,2,FALSE)*Urban!R85)+(VLOOKUP($S$2,Prices!$E$3:$F$17,2,FALSE)*Urban!S85)+(VLOOKUP($T$2,Prices!$E$3:$F$17,2,FALSE)*Urban!T85)+(VLOOKUP($U$2,Prices!$E$3:$F$17,2,FALSE)*Urban!U85)+(VLOOKUP($V$2,Prices!$E$3:$F$17,2,FALSE)*Urban!V85)+(VLOOKUP($W$2,Prices!$E$3:$F$17,2,FALSE)*Urban!W85)+(VLOOKUP($X$2,Prices!$E$3:$F$17,2,FALSE)*Urban!X85)+(VLOOKUP($Y$2,Prices!$E$3:$F$17,2,FALSE)*Urban!Y85)+(VLOOKUP($Z$2,Prices!$E$3:$F$17,2,FALSE)*Urban!Z85)+(VLOOKUP($AA$2,Prices!$E$3:$F$17,2,FALSE)*Urban!AA85)+(VLOOKUP($AB$2,Prices!$E$3:$F$17,2,FALSE)*Urban!AB85)+M85 -> 37504500 | AD85: 6900000 | AF85: =AD85-AE85 -> 6900000 | AH85: =AD85+AG85 -> 6900000 | AI85: =AH85/M85 -> 0.18397792 | AJ85: =AH85/AC85 -> 0.18397792
A86: 84 | I86: Salimat Elejo | J86: SWR | K86: Ilorin | L86: WCFA000096 | M86: =IFERROR(VLOOKUP($L86,[1]Consolidated!$C$9:$AC$341,27,0),0) -> 15712000 | N86: =IFERROR(VLOOKUP($L86,[1]Consolidated!$C$9:$AC$341,5,0),0) -> 75 | AC86: =(VLOOKUP($O$2,Prices!$E$3:$F$17,2,FALSE)*Urban!O86)+(VLOOKUP($P$2,Prices!$E$3:$F$17,2,FALSE)*Urban!P86)+(VLOOKUP($Q$2,Prices!$E$3:$F$17,2,FALSE)*Urban!Q86)+(VLOOKUP($R$2,Prices!$E$3:$F$17,2,FALSE)*Urban!R86)+(VLOOKUP($S$2,Prices!$E$3:$F$17,2,FALSE)*Urban!S86)+(VLOOKUP($T$2,Prices!$E$3:$F$17,2,FALSE)*Urban!T86)+(VLOOKUP($U$2,Prices!$E$3:$F$17,2,FALSE)*Urban!U86)+(VLOOKUP($V$2,Prices!$E$3:$F$17,2,FALSE)*Urban!V86)+(VLOOKUP($W$2,Prices!$E$3:$F$17,2,FALSE)*Urban!W86)+(VLOOKUP($X$2,Prices!$E$3:$F$17,2,FALSE)*Urban!X86)+(VLOOKUP($Y$2,Prices!$E$3:$F$17,2,FALSE)*Urban!Y86)+(VLOOKUP($Z$2,Prices!$E$3:$F$17,2,FALSE)*Urban!Z86)+(VLOOKUP($AA$2,Prices!$E$3:$F$17,2,FALSE)*Urban!AA86)+(VLOOKUP($AB$2,Prices!$E$3:$F$17,2,FALSE)*Urban!AB86)+M86 -> 15712000 | AD86: 4600000 | AF86: =AD86-AE86 -> 4600000 | AH86: =AD86+AG86 -> 4600000 | AI86: =AH86/M86 -> 0.29276986 | AJ86: =AH86/AC86 -> 0.29276986
A87: 85 | I87: Mumini Onikepe | J87: SWR | K87: Ilorin | L87: WCFA000091 | M87: =IFERROR(VLOOKUP($L87,[1]Consolidated!$C$9:$AC$341,27,0),0) -> 37468000 | N87: =IFERROR(VLOOKUP($L87,[1]Consolidated!$C$9:$AC$341,5,0),0) -> 170 | AC87: =(VLOOKUP($O$2,Prices!$E$3:$F$17,2,FALSE)*Urban!O87)+(VLOOKUP($P$2,Prices!$E$3:$F$17,2,FALSE)*Urban!P87)+(VLOOKUP($Q$2,Prices!$E$3:$F$17,2,FALSE)*Urban!Q87)+(VLOOKUP($R$2,Prices!$E$3:$F$17,2,FALSE)*Urban!R87)+(VLOOKUP($S$2,Prices!$E$3:$F$17,2,FALSE)*Urban!S87)+(VLOOKUP($T$2,Prices!$E$3:$F$17,2,FALSE)*Urban!T87)+(VLOOKUP($U$2,Prices!$E$3:$F$17,2,FALSE)*Urban!U87)+(VLOOKUP($V$2,Prices!$E$3:$F$17,2,FALSE)*Urban!V87)+(VLOOKUP($W$2,Prices!$E$3:$F$17,2,FALSE)*Urban!W87)+(VLOOKUP($X$2,Prices!$E$3:$F$17,2,FALSE)*Urban!X87)+(VLOOKUP($Y$2,Prices!$E$3:$F$17,2,FALSE)*Urban!Y87)+(VLOOKUP($Z$2,Prices!$E$3:$F$17,2,FALSE)*Urban!Z87)+(VLOOKUP($AA$2,Prices!$E$3:$F$17,2,FALSE)*Urban!AA87)+(VLOOKUP($AB$2,Prices!$E$3:$F$17,2,FALSE)*Urban!AB87)+M87 -> 37468000 | AD87: 6900000 | AF87: =AD87-AE87 -> 6900000 | AH87: =AD87+AG87 -> 6900000 | AI87: =AH87/M87 -> 0.18415715 | AJ87: =AH87/AC87 -> 0.18415715
A88: 86 | I88: Musili Sanni Ramota | J88: SWR | K88: Ilorin | L88: WCFA000090 | M88: =IFERROR(VLOOKUP($L88,[1]Consolidated!$C$9:$AC$341,27,0),0) -> 25294500 | N88: =IFERROR(VLOOKUP($L88,[1]Consolidated!$C$9:$AC$341,5,0),0) -> 120 | O88: 10 | AC88: =(VLOOKUP($O$2,Prices!$E$3:$F$17,2,FALSE)*Urban!O88)+(VLOOKUP($P$2,Prices!$E$3:$F$17,2,FALSE)*Urban!P88)+(VLOOKUP($Q$2,Prices!$E$3:$F$17,2,FALSE)*Urban!Q88)+(VLOOKUP($R$2,Prices!$E$3:$F$17,2,FALSE)*Urban!R88)+(VLOOKUP($S$2,Prices!$E$3:$F$17,2,FALSE)*Urban!S88)+(VLOOKUP($T$2,Prices!$E$3:$F$17,2,FALSE)*Urban!T88)+(VLOOKUP($U$2,Prices!$E$3:$F$17,2,FALSE)*Urban!U88)+(VLOOKUP($V$2,Prices!$E$3:$F$17,2,FALSE)*Urban!V88)+(VLOOKUP($W$2,Prices!$E$3:$F$17,2,FALSE)*Urban!W88)+(VLOOKUP($X$2,Prices!$E$3:$F$17,2,FALSE)*Urban!X88)+(VLOOKUP($Y$2,Prices!$E$3:$F$17,2,FALSE)*Urban!Y88)+(VLOOKUP($Z$2,Prices!$E$3:$F$17,2,FALSE)*Urban!Z88)+(VLOOKUP($AA$2,Prices!$E$3:$F$17,2,FALSE)*Urban!AA88)+(VLOOKUP($AB$2,Prices!$E$3:$F$17,2,FALSE)*Urban!AB88)+M88 -> 27904500 | AD88: 19600000 | AF88: =AD88-AE88 -> 19600000 | AG88: 1880000 | AH88: =AD88+AG88 -> 21480000 | AI88: =AH88/M88 -> 0.84919647 | AJ88: =AH88/AC88 -> 0.76976832 | AK88: Additional credit required for extra volume
A89: 87 | I89: Alfa Yahaya | J89: SWR | K89: Ilorin | L89: WCFA000088 | M89: =IFERROR(VLOOKUP($L89,'[2]Top WH -National'!$D$9:$AC$124,26,0),0) -> 52351500 | N89: =IFERROR(VLOOKUP($L89,'[2]Top WH -National'!$D$9:$AC$124,4,0),0) -> 299 | AC89: =(VLOOKUP($O$2,Prices!$E$3:$F$17,2,FALSE)*Urban!O89)+(VLOOKUP($P$2,Prices!$E$3:$F$17,2,FALSE)*Urban!P89)+(VLOOKUP($Q$2,Prices!$E$3:$F$17,2,FALSE)*Urban!Q89)+(VLOOKUP($R$2,Prices!$E$3:$F$17,2,FALSE)*Urban!R89)+(VLOOKUP($S$2,Prices!$E$3:$F$17,2,FALSE)*Urban!S89)+(VLOOKUP($T$2,Prices!$E$3:$F$17,2,FALSE)*Urban!T89)+(VLOOKUP($U$2,Prices!$E$3:$F$17,2,FALSE)*Urban!U89)+(VLOOKUP($V$2,Prices!$E$3:$F$17,2,FALSE)*Urban!V89)+(VLOOKUP($W$2,Prices!$E$3:$F$17,2,FALSE)*Urban!W89)+(VLOOKUP($X$2,Prices!$E$3:$F$17,2,FALSE)*Urban!X89)+(VLOOKUP($Y$2,Prices!$E$3:$F$17,2,FALSE)*Urban!Y89)+(VLOOKUP($Z$2,Prices!$E$3:$F$17,2,FALSE)*Urban!Z89)+(VLOOKUP($AA$2,Prices!$E$3:$F$17,2,FALSE)*Urban!AA89)+(VLOOKUP($AB$2,Prices!$E$3:$F$17,2,FALSE)*Urban!AB89)+M89 -> 52351500 | AD89: 20700000 | AF89: =AD89-AE89 -> 20700000 | AH89: =AD89+AG89 -> 20700000 | AI89: =AH89/M89 -> 0.39540414 | AJ89: =AH89/AC89 -> 0.39540414
A90: 88 | I90: Alhaja Oniwiridi | J90: SWR | K90: Ilorin | L90: SWC1039 | M90: =IFERROR(VLOOKUP($L90,[1]Consolidated!$C$9:$AC$341,27,0),0) -> 15477000 | N90: =IFERROR(VLOOKUP($L90,[1]Consolidated!$C$9:$AC$341,5,0),0) -> 70 | AC90: =(VLOOKUP($O$2,Prices!$E$3:$F$17,2,FALSE)*Urban!O90)+(VLOOKUP($P$2,Prices!$E$3:$F$17,2,FALSE)*Urban!P90)+(VLOOKUP($Q$2,Prices!$E$3:$F$17,2,FALSE)*Urban!Q90)+(VLOOKUP($R$2,Prices!$E$3:$F$17,2,FALSE)*Urban!R90)+(VLOOKUP($S$2,Prices!$E$3:$F$17,2,FALSE)*Urban!S90)+(VLOOKUP($T$2,Prices!$E$3:$F$17,2,FALSE)*Urban!T90)+(VLOOKUP($U$2,Prices!$E$3:$F$17,2,FALSE)*Urban!U90)+(VLOOKUP($V$2,Prices!$E$3:$F$17,2,FALSE)*Urban!V90)+(VLOOKUP($W$2,Prices!$E$3:$F$17,2,FALSE)*Urban!W90)+(VLOOKUP($X$2,Prices!$E$3:$F$17,2,FALSE)*Urban!X90)+(VLOOKUP($Y$2,Prices!$E$3:$F$17,2,FALSE)*Urban!Y90)+(VLOOKUP($Z$2,Prices!$E$3:$F$17,2,FALSE)*Urban!Z90)+(VLOOKUP($AA$2,Prices!$E$3:$F$17,2,FALSE)*Urban!AA90)+(VLOOKUP($AB$2,Prices!$E$3:$F$17,2,FALSE)*Urban!AB90)+M90 -> 15477000 | AD90: 0 | AF90: =AD90-AE90 -> 0 | AH90: =AD90+AG90 -> 0 | AI90: =AH90/M90 -> 0 | AJ90: =AH90/AC90 -> 0
A91: 89 | I91: Odofin Adekunle Global Limited | J91: SWR | K91: Ilorin | L91: SWC3226 | M91: =IFERROR(VLOOKUP($L91,[1]Consolidated!$C$9:$AC$341,27,0),0) -> 17050000 | N91: =IFERROR(VLOOKUP($L91,[1]Consolidated!$C$9:$AC$341,5,0),0) -> 80 | AC91: =(VLOOKUP($O$2,Prices!$E$3:$F$17,2,FALSE)*Urban!O91)+(VLOOKUP($P$2,Prices!$E$3:$F$17,2,FALSE)*Urban!P91)+(VLOOKUP($Q$2,Prices!$E$3:$F$17,2,FALSE)*Urban!Q91)+(VLOOKUP($R$2,Prices!$E$3:$F$17,2,FALSE)*Urban!R91)+(VLOOKUP($S$2,Prices!$E$3:$F$17,2,FALSE)*Urban!S91)+(VLOOKUP($T$2,Prices!$E$3:$F$17,2,FALSE)*Urban!T91)+(VLOOKUP($U$2,Prices!$E$3:$F$17,2,FALSE)*Urban!U91)+(VLOOKUP($V$2,Prices!$E$3:$F$17,2,FALSE)*Urban!V91)+(VLOOKUP($W$2,Prices!$E$3:$F$17,2,FALSE)*Urban!W91)+(VLOOKUP($X$2,Prices!$E$3:$F$17,2,FALSE)*Urban!X91)+(VLOOKUP($Y$2,Prices!$E$3:$F$17,2,FALSE)*Urban!Y91)+(VLOOKUP($Z$2,Prices!$E$3:$F$17,2,FALSE)*Urban!Z91)+(VLOOKUP($AA$2,Prices!$E$3:$F$17,2,FALSE)*Urban!AA91)+(VLOOKUP($AB$2,Prices!$E$3:$F$17,2,FALSE)*Urban!AB91)+M91 -> 17050000 | AD91: 3450000 | AF91: =AD91-AE91 -> 3450000 | AH91: =AD91+AG91 -> 3450000 | AI91: =AH91/M91 -> 0.20234604 | AJ91: =AH91/AC91 -> 0.20234604
A92: 90 | I92: Three Zeroes | J92: SWR | K92: Marina | L92: LAC1419 | M92: =IFERROR(VLOOKUP($L92,'[2]Top WH -National'!$D$9:$AC$124,26,0),0) -> 384078500 | N92: =IFERROR(VLOOKUP($L92,'[2]Top WH -National'!$D$9:$AC$124,4,0),0) -> 1865 | AC92: =(VLOOKUP($O$2,Prices!$E$3:$F$17,2,FALSE)*Urban!O92)+(VLOOKUP($P$2,Prices!$E$3:$F$17,2,FALSE)*Urban!P92)+(VLOOKUP($Q$2,Prices!$E$3:$F$17,2,FALSE)*Urban!Q92)+(VLOOKUP($R$2,Prices!$E$3:$F$17,2,FALSE)*Urban!R92)+(VLOOKUP($S$2,Prices!$E$3:$F$17,2,FALSE)*Urban!S92)+(VLOOKUP($T$2,Prices!$E$3:$F$17,2,FALSE)*Urban!T92)+(VLOOKUP($U$2,Prices!$E$3:$F$17,2,FALSE)*Urban!U92)+(VLOOKUP($V$2,Prices!$E$3:$F$17,2,FALSE)*Urban!V92)+(VLOOKUP($W$2,Prices!$E$3:$F$17,2,FALSE)*Urban!W92)+(VLOOKUP($X$2,Prices!$E$3:$F$17,2,FALSE)*Urban!X92)+(VLOOKUP($Y$2,Prices!$E$3:$F$17,2,FALSE)*Urban!Y92)+(VLOOKUP($Z$2,Prices!$E$3:$F$17,2,FALSE)*Urban!Z92)+(VLOOKUP($AA$2,Prices!$E$3:$F$17,2,FALSE)*Urban!AA92)+(VLOOKUP($AB$2,Prices!$E$3:$F$17,2,FALSE)*Urban!AB92)+M92 -> 384078500 | AD92: 192039250 | AF92: =AD92-AE92 -> 192039250 | AH92: =AD92+AG92 -> 192039250 | AI92: =AH92/M92 -> 0.5 | AJ92: =AH92/AC92 -> 0.5
A93: 91 | I93: Yahya Mutairu Rasheedat | J93: SWR | K93: Marina | L93: LAC3987 | M93: =IFERROR(VLOOKUP($L93,[1]Consolidated!$C$9:$AC$341,27,0),0) -> 18763500 | N93: =IFERROR(VLOOKUP($L93,[1]Consolidated!$C$9:$AC$341,5,0),0) -> 90 | AC93: =(VLOOKUP($O$2,Prices!$E$3:$F$17,2,FALSE)*Urban!O93)+(VLOOKUP($P$2,Prices!$E$3:$F$17,2,FALSE)*Urban!P93)+(VLOOKUP($Q$2,Prices!$E$3:$F$17,2,FALSE)*Urban!Q93)+(VLOOKUP($R$2,Prices!$E$3:$F$17,2,FALSE)*Urban!R93)+(VLOOKUP($S$2,Prices!$E$3:$F$17,2,FALSE)*Urban!S93)+(VLOOKUP($T$2,Prices!$E$3:$F$17,2,FALSE)*Urban!T93)+(VLOOKUP($U$2,Prices!$E$3:$F$17,2,FALSE)*Urban!U93)+(VLOOKUP($V$2,Prices!$E$3:$F$17,2,FALSE)*Urban!V93)+(VLOOKUP($W$2,Prices!$E$3:$F$17,2,FALSE)*Urban!W93)+(VLOOKUP($X$2,Prices!$E$3:$F$17,2,FALSE)*Urban!X93)+(VLOOKUP($Y$2,Prices!$E$3:$F$17,2,FALSE)*Urban!Y93)+(VLOOKUP($Z$2,Prices!$E$3:$F$17,2,FALSE)*Urban!Z93)+(VLOOKUP($AA$2,Prices!$E$3:$F$17,2,FALSE)*Urban!AA93)+(VLOOKUP($AB$2,Prices!$E$3:$F$17,2,FALSE)*Urban!AB93)+M93 -> 18763500 | AD93: 4321050 | AF93: =AD93-AE93 -> 4321050 | AH93: =AD93+AG93 -> 4321050 | AI93: =AH93/M93 -> 0.23029019 | AJ93: =AH93/AC93 -> 0.23029019
A94: 92 | I94: DAMTOY NIG LTD | J94: SWR | K94: Marina | L94: LAC0429 | M94: =IFERROR(VLOOKUP($L94,[1]Consolidated!$C$9:$AC$341,27,0),0) -> 14666000 | N94: =IFERROR(VLOOKUP($L94,[1]Consolidated!$C$9:$AC$341,5,0),0) -> 70 | AC94: =(VLOOKUP($O$2,Prices!$E$3:$F$17,2,FALSE)*Urban!O94)+(VLOOKUP($P$2,Prices!$E$3:$F$17,2,FALSE)*Urban!P94)+(VLOOKUP($Q$2,Prices!$E$3:$F$17,2,FALSE)*Urban!Q94)+(VLOOKUP($R$2,Prices!$E$3:$F$17,2,FALSE)*Urban!R94)+(VLOOKUP($S$2,Prices!$E$3:$F$17,2,FALSE)*Urban!S94)+(VLOOKUP($T$2,Prices!$E$3:$F$17,2,FALSE)*Urban!T94)+(VLOOKUP($U$2,Prices!$E$3:$F$17,2,FALSE)*Urban!U94)+(VLOOKUP($V$2,Prices!$E$3:$F$17,2,FALSE)*Urban!V94)+(VLOOKUP($W$2,Prices!$E$3:$F$17,2,FALSE)*Urban!W94)+(VLOOKUP($X$2,Prices!$E$3:$F$17,2,FALSE)*Urban!X94)+(VLOOKUP($Y$2,Prices!$E$3:$F$17,2,FALSE)*Urban!Y94)+(VLOOKUP($Z$2,Prices!$E$3:$F$17,2,FALSE)*Urban!Z94)+(VLOOKUP($AA$2,Prices!$E$3:$F$17,2,FALSE)*Urban!AA94)+(VLOOKUP($AB$2,Prices!$E$3:$F$17,2,FALSE)*Urban!AB94)+M94 -> 14666000 | AD94: 4399800 | AF94: =AD94-AE94 -> 4399800 | AH94: =AD94+AG94 -> 4399800 | AI94: =AH94/M94 -> 0.3 | AJ94: =AH94/AC94 -> 0.3
A95: 93 | I95: Marthy B | J95: SWR | K95: Marina | L95: LAC3995 | M95: =IFERROR(VLOOKUP($L95,[1]Consolidated!$C$9:$AC$341,27,0),0) -> 13755000 | N95: =IFERROR(VLOOKUP($L95,[1]Consolidated!$C$9:$AC$341,5,0),0) -> 70 | AC95: =(VLOOKUP($O$2,Prices!$E$3:$F$17,2,FALSE)*Urban!O95)+(VLOOKUP($P$2,Prices!$E$3:$F$17,2,FALSE)*Urban!P95)+(VLOOKUP($Q$2,Prices!$E$3:$F$17,2,FALSE)*Urban!Q95)+(VLOOKUP($R$2,Prices!$E$3:$F$17,2,FALSE)*Urban!R95)+(VLOOKUP($S$2,Prices!$E$3:$F$17,2,FALSE)*Urban!S95)+(VLOOKUP($T$2,Prices!$E$3:$F$17,2,FALSE)*Urban!T95)+(VLOOKUP($U$2,Prices!$E$3:$F$17,2,FALSE)*Urban!U95)+(VLOOKUP($V$2,Prices!$E$3:$F$17,2,FALSE)*Urban!V95)+(VLOOKUP($W$2,Prices!$E$3:$F$17,2,FALSE)*Urban!W95)+(VLOOKUP($X$2,Prices!$E$3:$F$17,2,FALSE)*Urban!X95)+(VLOOKUP($Y$2,Prices!$E$3:$F$17,2,FALSE)*Urban!Y95)+(VLOOKUP($Z$2,Prices!$E$3:$F$17,2,FALSE)*Urban!Z95)+(VLOOKUP($AA$2,Prices!$E$3:$F$17,2,FALSE)*Urban!AA95)+(VLOOKUP($AB$2,Prices!$E$3:$F$17,2,FALSE)*Urban!AB95)+M95 -> 13755000 | AD95: 4126500 | AF95: =AD95-AE95 -> 4126500 | AH95: =AD95+AG95 -> 4126500 | AI95: =AH95/M95 -> 0.3 | AJ95: =AH95/AC95 -> 0.3
A96: 94 | I96: Blessed Kanayo | J96: SWR | K96: Marina | L96: LAC0161 | M96: =IFERROR(VLOOKUP($L96,[1]Consolidated!$C$9:$AC$341,27,0),0) -> 0 | N96: =IFERROR(VLOOKUP($L96,[1]Consolidated!$C$9:$AC$341,5,0),0) -> 0 | AC96: =(VLOOKUP($O$2,Prices!$E$3:$F$17,2,FALSE)*Urban!O96)+(VLOOKUP($P$2,Prices!$E$3:$F$17,2,FALSE)*Urban!P96)+(VLOOKUP($Q$2,Prices!$E$3:$F$17,2,FALSE)*Urban!Q96)+(VLOOKUP($R$2,Prices!$E$3:$F$17,2,FALSE)*Urban!R96)+(VLOOKUP($S$2,Prices!$E$3:$F$17,2,FALSE)*Urban!S96)+(VLOOKUP($T$2,Prices!$E$3:$F$17,2,FALSE)*Urban!T96)+(VLOOKUP($U$2,Prices!$E$3:$F$17,2,FALSE)*Urban!U96)+(VLOOKUP($V$2,Prices!$E$3:$F$17,2,FALSE)*Urban!V96)+(VLOOKUP($W$2,Prices!$E$3:$F$17,2,FALSE)*Urban!W96)+(VLOOKUP($X$2,Prices!$E$3:$F$17,2,FALSE)*Urban!X96)+(VLOOKUP($Y$2,Prices!$E$3:$F$17,2,FALSE)*Urban!Y96)+(VLOOKUP($Z$2,Prices!$E$3:$F$17,2,FALSE)*Urban!Z96)+(VLOOKUP($AA$2,Prices!$E$3:$F$17,2,FALSE)*Urban!AA96)+(VLOOKUP($AB$2,Prices!$E$3:$F$17,2,FALSE)*Urban!AB96)+M96 -> 0 | AD96: 0 | AF96: =AD96-AE96 -> 0 | AH96: =AD96+AG96 -> 0 | AI96: =AH96/M96 -> #DIV/0! | AJ96: =AH96/AC96 -> #DIV/0!
A97: 95 | I97: Mumuni Ibrahim | J97: SWR | K97: Marina | L97: LAC0160 | M97: =IFERROR(VLOOKUP($L97,'[2]Top WH -National'!$D$9:$AC$124,26,0),0) -> 90305000 | N97: =IFERROR(VLOOKUP($L97,'[2]Top WH -National'!$D$9:$AC$124,4,0),0) -> 440 | AC97: =(VLOOKUP($O$2,Prices!$E$3:$F$17,2,FALSE)*Urban!O97)+(VLOOKUP($P$2,Prices!$E$3:$F$17,2,FALSE)*Urban!P97)+(VLOOKUP($Q$2,Prices!$E$3:$F$17,2,FALSE)*Urban!Q97)+(VLOOKUP($R$2,Prices!$E$3:$F$17,2,FALSE)*Urban!R97)+(VLOOKUP($S$2,Prices!$E$3:$F$17,2,FALSE)*Urban!S97)+(VLOOKUP($T$2,Prices!$E$3:$F$17,2,FALSE)*Urban!T97)+(VLOOKUP($U$2,Prices!$E$3:$F$17,2,FALSE)*Urban!U97)+(VLOOKUP($V$2,Prices!$E$3:$F$17,2,FALSE)*Urban!V97)+(VLOOKUP($W$2,Prices!$E$3:$F$17,2,FALSE)*Urban!W97)+(VLOOKUP($X$2,Prices!$E$3:$F$17,2,FALSE)*Urban!X97)+(VLOOKUP($Y$2,Prices!$E$3:$F$17,2,FALSE)*Urban!Y97)+(VLOOKUP($Z$2,Prices!$E$3:$F$17,2,FALSE)*Urban!Z97)+(VLOOKUP($AA$2,Prices!$E$3:$F$17,2,FALSE)*Urban!AA97)+(VLOOKUP($AB$2,Prices!$E$3:$F$17,2,FALSE)*Urban!AB97)+M97 -> 90305000 | AD97: 45152500 | AF97: =AD97-AE97 -> 45152500 | AH97: =AD97+AG97 -> 45152500 | AI97: =AH97/M97 -> 0.5 | AJ97: =AH97/AC97 -> 0.5
A98: 96 | I98: MR. SEGUN ADEMOLA | J98: SWR | K98: Marina | L98: CTAE0047 | M98: =IFERROR(VLOOKUP($L98,[1]Consolidated!$C$9:$AC$341,27,0),0) -> 41425000 | N98: =IFERROR(VLOOKUP($L98,[1]Consolidated!$C$9:$AC$341,5,0),0) -> 180 | AC98: =(VLOOKUP($O$2,Prices!$E$3:$F$17,2,FALSE)*Urban!O98)+(VLOOKUP($P$2,Prices!$E$3:$F$17,2,FALSE)*Urban!P98)+(VLOOKUP($Q$2,Prices!$E$3:$F$17,2,FALSE)*Urban!Q98)+(VLOOKUP($R$2,Prices!$E$3:$F$17,2,FALSE)*Urban!R98)+(VLOOKUP($S$2,Prices!$E$3:$F$17,2,FALSE)*Urban!S98)+(VLOOKUP($T$2,Prices!$E$3:$F$17,2,FALSE)*Urban!T98)+(VLOOKUP($U$2,Prices!$E$3:$F$17,2,FALSE)*Urban!U98)+(VLOOKUP($V$2,Prices!$E$3:$F$17,2,FALSE)*Urban!V98)+(VLOOKUP($W$2,Prices!$E$3:$F$17,2,FALSE)*Urban!W98)+(VLOOKUP($X$2,Prices!$E$3:$F$17,2,FALSE)*Urban!X98)+(VLOOKUP($Y$2,Prices!$E$3:$F$17,2,FALSE)*Urban!Y98)+(VLOOKUP($Z$2,Prices!$E$3:$F$17,2,FALSE)*Urban!Z98)+(VLOOKUP($AA$2,Prices!$E$3:$F$17,2,FALSE)*Urban!AA98)+(VLOOKUP($AB$2,Prices!$E$3:$F$17,2,FALSE)*Urban!AB98)+M98 -> 41425000 | AD98: 11737500 | AF98: =AD98-AE98 -> 11737500 | AH98: =AD98+AG98 -> 11737500 | AI98: =AH98/M98 -> 0.28334339 | AJ98: =AH98/AC98 -> 0.28334339
A99: 97 | I99: MRS SEMO & CO | J99: SWR | K99: Marina | L99: CTAE0045 | M99: =IFERROR(VLOOKUP($L99,'[2]Top WH -National'!$D$9:$AC$124,26,0),0) -> 67788000 | N99: =IFERROR(VLOOKUP($L99,'[2]Top WH -National'!$D$9:$AC$124,4,0),0) -> 325 | AC99: =(VLOOKUP($O$2,Prices!$E$3:$F$17,2,FALSE)*Urban!O99)+(VLOOKUP($P$2,Prices!$E$3:$F$17,2,FALSE)*Urban!P99)+(VLOOKUP($Q$2,Prices!$E$3:$F$17,2,FALSE)*Urban!Q99)+(VLOOKUP($R$2,Prices!$E$3:$F$17,2,FALSE)*Urban!R99)+(VLOOKUP($S$2,Prices!$E$3:$F$17,2,FALSE)*Urban!S99)+(VLOOKUP($T$2,Prices!$E$3:$F$17,2,FALSE)*Urban!T99)+(VLOOKUP($U$2,Prices!$E$3:$F$17,2,FALSE)*Urban!U99)+(VLOOKUP($V$2,Prices!$E$3:$F$17,2,FALSE)*Urban!V99)+(VLOOKUP($W$2,Prices!$E$3:$F$17,2,FALSE)*Urban!W99)+(VLOOKUP($X$2,Prices!$E$3:$F$17,2,FALSE)*Urban!X99)+(VLOOKUP($Y$2,Prices!$E$3:$F$17,2,FALSE)*Urban!Y99)+(VLOOKUP($Z$2,Prices!$E$3:$F$17,2,FALSE)*Urban!Z99)+(VLOOKUP($AA$2,Prices!$E$3:$F$17,2,FALSE)*Urban!AA99)+(VLOOKUP($AB$2,Prices!$E$3:$F$17,2,FALSE)*Urban!AB99)+M99 -> 67788000 | AD99: 33894000 | AF99: =AD99-AE99 -> 33894000 | AH99: =AD99+AG99 -> 33894000 | AI99: =AH99/M99 -> 0.5 | AJ99: =AH99/AC99 -> 0.5
A100: 98 | I100: MR R A IBRAHIM | J100: SWR | K100: Marina | L100: CTAE0042 | M100: =IFERROR(VLOOKUP($L100,[1]Consolidated!$C$9:$AC$341,27,0),0) -> 17541000 | N100: =IFERROR(VLOOKUP($L100,[1]Consolidated!$C$9:$AC$341,5,0),0) -> 80 | AC100: =(VLOOKUP($O$2,Prices!$E$3:$F$17,2,FALSE)*Urban!O100)+(VLOOKUP($P$2,Prices!$E$3:$F$17,2,FALSE)*Urban!P100)+(VLOOKUP($Q$2,Prices!$E$3:$F$17,2,FALSE)*Urban!Q100)+(VLOOKUP($R$2,Prices!$E$3:$F$17,2,FALSE)*Urban!R100)+(VLOOKUP($S$2,Prices!$E$3:$F$17,2,FALSE)*Urban!S100)+(VLOOKUP($T$2,Prices!$E$3:$F$17,2,FALSE)*Urban!T100)+(VLOOKUP($U$2,Prices!$E$3:$F$17,2,FALSE)*Urban!U100)+(VLOOKUP($V$2,Prices!$E$3:$F$17,2,FALSE)*Urban!V100)+(VLOOKUP($W$2,Prices!$E$3:$F$17,2,FALSE)*Urban!W100)+(VLOOKUP($X$2,Prices!$E$3:$F$17,2,FALSE)*Urban!X100)+(VLOOKUP($Y$2,Prices!$E$3:$F$17,2,FALSE)*Urban!Y100)+(VLOOKUP($Z$2,Prices!$E$3:$F$17,2,FALSE)*Urban!Z100)+(VLOOKUP($AA$2,Prices!$E$3:$F$17,2,FALSE)*Urban!AA100)+(VLOOKUP($AB$2,Prices!$E$3:$F$17,2,FALSE)*Urban!AB100)+M100 -> 17541000 | AD100: 4479300 | AF100: =AD100-AE100 -> 4479300 | AH100: =AD100+AG100 -> 4479300 | AI100: =AH100/M100 -> 0.25536172 | AJ100: =AH100/AC100 -> 0.25536172
A101: 99 | I101: ALHAJA MOGBONJUBOLA OLANREWAJU | J101: SWR | K101: Marina | L101: CTAE0033 | M101: =IFERROR(VLOOKUP($L101,'[2]Top WH -National'!$D$9:$AC$124,26,0),0) -> 137193500 | N101: =IFERROR(VLOOKUP($L101,'[2]Top WH -National'!$D$9:$AC$124,4,0),0) -> 638 | AC101: =(VLOOKUP($O$2,Prices!$E$3:$F$17,2,FALSE)*Urban!O101)+(VLOOKUP($P$2,Prices!$E$3:$F$17,2,FALSE)*Urban!P101)+(VLOOKUP($Q$2,Prices!$E$3:$F$17,2,FALSE)*Urban!Q101)+(VLOOKUP($R$2,Prices!$E$3:$F$17,2,FALSE)*Urban!R101)+(VLOOKUP($S$2,Prices!$E$3:$F$17,2,FALSE)*Urban!S101)+(VLOOKUP($T$2,Prices!$E$3:$F$17,2,FALSE)*Urban!T101)+(VLOOKUP($U$2,Prices!$E$3:$F$17,2,FALSE)*Urban!U101)+(VLOOKUP($V$2,Prices!$E$3:$F$17,2,FALSE)*Urban!V101)+(VLOOKUP($W$2,Prices!$E$3:$F$17,2,FALSE)*Urban!W101)+(VLOOKUP($X$2,Prices!$E$3:$F$17,2,FALSE)*Urban!X101)+(VLOOKUP($Y$2,Prices!$E$3:$F$17,2,FALSE)*Urban!Y101)+(VLOOKUP($Z$2,Prices!$E$3:$F$17,2,FALSE)*Urban!Z101)+(VLOOKUP($AA$2,Prices!$E$3:$F$17,2,FALSE)*Urban!AA101)+(VLOOKUP($AB$2,Prices!$E$3:$F$17,2,FALSE)*Urban!AB101)+M101 -> 137193500 | AD101: 71796218 | AF101: =AD101-AE101 -> 71796218 | AH101: =AD101+AG101 -> 71796218 | AI101: =AH101/M101 -> 0.52332085 | AJ101: =AH101/AC101 -> 0.52332085
A102: 100 | I102: MR MADINAT YUSUF | J102: SWR | K102: Marina | L102: CTAE0032 | M102: =IFERROR(VLOOKUP($L102,[1]Consolidated!$C$9:$AC$341,27,0),0) -> 0 | N102: =IFERROR(VLOOKUP($L102,[1]Consolidated!$C$9:$AC$341,5,0),0) -> 0 | AC102: =(VLOOKUP($O$2,Prices!$E$3:$F$17,2,FALSE)*Urban!O102)+(VLOOKUP($P$2,Prices!$E$3:$F$17,2,FALSE)*Urban!P102)+(VLOOKUP($Q$2,Prices!$E$3:$F$17,2,FALSE)*Urban!Q102)+(VLOOKUP($R$2,Prices!$E$3:$F$17,2,FALSE)*Urban!R102)+(VLOOKUP($S$2,Prices!$E$3:$F$17,2,FALSE)*Urban!S102)+(VLOOKUP($T$2,Prices!$E$3:$F$17,2,FALSE)*Urban!T102)+(VLOOKUP($U$2,Prices!$E$3:$F$17,2,FALSE)*Urban!U102)+(VLOOKUP($V$2,Prices!$E$3:$F$17,2,FALSE)*Urban!V102)+(VLOOKUP($W$2,Prices!$E$3:$F$17,2,FALSE)*Urban!W102)+(VLOOKUP($X$2,Prices!$E$3:$F$17,2,FALSE)*Urban!X102)+(VLOOKUP($Y$2,Prices!$E$3:$F$17,2,FALSE)*Urban!Y102)+(VLOOKUP($Z$2,Prices!$E$3:$F$17,2,FALSE)*Urban!Z102)+(VLOOKUP($AA$2,Prices!$E$3:$F$17,2,FALSE)*Urban!AA102)+(VLOOKUP($AB$2,Prices!$E$3:$F$17,2,FALSE)*Urban!AB102)+M102 -> 0 | AD102: 0 | AF102: =AD102-AE102 -> 0 | AH102: =AD102+AG102 -> 0 | AI102: =AH102/M102 -> #DIV/0! | AJ102: =AH102/AC102 -> #DIV/0!
A103: 101 | I103: ALH LUKMAN BELLO | J103: SWR | K103: Marina | L103: CTAE0031 | M103: =IFERROR(VLOOKUP($L103,[1]Consolidated!$C$9:$AC$341,27,0),0) -> 15420000 | N103: =IFERROR(VLOOKUP($L103,[1]Consolidated!$C$9:$AC$341,5,0),0) -> 70 | AC103: =(VLOOKUP($O$2,Prices!$E$3:$F$17,2,FALSE)*Urban!O103)+(VLOOKUP($P$2,Prices!$E$3:$F$17,2,FALSE)*Urban!P103)+(VLOOKUP($Q$2,Prices!$E$3:$F$17,2,FALSE)*Urban!Q103)+(VLOOKUP($R$2,Prices!$E$3:$F$17,2,FALSE)*Urban!R103)+(VLOOKUP($S$2,Prices!$E$3:$F$17,2,FALSE)*Urban!S103)+(VLOOKUP($T$2,Prices!$E$3:$F$17,2,FALSE)*Urban!T103)+(VLOOKUP($U$2,Prices!$E$3:$F$17,2,FALSE)*Urban!U103)+(VLOOKUP($V$2,Prices!$E$3:$F$17,2,FALSE)*Urban!V103)+(VLOOKUP($W$2,Prices!$E$3:$F$17,2,FALSE)*Urban!W103)+(VLOOKUP($X$2,Prices!$E$3:$F$17,2,FALSE)*Urban!X103)+(VLOOKUP($Y$2,Prices!$E$3:$F$17,2,FALSE)*Urban!Y103)+(VLOOKUP($Z$2,Prices!$E$3:$F$17,2,FALSE)*Urban!Z103)+(VLOOKUP($AA$2,Prices!$E$3:$F$17,2,FALSE)*Urban!AA103)+(VLOOKUP($AB$2,Prices!$E$3:$F$17,2,FALSE)*Urban!AB103)+M103 -> 15420000 | AD103: 4626000 | AF103: =AD103-AE103 -> 4626000 | AH103: =AD103+AG103 -> 4626000 | AI103: =AH103/M103 -> 0.3 | AJ103: =AH103/AC103 -> 0.3
A104: 102 | I104: MR EDATOMOLA KAZEEM | J104: SWR | K104: Marina | L104: LAC3996 | M104: =IFERROR(VLOOKUP($L104,[1]Consolidated!$C$9:$AC$341,27,0),0) -> 27775000 | N104: =IFERROR(VLOOKUP($L104,[1]Consolidated!$C$9:$AC$341,5,0),0) -> 130 | AC104: =(VLOOKUP($O$2,Prices!$E$3:$F$17,2,FALSE)*Urban!O104)+(VLOOKUP($P$2,Prices!$E$3:$F$17,2,FALSE)*Urban!P104)+(VLOOKUP($Q$2,Prices!$E$3:$F$17,2,FALSE)*Urban!Q104)+(VLOOKUP($R$2,Prices!$E$3:$F$17,2,FALSE)*Urban!R104)+(VLOOKUP($S$2,Prices!$E$3:$F$17,2,FALSE)*Urban!S104)+(VLOOKUP($T$2,Prices!$E$3:$F$17,2,FALSE)*Urban!T104)+(VLOOKUP($U$2,Prices!$E$3:$F$17,2,FALSE)*Urban!U104)+(VLOOKUP($V$2,Prices!$E$3:$F$17,2,FALSE)*Urban!V104)+(VLOOKUP($W$2,Prices!$E$3:$F$17,2,FALSE)*Urban!W104)+(VLOOKUP($X$2,Prices!$E$3:$F$17,2,FALSE)*Urban!X104)+(VLOOKUP($Y$2,Prices!$E$3:$F$17,2,FALSE)*Urban!Y104)+(VLOOKUP($Z$2,Prices!$E$3:$F$17,2,FALSE)*Urban!Z104)+(VLOOKUP($AA$2,Prices!$E$3:$F$17,2,FALSE)*Urban!AA104)+(VLOOKUP($AB$2,Prices!$E$3:$F$17,2,FALSE)*Urban!AB104)+M104 -> 27775000 | AD104: 7941000 | AF104: =AD104-AE104 -> 7941000 | AH104: =AD104+AG104 -> 7941000 | AI104: =AH104/M104 -> 0.28590459 | AJ104: =AH104/AC104 -> 0.28590459
A105: 103 | I105: BOLTIKAY NIG LIMITED | J105: SWR | K105: Marina | L105: CTAE0017 | M105: =IFERROR(VLOOKUP($L105,[1]Consolidated!$C$9:$AC$341,27,0),0) -> 27277000 | N105: =IFERROR(VLOOKUP($L105,[1]Consolidated!$C$9:$AC$341,5,0),0) -> 130 | AC105: =(VLOOKUP($O$2,Prices!$E$3:$F$17,2,FALSE)*Urban!O105)+(VLOOKUP($P$2,Prices!$E$3:$F$17,2,FALSE)*Urban!P105)+(VLOOKUP($Q$2,Prices!$E$3:$F$17,2,FALSE)*Urban!Q105)+(VLOOKUP($R$2,Prices!$E$3:$F$17,2,FALSE)*Urban!R105)+(VLOOKUP($S$2,Prices!$E$3:$F$17,2,FALSE)*Urban!S105)+(VLOOKUP($T$2,Prices!$E$3:$F$17,2,FALSE)*Urban!T105)+(VLOOKUP($U$2,Prices!$E$3:$F$17,2,FALSE)*Urban!U105)+(VLOOKUP($V$2,Prices!$E$3:$F$17,2,FALSE)*Urban!V105)+(VLOOKUP($W$2,Prices!$E$3:$F$17,2,FALSE)*Urban!W105)+(VLOOKUP($X$2,Prices!$E$3:$F$17,2,FALSE)*Urban!X105)+(VLOOKUP($Y$2,Prices!$E$3:$F$17,2,FALSE)*Urban!Y105)+(VLOOKUP($Z$2,Prices!$E$3:$F$17,2,FALSE)*Urban!Z105)+(VLOOKUP($AA$2,Prices!$E$3:$F$17,2,FALSE)*Urban!AA105)+(VLOOKUP($AB$2,Prices!$E$3:$F$17,2,FALSE)*Urban!AB105)+M105 -> 27277000 | AD105: 11791600 | AF105: =AD105-AE105 -> 11791600 | AG105: 7000000 | AH105: =AD105+AG105 -> 18791600 | AI105: =AH105/M105 -> 0.6889174 | AJ105: =AH105/AC105 -> 0.6889174
A106: 104 | I106: AROWOLO TAIBAT | J106: SWR | K106: Marina | L106: CTAE0013 | M106: =IFERROR(VLOOKUP($L106,[1]Consolidated!$C$9:$AC$341,27,0),0) -> 64577500 | N106: =IFERROR(VLOOKUP($L106,[1]Consolidated!$C$9:$AC$341,5,0),0) -> 300 | AC106: =(VLOOKUP($O$2,Prices!$E$3:$F$17,2,FALSE)*Urban!O106)+(VLOOKUP($P$2,Prices!$E$3:$F$17,2,FALSE)*Urban!P106)+(VLOOKUP($Q$2,Prices!$E$3:$F$17,2,FALSE)*Urban!Q106)+(VLOOKUP($R$2,Prices!$E$3:$F$17,2,FALSE)*Urban!R106)+(VLOOKUP($S$2,Prices!$E$3:$F$17,2,FALSE)*Urban!S106)+(VLOOKUP($T$2,Prices!$E$3:$F$17,2,FALSE)*Urban!T106)+(VLOOKUP($U$2,Prices!$E$3:$F$17,2,FALSE)*Urban!U106)+(VLOOKUP($V$2,Prices!$E$3:$F$17,2,FALSE)*Urban!V106)+(VLOOKUP($W$2,Prices!$E$3:$F$17,2,FALSE)*Urban!W106)+(VLOOKUP($X$2,Prices!$E$3:$F$17,2,FALSE)*Urban!X106)+(VLOOKUP($Y$2,Prices!$E$3:$F$17,2,FALSE)*Urban!Y106)+(VLOOKUP($Z$2,Prices!$E$3:$F$17,2,FALSE)*Urban!Z106)+(VLOOKUP($AA$2,Prices!$E$3:$F$17,2,FALSE)*Urban!AA106)+(VLOOKUP($AB$2,Prices!$E$3:$F$17,2,FALSE)*Urban!AB106)+M106 -> 64577500 | AD106: 18683250 | AF106: =AD106-AE106 -> 18683250 | AH106: =AD106+AG106 -> 18683250 | AI106: =AH106/M106 -> 0.28931516 | AJ106: =AH106/AC106 -> 0.28931516
A107: 105 | I107: MR AJAYI AYINKE | J107: SWR | K107: Marina | L107: CTAE0006 | M107: =IFERROR(VLOOKUP($L107,'[2]Top WH -National'!$D$9:$AC$124,26,0),0) -> 65462000 | N107: =IFERROR(VLOOKUP($L107,'[2]Top WH -National'!$D$9:$AC$124,4,0),0) -> 300 | AC107: =(VLOOKUP($O$2,Prices!$E$3:$F$17,2,FALSE)*Urban!O107)+(VLOOKUP($P$2,Prices!$E$3:$F$17,2,FALSE)*Urban!P107)+(VLOOKUP($Q$2,Prices!$E$3:$F$17,2,FALSE)*Urban!Q107)+(VLOOKUP($R$2,Prices!$E$3:$F$17,2,FALSE)*Urban!R107)+(VLOOKUP($S$2,Prices!$E$3:$F$17,2,FALSE)*Urban!S107)+(VLOOKUP($T$2,Prices!$E$3:$F$17,2,FALSE)*Urban!T107)+(VLOOKUP($U$2,Prices!$E$3:$F$17,2,FALSE)*Urban!U107)+(VLOOKUP($V$2,Prices!$E$3:$F$17,2,FALSE)*Urban!V107)+(VLOOKUP($W$2,Prices!$E$3:$F$17,2,FALSE)*Urban!W107)+(VLOOKUP($X$2,Prices!$E$3:$F$17,2,FALSE)*Urban!X107)+(VLOOKUP($Y$2,Prices!$E$3:$F$17,2,FALSE)*Urban!Y107)+(VLOOKUP($Z$2,Prices!$E$3:$F$17,2,FALSE)*Urban!Z107)+(VLOOKUP($AA$2,Prices!$E$3:$F$17,2,FALSE)*Urban!AA107)+(VLOOKUP($AB$2,Prices!$E$3:$F$17,2,FALSE)*Urban!AB107)+M107 -> 65462000 | AD107: 32731000 | AF107: =AD107-AE107 -> 32731000 | AH107: =AD107+AG107 -> 32731000 | AI107: =AH107/M107 -> 0.5 | AJ107: =AH107/AC107 -> 0.5
A108: 106 | I108: MESSRS YAKUBU AISHA | J108: SWR | K108: Marina | L108: CTAE0054 | M108: =IFERROR(VLOOKUP($L108,[1]Consolidated!$C$9:$AC$341,27,0),0) -> 0 | N108: =IFERROR(VLOOKUP($L108,[1]Consolidated!$C$9:$AC$341,5,0),0) -> 0 | AC108: =(VLOOKUP($O$2,Prices!$E$3:$F$17,2,FALSE)*Urban!O108)+(VLOOKUP($P$2,Prices!$E$3:$F$17,2,FALSE)*Urban!P108)+(VLOOKUP($Q$2,Prices!$E$3:$F$17,2,FALSE)*Urban!Q108)+(VLOOKUP($R$2,Prices!$E$3:$F$17,2,FALSE)*Urban!R108)+(VLOOKUP($S$2,Prices!$E$3:$F$17,2,FALSE)*Urban!S108)+(VLOOKUP($T$2,Prices!$E$3:$F$17,2,FALSE)*Urban!T108)+(VLOOKUP($U$2,Prices!$E$3:$F$17,2,FALSE)*Urban!U108)+(VLOOKUP($V$2,Prices!$E$3:$F$17,2,FALSE)*Urban!V108)+(VLOOKUP($W$2,Prices!$E$3:$F$17,2,FALSE)*Urban!W108)+(VLOOKUP($X$2,Prices!$E$3:$F$17,2,FALSE)*Urban!X108)+(VLOOKUP($Y$2,Prices!$E$3:$F$17,2,FALSE)*Urban!Y108)+(VLOOKUP($Z$2,Prices!$E$3:$F$17,2,FALSE)*Urban!Z108)+(VLOOKUP($AA$2,Prices!$E$3:$F$17,2,FALSE)*Urban!AA108)+(VLOOKUP($AB$2,Prices!$E$3:$F$17,2,FALSE)*Urban!AB108)+M108 -> 0 | AD108: 0 | AF108: =AD108-AE108 -> 0 | AH108: =AD108+AG108 -> 0 | AI108: =AH108/M108 -> #DIV/0! | AJ108: =AH108/AC108 -> #DIV/0!
...

Sheet Rural1
A2: S/N | B2: Customer | C2: Area | D2: GBNL URN | E2: Initial Credit Value | F2: To be Utilized | G2: Balance | H2: New Credit Value | I2: Name | J2: Region | K2: AREA | L2: GBNL URN | M2: August '22 Target Value (₦) | N2: Current Target | O2: B & H Switch | P2: Rothmans Switch | Q2: Benson & Hedges Boost | R2: Benson & Hedges Demi-Slims | S2: Benson & Hedges Flavour | T2: Dunhill Switch | U2: ST Moritz By Dunhill | V2: Rothmans Menthol | W2: Pall Mall Filter | X2: Pall Mall Menthol | Y2: Rothmans Flavour | Z2: Royal Std Filter | AA2: Pall Mall - Excel Blend | AB2: Pall Mall Boost | AC2: New August Target Value | AD2: August '22 Initial Credit Deployment (₦) | AE2: August '22 Initial Credit Deployment (₦) BD View | AF2: BD Check | AG2: Extra Credit Request (₦) | AH2: Total Credit for Upload August '22 (₦) | AI2: % Credit Exposure vs Initial Target | AJ2: % Credit Exposure vs New expected volume | AK2: Justification
A3: 1 | I3: EMMANUEL AGRO | J3: SER | K3: Benin | L3: SWC2876 | M3: =IFERROR(VLOOKUP($L3,[3]Consolidated!$C$9:$AC$452,27,0),0) -> 10358900 | N3: =IFERROR(VLOOKUP($L3,[3]Consolidated!$C$9:$AC$452,5,0),0) -> 50 | O3: 0 | S3: 10 | AC3: =(VLOOKUP($O$2,[4]Prices!$E$3:$K$17,2,FALSE)*O3)+(VLOOKUP($P$2,[4]Prices!$J$3:$K$17,2,FALSE)*P3)+(VLOOKUP($Q$2,[4]Prices!$J$3:$K$17,2,FALSE)*Q3)+(VLOOKUP($R$2,[4]Prices!$J$3:$K$17,2,FALSE)*R3)+(VLOOKUP($S$2,[4]Prices!$J$3:$K$17,2,FALSE)*S3)+(VLOOKUP($T$2,[4]Prices!$J$3:$K$17,2,FALSE)*T3)+(VLOOKUP($U$2,[4]Prices!$J$3:$K$17,2,FALSE)*U3)+(VLOOKUP($V$2,[4]Prices!$J$3:$K$17,2,FALSE)*V3)+(VLOOKUP($W$2,[4]Prices!$J$3:$K$17,2,FALSE)*W3)+(VLOOKUP($X$2,[4]Prices!$J$3:$K$17,2,FALSE)*X3)+(VLOOKUP($Y$2,[4]Prices!$J$3:$K$17,2,FALSE)*Y3)+(VLOOKUP($Z$2,[4]Prices!$J$3:$K$17,2,FALSE)*Z3)+(VLOOKUP($AA$2,[4]Prices!$J$3:$K$17,2,FALSE)*AA3)+(VLOOKUP($AB$2,[4]Prices!$J$3:$K$17,2,FALSE)*AB3)+M3 -> 12663900 | AD3: 0 | AF3: =AD3-AE3 -> 0 | AG3: 0 | AH3: =AD3+AG3 -> 0 | AI3: =AH3/M3 -> 0 | AJ3: =AH3/AC3 -> 0
A4: 2 | I4: Benzoro Store | J4: SER | K4: Benin | L4: SWC2755 | M4: =IFERROR(VLOOKUP($L4,[3]Consolidated!$C$9:$AC$452,27,0),0) -> 9468200 | N4: =IFERROR(VLOOKUP($L4,[3]Consolidated!$C$9:$AC$452,5,0),0) -> 50 | AC4: =(VLOOKUP($O$2,[4]Prices!$E$3:$K$17,2,FALSE)*O4)+(VLOOKUP($P$2,[4]Prices!$J$3:$K$17,2,FALSE)*P4)+(VLOOKUP($Q$2,[4]Prices!$J$3:$K$17,2,FALSE)*Q4)+(VLOOKUP($R$2,[4]Prices!$J$3:$K$17,2,FALSE)*R4)+(VLOOKUP($S$2,[4]Prices!$J$3:$K$17,2,FALSE)*S4)+(VLOOKUP($T$2,[4]Prices!$J$3:$K$17,2,FALSE)*T4)+(VLOOKUP($U$2,[4]Prices!$J$3:$K$17,2,FALSE)*U4)+(VLOOKUP($V$2,[4]Prices!$J$3:$K$17,2,FALSE)*V4)+(VLOOKUP($W$2,[4]Prices!$J$3:$K$17,2,FALSE)*W4)+(VLOOKUP($X$2,[4]Prices!$J$3:$K$17,2,FALSE)*X4)+(VLOOKUP($Y$2,[4]Prices!$J$3:$K$17,2,FALSE)*Y4)+(VLOOKUP($Z$2,[4]Prices!$J$3:$K$17,2,FALSE)*Z4)+(VLOOKUP($AA$2,[4]Prices!$J$3:$K$17,2,FALSE)*AA4)+(VLOOKUP($AB$2,[4]Prices!$J$3:$K$17,2,FALSE)*AB4)+M4 -> 9468200 | AF4: =AD4-AE4 -> 0 | AH4: =AD4+AG4 -> 0 | AI4: =AH4/M4 -> 0 | AJ4: =AH4/AC4 -> 0
A5: 3 | I5: Paul Ovieba | J5: SER | K5: Benin | L5: WCFA000159 | M5: =IFERROR(VLOOKUP($L5,[3]Consolidated!$C$9:$AC$452,27,0),0) -> 7420000 | N5: =IFERROR(VLOOKUP($L5,[3]Consolidated!$C$9:$AC$452,5,0),0) -> 40 | AC5: =(VLOOKUP($O$2,[4]Prices!$E$3:$K$17,2,FALSE)*O5)+(VLOOKUP($P$2,[4]Prices!$J$3:$K$17,2,FALSE)*P5)+(VLOOKUP($Q$2,[4]Prices!$J$3:$K$17,2,FALSE)*Q5)+(VLOOKUP($R$2,[4]Prices!$J$3:$K$17,2,FALSE)*R5)+(VLOOKUP($S$2,[4]Prices!$J$3:$K$17,2,FALSE)*S5)+(VLOOKUP($T$2,[4]Prices!$J$3:$K$17,2,FALSE)*T5)+(VLOOKUP($U$2,[4]Prices!$J$3:$K$17,2,FALSE)*U5)+(VLOOKUP($V$2,[4]Prices!$J$3:$K$17,2,FALSE)*V5)+(VLOOKUP($W$2,[4]Prices!$J$3:$K$17,2,FALSE)*W5)+(VLOOKUP($X$2,[4]Prices!$J$3:$K$17,2,FALSE)*X5)+(VLOOKUP($Y$2,[4]Prices!$J$3:$K$17,2,FALSE)*Y5)+(VLOOKUP($Z$2,[4]Prices!$J$3:$K$17,2,FALSE)*Z5)+(VLOOKUP($AA$2,[4]Prices!$J$3:$K$17,2,FALSE)*AA5)+(VLOOKUP($AB$2,[4]Prices!$J$3:$K$17,2,FALSE)*AB5)+M5 -> 7420000 | AF5: =AD5-AE5 -> 0 | AH5: =AD5+AG5 -> 0 | AI5: =AH5/M5 -> 0 | AJ5: =AH5/AC5 -> 0
A6: 4 | I6: Ejike Nnamani (Stockiest) | J6: SER | K6: Benin | L6: SWC0888 | M6: =IFERROR(VLOOKUP($L6,[3]Consolidated!$C$9:$AC$452,27,0),0) -> 5314500 | N6: =IFERROR(VLOOKUP($L6,[3]Consolidated!$C$9:$AC$452,5,0),0) -> 24.95 | AC6: =(VLOOKUP($O$2,[4]Prices!$E$3:$K$17,2,FALSE)*O6)+(VLOOKUP($P$2,[4]Prices!$J$3:$K$17,2,FALSE)*P6)+(VLOOKUP($Q$2,[4]Prices!$J$3:$K$17,2,FALSE)*Q6)+(VLOOKUP($R$2,[4]Prices!$J$3:$K$17,2,FALSE)*R6)+(VLOOKUP($S$2,[4]Prices!$J$3:$K$17,2,FALSE)*S6)+(VLOOKUP($T$2,[4]Prices!$J$3:$K$17,2,FALSE)*T6)+(VLOOKUP($U$2,[4]Prices!$J$3:$K$17,2,FALSE)*U6)+(VLOOKUP($V$2,[4]Prices!$J$3:$K$17,2,FALSE)*V6)+(VLOOKUP($W$2,[4]Prices!$J$3:$K$17,2,FALSE)*W6)+(VLOOKUP($X$2,[4]Prices!$J$3:$K$17,2,FALSE)*X6)+(VLOOKUP($Y$2,[4]Prices!$J$3:$K$17,2,FALSE)*Y6)+(VLOOKUP($Z$2,[4]Prices!$J$3:$K$17,2,FALSE)*Z6)+(VLOOKUP($AA$2,[4]Prices!$J$3:$K$17,2,FALSE)*AA6)+(VLOOKUP($AB$2,[4]Prices!$J$3:$K$17,2,FALSE)*AB6)+M6 -> 5314500 | AF6: =AD6-AE6 -> 0 | AH6: =AD6+AG6 -> 0 | AI6: =AH6/M6 -> 0 | AJ6: =AH6/AC6 -> 0
A7: 5 | I7: Amos Abu | J7: SER | K7: Benin | L7: SWC2356 | M7: =IFERROR(VLOOKUP($L7,[3]Consolidated!$C$9:$AC$452,27,0),0) -> 13223000 | N7: =IFERROR(VLOOKUP($L7,[3]Consolidated!$C$9:$AC$452,5,0),0) -> 70 | AC7: =(VLOOKUP($O$2,[4]Prices!$E$3:$K$17,2,FALSE)*O7)+(VLOOKUP($P$2,[4]Prices!$J$3:$K$17,2,FALSE)*P7)+(VLOOKUP($Q$2,[4]Prices!$J$3:$K$17,2,FALSE)*Q7)+(VLOOKUP($R$2,[4]Prices!$J$3:$K$17,2,FALSE)*R7)+(VLOOKUP($S$2,[4]Prices!$J$3:$K$17,2,FALSE)*S7)+(VLOOKUP($T$2,[4]Prices!$J$3:$K$17,2,FALSE)*T7)+(VLOOKUP($U$2,[4]Prices!$J$3:$K$17,2,FALSE)*U7)+(VLOOKUP($V$2,[4]Prices!$J$3:$K$17,2,FALSE)*V7)+(VLOOKUP($W$2,[4]Prices!$J$3:$K$17,2,FALSE)*W7)+(VLOOKUP($X$2,[4]Prices!$J$3:$K$17,2,FALSE)*X7)+(VLOOKUP($Y$2,[4]Prices!$J$3:$K$17,2,FALSE)*Y7)+(VLOOKUP($Z$2,[4]Prices!$J$3:$K$17,2,FALSE)*Z7)+(VLOOKUP($AA$2,[4]Prices!$J$3:$K$17,2,FALSE)*AA7)+(VLOOKUP($AB$2,[4]Prices!$J$3:$K$17,2,FALSE)*AB7)+M7 -> 13223000 | AF7: =AD7-AE7 -> 0 | AH7: =AD7+AG7 -> 0 | AI7: =AH7/M7 -> 0 | AJ7: =AH7/AC7 -> 0
A8: 6 | I8: Otega Super Store | J8: SER | K8: Benin | L8: SWC2203 | M8: =IFERROR(VLOOKUP($L8,[3]Consolidated!$C$9:$AC$452,27,0),0) -> 6528900 | N8: =IFERROR(VLOOKUP($L8,[3]Consolidated!$C$9:$AC$452,5,0),0) -> 35 | AC8: =(VLOOKUP($O$2,[4]Prices!$E$3:$K$17,2,FALSE)*O8)+(VLOOKUP($P$2,[4]Prices!$J$3:$K$17,2,FALSE)*P8)+(VLOOKUP($Q$2,[4]Prices!$J$3:$K$17,2,FALSE)*Q8)+(VLOOKUP($R$2,[4]Prices!$J$3:$K$17,2,FALSE)*R8)+(VLOOKUP($S$2,[4]Prices!$J$3:$K$17,2,FALSE)*S8)+(VLOOKUP($T$2,[4]Prices!$J$3:$K$17,2,FALSE)*T8)+(VLOOKUP($U$2,[4]Prices!$J$3:$K$17,2,FALSE)*U8)+(VLOOKUP($V$2,[4]Prices!$J$3:$K$17,2,FALSE)*V8)+(VLOOKUP($W$2,[4]Prices!$J$3:$K$17,2,FALSE)*W8)+(VLOOKUP($X$2,[4]Prices!$J$3:$K$17,2,FALSE)*X8)+(VLOOKUP($Y$2,[4]Prices!$J$3:$K$17,2,FALSE)*Y8)+(VLOOKUP($Z$2,[4]Prices!$J$3:$K$17,2,FALSE)*Z8)+(VLOOKUP($AA$2,[4]Prices!$J$3:$K$17,2,FALSE)*AA8)+(VLOOKUP($AB$2,[4]Prices!$J$3:$K$17,2,FALSE)*AB8)+M8 -> 6528900 | AF8: =AD8-AE8 -> 0 | AH8: =AD8+AG8 -> 0 | AI8: =AH8/M8 -> 0 | AJ8: =AH8/AC8 -> 0
A9: 7 | I9: Madam Isaac Chukwudike (RME) | J9: SER | K9: Benin | L9: SWC1818 | M9: =IFERROR(VLOOKUP($L9,[3]Consolidated!$C$9:$AC$452,27,0),0) -> 7289100 | N9: =IFERROR(VLOOKUP($L9,[3]Consolidated!$C$9:$AC$452,5,0),0) -> 35 | AC9: =(VLOOKUP($O$2,[4]Prices!$E$3:$K$17,2,FALSE)*O9)+(VLOOKUP($P$2,[4]Prices!$J$3:$K$17,2,FALSE)*P9)+(VLOOKUP($Q$2,[4]Prices!$J$3:$K$17,2,FALSE)*Q9)+(VLOOKUP($R$2,[4]Prices!$J$3:$K$17,2,FALSE)*R9)+(VLOOKUP($S$2,[4]Prices!$J$3:$K$17,2,FALSE)*S9)+(VLOOKUP($T$2,[4]Prices!$J$3:$K$17,2,FALSE)*T9)+(VLOOKUP($U$2,[4]Prices!$J$3:$K$17,2,FALSE)*U9)+(VLOOKUP($V$2,[4]Prices!$J$3:$K$17,2,FALSE)*V9)+(VLOOKUP($W$2,[4]Prices!$J$3:$K$17,2,FALSE)*W9)+(VLOOKUP($X$2,[4]Prices!$J$3:$K$17,2,FALSE)*X9)+(VLOOKUP($Y$2,[4]Prices!$J$3:$K$17,2,FALSE)*Y9)+(VLOOKUP($Z$2,[4]Prices!$J$3:$K$17,2,FALSE)*Z9)+(VLOOKUP($AA$2,[4]Prices!$J$3:$K$17,2,FALSE)*AA9)+(VLOOKUP($AB$2,[4]Prices!$J$3:$K$17,2,FALSE)*AB9)+M9 -> 7289100 | AF9: =AD9-AE9 -> 0 | AH9: =AD9+AG9 -> 0 | AI9: =AH9/M9 -> 0 | AJ9: =AH9/AC9 -> 0
A10: 8 | I10: Madam Rosemary | J10: SER | K10: Benin | L10: SWC0033 | M10: =IFERROR(VLOOKUP($L10,[3]Consolidated!$C$9:$AC$452,27,0),0) -> 7017150 | N10: =IFERROR(VLOOKUP($L10,[3]Consolidated!$C$9:$AC$452,5,0),0) -> 35 | AC10: =(VLOOKUP($O$2,[4]Prices!$E$3:$K$17,2,FALSE)*O10)+(VLOOKUP($P$2,[4]Prices!$J$3:$K$17,2,FALSE)*P10)+(VLOOKUP($Q$2,[4]Prices!$J$3:$K$17,2,FALSE)*Q10)+(VLOOKUP($R$2,[4]Prices!$J$3:$K$17,2,FALSE)*R10)+(VLOOKUP($S$2,[4]Prices!$J$3:$K$17,2,FALSE)*S10)+(VLOOKUP($T$2,[4]Prices!$J$3:$K$17,2,FALSE)*T10)+(VLOOKUP($U$2,[4]Prices!$J$3:$K$17,2,FALSE)*U10)+(VLOOKUP($V$2,[4]Prices!$J$3:$K$17,2,FALSE)*V10)+(VLOOKUP($W$2,[4]Prices!$J$3:$K$17,2,FALSE)*W10)+(VLOOKUP($X$2,[4]Prices!$J$3:$K$17,2,FALSE)*X10)+(VLOOKUP($Y$2,[4]Prices!$J$3:$K$17,2,FALSE)*Y10)+(VLOOKUP($Z$2,[4]Prices!$J$3:$K$17,2,FALSE)*Z10)+(VLOOKUP($AA$2,[4]Prices!$J$3:$K$17,2,FALSE)*AA10)+(VLOOKUP($AB$2,[4]Prices!$J$3:$K$17,2,FALSE)*AB10)+M10 -> 7017150 | AF10: =AD10-AE10 -> 0 | AH10: =AD10+AG10 -> 0 | AI10: =AH10/M10 -> 0 | AJ10: =AH10/AC10 -> 0
A11: 9 | I11: Mr Pauluns Store (RME) | J11: SER | K11: Benin | L11: SWC1823 | M11: =IFERROR(VLOOKUP($L11,[3]Consolidated!$C$9:$AC$452,27,0),0) -> 0 | N11: =IFERROR(VLOOKUP($L11,[3]Consolidated!$C$9:$AC$452,5,0),0) -> 0 | AC11: =(VLOOKUP($O$2,[4]Prices!$E$3:$K$17,2,FALSE)*O11)+(VLOOKUP($P$2,[4]Prices!$J$3:$K$17,2,FALSE)*P11)+(VLOOKUP($Q$2,[4]Prices!$J$3:$K$17,2,FALSE)*Q11)+(VLOOKUP($R$2,[4]Prices!$J$3:$K$17,2,FALSE)*R11)+(VLOOKUP($S$2,[4]Prices!$J$3:$K$17,2,FALSE)*S11)+(VLOOKUP($T$2,[4]Prices!$J$3:$K$17,2,FALSE)*T11)+(VLOOKUP($U$2,[4]Prices!$J$3:$K$17,2,FALSE)*U11)+(VLOOKUP($V$2,[4]Prices!$J$3:$K$17,2,FALSE)*V11)+(VLOOKUP($W$2,[4]Prices!$J$3:$K$17,2,FALSE)*W11)+(VLOOKUP($X$2,[4]Prices!$J$3:$K$17,2,FALSE)*X11)+(VLOOKUP($Y$2,[4]Prices!$J$3:$K$17,2,FALSE)*Y11)+(VLOOKUP($Z$2,[4]Prices!$J$3:$K$17,2,FALSE)*Z11)+(VLOOKUP($AA$2,[4]Prices!$J$3:$K$17,2,FALSE)*AA11)+(VLOOKUP($AB$2,[4]Prices!$J$3:$K$17,2,FALSE)*AB11)+M11 -> 0 | AF11: =AD11-AE11 -> 0 | AH11: =AD11+AG11 -> 0 | AI11: =AH11/M11 -> #DIV/0! | AJ11: =AH11/AC11 -> #DIV/0!
A12: 10 | I12: Larry Happy | J12: SER | K12: Benin | L12: SWC2271 | M12: =IFERROR(VLOOKUP($L12,[3]Consolidated!$C$9:$AC$452,27,0),0) -> 7123800 | N12: =IFERROR(VLOOKUP($L12,[3]Consolidated!$C$9:$AC$452,5,0),0) -> 35 | AC12: =(VLOOKUP($O$2,[4]Prices!$E$3:$K$17,2,FALSE)*O12)+(VLOOKUP($P$2,[4]Prices!$J$3:$K$17,2,FALSE)*P12)+(VLOOKUP($Q$2,[4]Prices!$J$3:$K$17,2,FALSE)*Q12)+(VLOOKUP($R$2,[4]Prices!$J$3:$K$17,2,FALSE)*R12)+(VLOOKUP($S$2,[4]Prices!$J$3:$K$17,2,FALSE)*S12)+(VLOOKUP($T$2,[4]Prices!$J$3:$K$17,2,FALSE)*T12)+(VLOOKUP($U$2,[4]Prices!$J$3:$K$17,2,FALSE)*U12)+(VLOOKUP($V$2,[4]Prices!$J$3:$K$17,2,FALSE)*V12)+(VLOOKUP($W$2,[4]Prices!$J$3:$K$17,2,FALSE)*W12)+(VLOOKUP($X$2,[4]Prices!$J$3:$K$17,2,FALSE)*X12)+(VLOOKUP($Y$2,[4]Prices!$J$3:$K$17,2,FALSE)*Y12)+(VLOOKUP($Z$2,[4]Prices!$J$3:$K$17,2,FALSE)*Z12)+(VLOOKUP($AA$2,[4]Prices!$J$3:$K$17,2,FALSE)*AA12)+(VLOOKUP($AB$2,[4]Prices!$J$3:$K$17,2,FALSE)*AB12)+M12 -> 7123800 | AF12: =AD12-AE12 -> 0 | AH12: =AD12+AG12 -> 0 | AI12: =AH12/M12 -> 0 | AJ12: =AH12/AC12 -> 0
A13: 11 | I13: Lady Jane Integrated | J13: SER | K13: Benin | L13: SWC2174 | M13: =IFERROR(VLOOKUP($L13,[3]Consolidated!$C$9:$AC$452,27,0),0) -> 6819800 | N13: =IFERROR(VLOOKUP($L13,[3]Consolidated!$C$9:$AC$452,5,0),0) -> 35 | AC13: =(VLOOKUP($O$2,[4]Prices!$E$3:$K$17,2,FALSE)*O13)+(VLOOKUP($P$2,[4]Prices!$J$3:$K$17,2,FALSE)*P13)+(VLOOKUP($Q$2,[4]Prices!$J$3:$K$17,2,FALSE)*Q13)+(VLOOKUP($R$2,[4]Prices!$J$3:$K$17,2,FALSE)*R13)+(VLOOKUP($S$2,[4]Prices!$J$3:$K$17,2,FALSE)*S13)+(VLOOKUP($T$2,[4]Prices!$J$3:$K$17,2,FALSE)*T13)+(VLOOKUP($U$2,[4]Prices!$J$3:$K$17,2,FALSE)*U13)+(VLOOKUP($V$2,[4]Prices!$J$3:$K$17,2,FALSE)*V13)+(VLOOKUP($W$2,[4]Prices!$J$3:$K$17,2,FALSE)*W13)+(VLOOKUP($X$2,[4]Prices!$J$3:$K$17,2,FALSE)*X13)+(VLOOKUP($Y$2,[4]Prices!$J$3:$K$17,2,FALSE)*Y13)+(VLOOKUP($Z$2,[4]Prices!$J$3:$K$17,2,FALSE)*Z13)+(VLOOKUP($AA$2,[4]Prices!$J$3:$K$17,2,FALSE)*AA13)+(VLOOKUP($AB$2,[4]Prices!$J$3:$K$17,2,FALSE)*AB13)+M13 -> 6819800 | AF13: =AD13-AE13 -> 0 | AH13: =AD13+AG13 -> 0 | AI13: =AH13/M13 -> 0 | AJ13: =AH13/AC13 -> 0
A14: 12 | I14: S.K Awe | J14: SER | K14: Benin | L14: WCFA000156 | M14: =IFERROR(VLOOKUP($L14,[3]Consolidated!$C$9:$AC$452,27,0),0) -> 7014800 | N14: =IFERROR(VLOOKUP($L14,[3]Consolidated!$C$9:$AC$452,5,0),0) -> 35 | AC14: =(VLOOKUP($O$2,[4]Prices!$E$3:$K$17,2,FALSE)*O14)+(VLOOKUP($P$2,[4]Prices!$J$3:$K$17,2,FALSE)*P14)+(VLOOKUP($Q$2,[4]Prices!$J$3:$K$17,2,FALSE)*Q14)+(VLOOKUP($R$2,[4]Prices!$J$3:$K$17,2,FALSE)*R14)+(VLOOKUP($S$2,[4]Prices!$J$3:$K$17,2,FALSE)*S14)+(VLOOKUP($T$2,[4]Prices!$J$3:$K$17,2,FALSE)*T14)+(VLOOKUP($U$2,[4]Prices!$J$3:$K$17,2,FALSE)*U14)+(VLOOKUP($V$2,[4]Prices!$J$3:$K$17,2,FALSE)*V14)+(VLOOKUP($W$2,[4]Prices!$J$3:$K$17,2,FALSE)*W14)+(VLOOKUP($X$2,[4]Prices!$J$3:$K$17,2,FALSE)*X14)+(VLOOKUP($Y$2,[4]Prices!$J$3:$K$17,2,FALSE)*Y14)+(VLOOKUP($Z$2,[4]Prices!$J$3:$K$17,2,FALSE)*Z14)+(VLOOKUP($AA$2,[4]Prices!$J$3:$K$17,2,FALSE)*AA14)+(VLOOKUP($AB$2,[4]Prices!$J$3:$K$17,2,FALSE)*AB14)+M14 -> 7014800 | AF14: =AD14-AE14 -> 0 | AH14: =AD14+AG14 -> 0 | AI14: =AH14/M14 -> 0 | AJ14: =AH14/AC14 -> 0
A15: 13 | I15: Sunday Oloyede | J15: SER | K15: Benin | L15: SWC2217 | M15: =IFERROR(VLOOKUP($L15,[3]Consolidated!$C$9:$AC$452,27,0),0) -> 22573600 | N15: =IFERROR(VLOOKUP($L15,[3]Consolidated!$C$9:$AC$452,5,0),0) -> 110 | AC15: =(VLOOKUP($O$2,[4]Prices!$E$3:$K$17,2,FALSE)*O15)+(VLOOKUP($P$2,[4]Prices!$J$3:$K$17,2,FALSE)*P15)+(VLOOKUP($Q$2,[4]Prices!$J$3:$K$17,2,FALSE)*Q15)+(VLOOKUP($R$2,[4]Prices!$J$3:$K$17,2,FALSE)*R15)+(VLOOKUP($S$2,[4]Prices!$J$3:$K$17,2,FALSE)*S15)+(VLOOKUP($T$2,[4]Prices!$J$3:$K$17,2,FALSE)*T15)+(VLOOKUP($U$2,[4]Prices!$J$3:$K$17,2,FALSE)*U15)+(VLOOKUP($V$2,[4]Prices!$J$3:$K$17,2,FALSE)*V15)+(VLOOKUP($W$2,[4]Prices!$J$3:$K$17,2,FALSE)*W15)+(VLOOKUP($X$2,[4]Prices!$J$3:$K$17,2,FALSE)*X15)+(VLOOKUP($Y$2,[4]Prices!$J$3:$K$17,2,FALSE)*Y15)+(VLOOKUP($Z$2,[4]Prices!$J$3:$K$17,2,FALSE)*Z15)+(VLOOKUP($AA$2,[4]Prices!$J$3:$K$17,2,FALSE)*AA15)+(VLOOKUP($AB$2,[4]Prices!$J$3:$K$17,2,FALSE)*AB15)+M15 -> 22573600 | AF15: =AD15-AE15 -> 0 | AH15: =AD15+AG15 -> 0 | AI15: =AH15/M15 -> 0 | AJ15: =AH15/AC15 -> 0
... A30: 28 | I30: Ndukwe Ozoemelam | J30: SER | K30: Calabar | L30: SEC003550 | M30: =IFERROR(VLOOKUP($L30,[3]Consolidated!$C$9:$AC$452,27,0),0) -> 18150000 | N30: =IFERROR(VLOOKUP($L30,[3]Consolidated!$C$9:$AC$452,5,0),0) -> 70 | AC30: =(VLOOKUP($O$2,[4]Prices!$E$3:$K$17,2,FALSE)*O30)+(VLOOKUP($P$2,[4]Prices!$J$3:$K$17,2,FALSE)*P30)+(VLOOKUP($Q$2,[4]Prices!$J$3:$K$17,2,FALSE)*Q30)+(VLOOKUP($R$2,[4]Prices!$J$3:$K$17,2,FALSE)*R30)+(VLOOKUP($S$2,[4]Prices!$J$3:$K$17,2,FALSE)*S30)+(VLOOKUP($T$2,[4]Prices!$J$3:$K$17,2,FALSE)*T30)+(VLOOKUP($U$2,[4]Prices!$J$3:$K$17,2,FALSE)*U30)+(VLOOKUP($V$2,[4]Prices!$J$3:$K$17,2,FALSE)*V30)+(VLOOKUP($W$2,[4]Prices!$J$3:$K$17,2,FALSE)*W30)+(VLOOKUP($X$2,[4]Prices!$J$3:$K$17,2,FALSE)*X30)+(VLOOKUP($Y$2,[4]Prices!$J$3:$K$17,2,FALSE)*Y30)+(VLOOKUP($Z$2,[4]Prices!$J$3:$K$17,2,FALSE)*Z30)+(VLOOKUP($AA$2,[4]Prices!$J$3:$K$17,2,FALSE)*AA30)+(VLOOKUP($AB$2,[4]Prices!$J$3:$K$17,2,FALSE)*AB30)+M30 -> 18150000 | AF30: =AD30-AE30 -> 0 | AH30: =AD30+AG30 -> 0 | AI30: =AH30/M30 -> 0 | AJ30: =AH30/AC30 -> 0
A31: 29 | G31: =SUM(G3:G30) -> 0 | I31: LOVETH George Etukudo | J31: SER | K31: Calabar | L31: SEC003369 | M31: =IFERROR(VLOOKUP($L31,[3]Consolidated!$C$9:$AC$452,27,0),0) -> 22567000 | N31: =IFERROR(VLOOKUP($L31,[3]Consolidated!$C$9:$AC$452,5,0),0) -> 105 | AC31: =(VLOOKUP($O$2,[4]Prices!$E$3:$K$17,2,FALSE)*O31)+(VLOOKUP($P$2,[4]Prices!$J$3:$K$17,2,FALSE)*P31)+(VLOOKUP($Q$2,[4]Prices!$J$3:$K$17,2,FALSE)*Q31)+(VLOOKUP($R$2,[4]Prices!$J$3:$K$17,2,FALSE)*R31)+(VLOOKUP($S$2,[4]Prices!$J$3:$K$17,2,FALSE)*S31)+(VLOOKUP($T$2,[4]Prices!$J$3:$K$17,2,FALSE)*T31)+(VLOOKUP($U$2,[4]Prices!$J$3:$K$17,2,FALSE)*U31)+(VLOOKUP($V$2,[4]Prices!$J$3:$K$17,2,FALSE)*V31)+(VLOOKUP($W$2,[4]Prices!$J$3:$K$17,2,FALSE)*W31)+(VLOOKUP($X$2,[4]Prices!$J$3:$K$17,2,FALSE)*X31)+(VLOOKUP($Y$2,[4]Prices!$J$3:$K$17,2,FALSE)*Y31)+(VLOOKUP($Z$2,[4]Prices!$J$3:$K$17,2,FALSE)*Z31)+(VLOOKUP($AA$2,[4]Prices!$J$3:$K$17,2,FALSE)*AA31)+(VLOOKUP($AB$2,[4]Prices!$J$3:$K$17,2,FALSE)*AB31)+M31 -> 22567000 | AF31: =AD31-AE31 -> 0 | AH31: =AD31+AG31 -> 0 | AI31: =AH31/M31 -> 0 | AJ31: =AH31/AC31 -> 0
A32: 30 | I32: Monday Nweka | J32: SER | K32: Calabar | L32: SEC001103 | M32: =IFERROR(VLOOKUP($L32,[3]Consolidated!$C$9:$AC$452,27,0),0) -> 2091000 | N32: =IFERROR(VLOOKUP($L32,[3]Consolidated!$C$9:$AC$452,5,0),0) -> 10 | AC32: =(VLOOKUP($O$2,[4]Prices!$E$3:$K$17,2,FALSE)*O32)+(VLOOKUP($P$2,[4]Prices!$J$3:$K$17,2,FALSE)*P32)+(VLOOKUP($Q$2,[4]Prices!$J$3:$K$17,2,FALSE)*Q32)+(VLOOKUP($R$2,[4]Prices!$J$3:$K$17,2,FALSE)*R32)+(VLOOKUP($S$2,[4]Prices!$J$3:$K$17,2,FALSE)*S32)+(VLOOKUP($T$2,[4]Prices!$J$3:$K$17,2,FALSE)*T32)+(VLOOKUP($U$2,[4]Prices!$J$3:$K$17,2,FALSE)*U32)+(VLOOKUP($V$2,[4]Prices!$J$3:$K$17,2,FALSE)*V32)+(VLOOKUP($W$2,[4]Prices!$J$3:$K$17,2,FALSE)*W32)+(VLOOKUP($X$2,[4]Prices!$J$3:$K$17,2,FALSE)*X32)+(VLOOKUP($Y$2,[4]Prices!$J$3:$K$17,2,FALSE)*Y32)+(VLOOKUP($Z$2,[4]Prices!$J$3:$K$17,2,FALSE)*Z32)+(VLOOKUP($AA$2,[4]Prices!$J$3:$K$17,2,FALSE)*AA32)+(VLOOKUP($AB$2,[4]Prices!$J$3:$K$17,2,FALSE)*AB32)+M32 -> 2091000 | AF32: =AD32-AE32 -> 0 | AH32: =AD32+AG32 -> 0 | AI32: =AH32/M32 -> 0 | AJ32: =AH32/AC32 -> 0
A33: 31 | I33: Mfon Ndarake Udo (RME) | J33: SER | K33: Calabar | L33: SEC003647 | M33: =IFERROR(VLOOKUP($L33,[3]Consolidated!$C$9:$AC$452,27,0),0) -> 6180750 | N33: =IFERROR(VLOOKUP($L33,[3]Consolidated!$C$9:$AC$452,5,0),0) -> 35 | AC33: =(VLOOKUP($O$2,[4]Prices!$E$3:$K$17,2,FALSE)*O33)+(VLOOKUP($P$2,[4]Prices!$J$3:$K$17,2,FALSE)*P33)+(VLOOKUP($Q$2,[4]Prices!$J$3:$K$17,2,FALSE)*Q33)+(VLOOKUP($R$2,[4]Prices!$J$3:$K$17,2,FALSE)*R33)+(VLOOKUP($S$2,[4]Prices!$J$3:$K$17,2,FALSE)*S33)+(VLOOKUP($T$2,[4]Prices!$J$3:$K$17,2,FALSE)*T33)+(VLOOKUP($U$2,[4]Prices!$J$3:$K$17,2,FALSE)*U33)+(VLOOKUP($V$2,[4]Prices!$J$3:$K$17,2,FALSE)*V33)+(VLOOKUP($W$2,[4]Prices!$J$3:$K$17,2,FALSE)*W33)+(VLOOKUP($X$2,[4]Prices!$J$3:$K$17,2,FALSE)*X33)+(VLOOKUP($Y$2,[4]Prices!$J$3:$K$17,2,FALSE)*Y33)+(VLOOKUP($Z$2,[4]Prices!$J$3:$K$17,2,FALSE)*Z33)+(VLOOKUP($AA$2,[4]Prices!$J$3:$K$17,2,FALSE)*AA33)+(VLOOKUP($AB$2,[4]Prices!$J$3:$K$17,2,FALSE)*AB33)+M33 -> 6180750 | AF33: =AD33-AE33 -> 0 | AH33: =AD33+AG33 -> 0 | AI33: =AH33/M33 -> 0 | AJ33: =AH33/AC33 -> 0
A34: 32 | I34: EMMANUEL(Stockist) | J34: SER | K34: Calabar | L34: SEC000064 | M34: =IFERROR(VLOOKUP($L34,[3]Consolidated!$C$9:$AC$452,27,0),0) -> 1678500 | N34: =IFERROR(VLOOKUP($L34,[3]Consolidated!$C$9:$AC$452,5,0),0) -> 10 | AC34: =(VLOOKUP($O$2,[4]Prices!$E$3:$K$17,2,FALSE)*O34)+(VLOOKUP($P$2,[4]Prices!$J$3:$K$17,2,FALSE)*P34)+(VLOOKUP($Q$2,[4]Prices!$J$3:$K$17,2,FALSE)*Q34)+(VLOOKUP($R$2,[4]Prices!$J$3:$K$17,2,FALSE)*R34)+(VLOOKUP($S$2,[4]Prices!$J$3:$K$17,2,FALSE)*S34)+(VLOOKUP($T$2,[4]Prices!$J$3:$K$17,2,FALSE)*T34)+(VLOOKUP($U$2,[4]Prices!$J$3:$K$17,2,FALSE)*U34)+(VLOOKUP($V$2,[4]Prices!$J$3:$K$17,2,FALSE)*V34)+(VLOOKUP($W$2,[4]Prices!$J$3:$K$17,2,FALSE)*W34)+(VLOOKUP($X$2,[4]Prices!$J$3:$K$17,2,FALSE)*X34)+(VLOOKUP($Y$2,[4]Prices!$J$3:$K$17,2,FALSE)*Y34)+(VLOOKUP($Z$2,[4]Prices!$J$3:$K$17,2,FALSE)*Z34)+(VLOOKUP($AA$2,[4]Prices!$J$3:$K$17,2,FALSE)*AA34)+(VLOOKUP($AB$2,[4]Prices!$J$3:$K$17,2,FALSE)*AB34)+M34 -> 1678500 | AF34: =AD34-AE34 -> 0 | AH34: =AD34+AG34 -> 0 | AI34: =AH34/M34 -> 0 | AJ34: =AH34/AC34 -> 0
A35: 33 | I35: Edobong Godwin | J35: SER | K35: Calabar | L35: SEC002532 | M35: =IFERROR(VLOOKUP($L35,[3]Consolidated!$C$9:$AC$452,27,0),0) -> 7878000 | N35: =IFERROR(VLOOKUP($L35,[3]Consolidated!$C$9:$AC$452,5,0),0) -> 40 | AC35: =(VLOOKUP($O$2,[4]Prices!$E$3:$K$17,2,FALSE)*O35)+(VLOOKUP($P$2,[4]Prices!$J$3:$K$17,2,FALSE)*P35)+(VLOOKUP($Q$2,[4]Prices!$J$3:$K$17,2,FALSE)*Q35)+(VLOOKUP($R$2,[4]Prices!$J$3:$K$17,2,FALSE)*R35)+(VLOOKUP($S$2,[4]Prices!$J$3:$K$17,2,FALSE)*S35)+(VLOOKUP($T$2,[4]Prices!$J$3:$K$17,2,FALSE)*T35)+(VLOOKUP($U$2,[4]Prices!$J$3:$K$17,2,FALSE)*U35)+(VLOOKUP($V$2,[4]Prices!$J$3:$K$17,2,FALSE)*V35)+(VLOOKUP($W$2,[4]Prices!$J$3:$K$17,2,FALSE)*W35)+(VLOOKUP($X$2,[4]Prices!$J$3:$K$17,2,FALSE)*X35)+(VLOOKUP($Y$2,[4]Prices!$J$3:$K$17,2,FALSE)*Y35)+(VLOOKUP($Z$2,[4]Prices!$J$3:$K$17,2,FALSE)*Z35)+(VLOOKUP($AA$2,[4]Prices!$J$3:$K$17,2,FALSE)*AA35)+(VLOOKUP($AB$2,[4]Prices!$J$3:$K$17,2,FALSE)*AB35)+M35 -> 7878000 | AF35: =AD35-AE35 -> 0 | AH35: =AD35+AG35 -> 0 | AI35: =AH35/M35 -> 0 | AJ35: =AH35/AC35 -> 0
A36: 34 | I36: Innocent Okeke (RME) | J36: SER | K36: Calabar | L36: SEC002515 | M36: =IFERROR(VLOOKUP($L36,[3]Consolidated!$C$9:$AC$452,27,0),0) -> 7508500 | N36: =IFERROR(VLOOKUP($L36,[3]Consolidated!$C$9:$AC$452,5,0),0) -> 35 | AC36: =(VLOOKUP($O$2,[4]Prices!$E$3:$K$17,2,FALSE)*O36)+(VLOOKUP($P$2,[4]Prices!$J$3:$K$17,2,FALSE)*P36)+(VLOOKUP($Q$2,[4]Prices!$J$3:$K$17,2,FALSE)*Q36)+(VLOOKUP($R$2,[4]Prices!$J$3:$K$17,2,FALSE)*R36)+(VLOOKUP($S$2,[4]Prices!$J$3:$K$17,2,FALSE)*S36)+(VLOOKUP($T$2,[4]Prices!$J$3:$K$17,2,FALSE)*T36)+(VLOOKUP($U$2,[4]Prices!$J$3:$K$17,2,FALSE)*U36)+(VLOOKUP($V$2,[4]Prices!$J$3:$K$17,2,FALSE)*V36)+(VLOOKUP($W$2,[4]Prices!$J$3:$K$17,2,FALSE)*W36)+(VLOOKUP($X$2,[4]Prices!$J$3:$K$17,2,FALSE)*X36)+(VLOOKUP($Y$2,[4]Prices!$J$3:$K$17,2,FALSE)*Y36)+(VLOOKUP($Z$2,[4]Prices!$J$3:$K$17,2,FALSE)*Z36)+(VLOOKUP($AA$2,[4]Prices!$J$3:$K$17,2,FALSE)*AA36)+(VLOOKUP($AB$2,[4]Prices!$J$3:$K$17,2,FALSE)*AB36)+M36 -> 7508500 | AF36: =AD36-AE36 -> 0 | AH36: =AD36+AG36 -> 0 | AI36: =AH36/M36 -> 0 | AJ36: =AH36/AC36 -> 0
A37: 35 | I37: Madam Kate (RME) | J37: SER | K37: Calabar | L37: SEC001627 | M37: =IFERROR(VLOOKUP($L37,[3]Consolidated!$C$9:$AC$452,27,0),0) -> 2060000 | N37: =IFERROR(VLOOKUP($L37,[3]Consolidated!$C$9:$AC$452,5,0),0) -> 10 | AC37: =(VLOOKUP($O$2,[4]Prices!$E$3:$K$17,2,FALSE)*O37)+(VLOOKUP($P$2,[4]Prices!$J$3:$K$17,2,FALSE)*P37)+(VLOOKUP($Q$2,[4]Prices!$J$3:$K$17,2,FALSE)*Q37)+(VLOOKUP($R$2,[4]Prices!$J$3:$K$17,2,FALSE)*R37)+(VLOOKUP($S$2,[4]Prices!$J$3:$K$17,2,FALSE)*S37)+(VLOOKUP($T$2,[4]Prices!$J$3:$K$17,2,FALSE)*T37)+(VLOOKUP($U$2,[4]Prices!$J$3:$K$17,2,FALSE)*U37)+(VLOOKUP($V$2,[4]Prices!$J$3:$K$17,2,FALSE)*V37)+(VLOOKUP($W$2,[4]Prices!$J$3:$K$17,2,FALSE)*W37)+(VLOOKUP($X$2,[4]Prices!$J$3:$K$17,2,FALSE)*X37)+(VLOOKUP($Y$2,[4]Prices!$J$3:$K$17,2,FALSE)*Y37)+(VLOOKUP($Z$2,[4]Prices!$J$3:$K$17,2,FALSE)*Z37)+(VLOOKUP($AA$2,[4]Prices!$J$3:$K$17,2,FALSE)*AA37)+(VLOOKUP($AB$2,[4]Prices!$J$3:$K$17,2,FALSE)*AB37)+M37 -> 2060000 | AF37: =AD37-AE37 -> 0 | AH37: =AD37+AG37 -> 0 | AI37: =AH37/M37 -> 0 | AJ37: =AH37/AC37 -> 0
A38: 36 | I38: 0nyebros Agu Enterprises | J38: SER | K38: Calabar | L38: SEC004135 | M38: =IFERROR(VLOOKUP($L38,[3]Consolidated!$C$9:$AC$452,27,0),0) -> 9059500 | N38: =IFERROR(VLOOKUP($L38,[3]Consolidated!$C$9:$AC$452,5,0),0) -> 35 | AC38: =(VLOOKUP($O$2,[4]Prices!$E$3:$K$17,2,FALSE)*O38)+(VLOOKUP($P$2,[4]Prices!$J$3:$K$17,2,FALSE)*P38)+(VLOOKUP($Q$2,[4]Prices!$J$3:$K$17,2,FALSE)*Q38)+(VLOOKUP($R$2,[4]Prices!$J$3:$K$17,2,FALSE)*R38)+(VLOOKUP($S$2,[4]Prices!$J$3:$K$17,2,FALSE)*S38)+(VLOOKUP($T$2,[4]Prices!$J$3:$K$17,2,FALSE)*T38)+(VLOOKUP($U$2,[4]Prices!$J$3:$K$17,2,FALSE)*U38)+(VLOOKUP($V$2,[4]Prices!$J$3:$K$17,2,FALSE)*V38)+(VLOOKUP($W$2,[4]Prices!$J$3:$K$17,2,FALSE)*W38)+(VLOOKUP($X$2,[4]Prices!$J$3:$K$17,2,FALSE)*X38)+(VLOOKUP($Y$2,[4]Prices!$J$3:$K$17,2,FALSE)*Y38)+(VLOOKUP($Z$2,[4]Prices!$J$3:$K$17,2,FALSE)*Z38)+(VLOOKUP($AA$2,[4]Prices!$J$3:$K$17,2,FALSE)*AA38)+(VLOOKUP($AB$2,[4]Prices!$J$3:$K$17,2,FALSE)*AB38)+M38 -> 9059500 | AF38: =AD38-AE38 -> 0 | AH38: =AD38+AG38 -> 0 | AI38: =AH38/M38 -> 0 | AJ38: =AH38/AC38 -> 0
A39: 37 | I39: Ecowas (Stockist) | J39: SER | K39: Calabar | L39: SEC000028 | M39: =IFERROR(VLOOKUP($L39,[3]Consolidated!$C$9:$AC$452,27,0),0) -> 8251000 | N39: =IFERROR(VLOOKUP($L39,[3]Consolidated!$C$9:$AC$452,5,0),0) -> 40 | AC39: =(VLOOKUP($O$2,[4]Prices!$E$3:$K$17,2,FALSE)*O39)+(VLOOKUP($P$2,[4]Prices!$J$3:$K$17,2,FALSE)*P39)+(VLOOKUP($Q$2,[4]Prices!$J$3:$K$17,2,FALSE)*Q39)+(VLOOKUP($R$2,[4]Prices!$J$3:$K$17,2,FALSE)*R39)+(VLOOKUP($S$2,[4]Prices!$J$3:$K$17,2,FALSE)*S39)+(VLOOKUP($T$2,[4]Prices!$J$3:$K$17,2,FALSE)*T39)+(VLOOKUP($U$2,[4]Prices!$J$3:$K$17,2,FALSE)*U39)+(VLOOKUP($V$2,[4]Prices!$J$3:$K$17,2,FALSE)*V39)+(VLOOKUP($W$2,[4]Prices!$J$3:$K$17,2,FALSE)*W39)+(VLOOKUP($X$2,[4]Prices!$J$3:$K$17,2,FALSE)*X39)+(VLOOKUP($Y$2,[4]Prices!$J$3:$K$17,2,FALSE)*Y39)+(VLOOKUP($Z$2,[4]Prices!$J$3:$K$17,2,FALSE)*Z39)+(VLOOKUP($AA$2,[4]Prices!$J$3:$K$17,2,FALSE)*AA39)+(VLOOKUP($AB$2,[4]Prices!$J$3:$K$17,2,FALSE)*AB39)+M39 -> 8251000 | AF39: =AD39-AE39 -> 0 | AH39: =AD39+AG39 -> 0 | AI39: =AH39/M39 -> 0 | AJ39: =AH39/AC39 -> 0
A40: 38 | I40: EL & EL Wine Shop | J40: SER | K40: Calabar | L40: SEC003659 | M40: =IFERROR(VLOOKUP($L40,[3]Consolidated!$C$9:$AC$452,27,0),0) -> 15659000 | N40: =IFERROR(VLOOKUP($L40,[3]Consolidated!$C$9:$AC$452,5,0),0) -> 60 | AC40: =(VLOOKUP($O$2,[4]Prices!$E$3:$K$17,2,FALSE)*O40)+(VLOOKUP($P$2,[4]Prices!$J$3:$K$17,2,FALSE)*P40)+(VLOOKUP($Q$2,[4]Prices!$J$3:$K$17,2,FALSE)*Q40)+(VLOOKUP($R$2,[4]Prices!$J$3:$K$17,2,FALSE)*R40)+(VLOOKUP($S$2,[4]Prices!$J$3:$K$17,2,FALSE)*S40)+(VLOOKUP($T$2,[4]Prices!$J$3:$K$17,2,FALSE)*T40)+(VLOOKUP($U$2,[4]Prices!$J$3:$K$17,2,FALSE)*U40)+(VLOOKUP($V$2,[4]Prices!$J$3:$K$17,2,FALSE)*V40)+(VLOOKUP($W$2,[4]Prices!$J$3:$K$17,2,FALSE)*W40)+(VLOOKUP($X$2,[4]Prices!$J$3:$K$17,2,FALSE)*X40)+(VLOOKUP($Y$2,[4]Prices!$J$3:$K$17,2,FALSE)*Y40)+(VLOOKUP($Z$2,[4]Prices!$J$3:$K$17,2,FALSE)*Z40)+(VLOOKUP($AA$2,[4]Prices!$J$3:$K$17,2,FALSE)*AA40)+(VLOOKUP($AB$2,[4]Prices!$J$3:$K$17,2,FALSE)*AB40)+M40 -> 15659000 | AF40: =AD40-AE40 -> 0 | AH40: =AD40+AG40 -> 0 | AI40: =AH40/M40 -> 0 | AJ40: =AH40/AC40 -> 0
A41: 39 | I41: Ikechi Nwabubani | J41: SER | K41: Calabar | L41: SEC003658 | M41: =IFERROR(VLOOKUP($L41,[3]Consolidated!$C$9:$AC$452,27,0),0) -> 2615000 | N41: =IFERROR(VLOOKUP($L41,[3]Consolidated!$C$9:$AC$452,5,0),0) -> 10 | AC41: =(VLOOKUP($O$2,[4]Prices!$E$3:$K$17,2,FALSE)*O41)+(VLOOKUP($P$2,[4]Prices!$J$3:$K$17,2,FALSE)*P41)+(VLOOKUP($Q$2,[4]Prices!$J$3:$K$17,2,FALSE)*Q41)+(VLOOKUP($R$2,[4]Prices!$J$3:$K$17,2,FALSE)*R41)+(VLOOKUP($S$2,[4]Prices!$J$3:$K$17,2,FALSE)*S41)+(VLOOKUP($T$2,[4]Prices!$J$3:$K$17,2,FALSE)*T41)+(VLOOKUP($U$2,[4]Prices!$J$3:$K$17,2,FALSE)*U41)+(VLOOKUP($V$2,[4]Prices!$J$3:$K$17,2,FALSE)*V41)+(VLOOKUP($W$2,[4]Prices!$J$3:$K$17,2,FALSE)*W41)+(VLOOKUP($X$2,[4]Prices!$J$3:$K$17,2,FALSE)*X41)+(VLOOKUP($Y$2,[4]Prices!$J$3:$K$17,2,FALSE)*Y41)+(VLOOKUP($Z$2,[4]Prices!$J$3:$K$17,2,FALSE)*Z41)+(VLOOKUP($AA$2,[4]Prices!$J$3:$K$17,2,FALSE)*AA41)+(VLOOKUP($AB$2,[4]Prices!$J$3:$K$17,2,FALSE)*AB41)+M41 -> 2615000 | AF41: =AD41-AE41 -> 0 | AH41: =AD41+AG41 -> 0 | AI41: =AH41/M41 -> 0 | AJ41: =AH41/AC41 -> 0
A42: 40 | I42: GMTC | J42: SER | K42: Calabar | L42: SEC003729 | M42: =IFERROR(VLOOKUP($L42,[3]Consolidated!$C$9:$AC$452,27,0),0) -> 1838500 | N42: =IFERROR(VLOOKUP($L42,[3]Consolidated!$C$9:$AC$452,5,0),0) -> 10 | AC42: =(VLOOKUP($O$2,[4]Prices!$E$3:$K$17,2,FALSE)*O42)+(VLOOKUP($P$2,[4]Prices!$J$3:$K$17,2,FALSE)*P42)+(VLOOKUP($Q$2,[4]Prices!$J$3:$K$17,2,FALSE)*Q42)+(VLOOKUP($R$2,[4]Prices!$J$3:$K$17,2,FALSE)*R42)+(VLOOKUP($S$2,[4]Prices!$J$3:$K$17,2,FALSE)*S42)+(VLOOKUP($T$2,[4]Prices!$J$3:$K$17,2,FALSE)*T42)+(VLOOKUP($U$2,[4]Prices!$J$3:$K$17,2,FALSE)*U42)+(VLOOKUP($V$2,[4]Prices!$J$3:$K$17,2,FALSE)*V42)+(VLOOKUP($W$2,[4]Prices!$J$3:$K$17,2,FALSE)*W42)+(VLOOKUP($X$2,[4]Prices!$J$3:$K$17,2,FALSE)*X42)+(VLOOKUP($Y$2,[4]Prices!$J$3:$K$17,2,FALSE)*Y42)+(VLOOKUP($Z$2,[4]Prices!$J$3:$K$17,2,FALSE)*Z42)+(VLOOKUP($AA$2,[4]Prices!$J$3:$K$17,2,FALSE)*AA42)+(VLOOKUP($AB$2,[4]Prices!$J$3:$K$17,2,FALSE)*AB42)+M42 -> 1838500 | AF42: =AD42-AE42 -> 0 | AH42: =AD42+AG42 -> 0 | AI42: =AH42/M42 -> 0 | AJ42: =AH42/AC42 -> 0
A43: 41 | I43: Mr.Onyekachi Nwokocha | J43: SER | K43: Calabar | L43: SEC004010 | M43: =IFERROR(VLOOKUP($L43,[3]Consolidated!$C$9:$AC$452,27,0),0) -> 2314000 | N43: =IFERROR(VLOOKUP($L43,[3]Consolidated!$C$9:$AC$452,5,0),0) -> 10 | AC43: =(VLOOKUP($O$2,[4]Prices!$E$3:$K$17,2,FALSE)*O43)+(VLOOKUP($P$2,[4]Prices!$J$3:$K$17,2,FALSE)*P43)+(VLOOKUP($Q$2,[4]Prices!$J$3:$K$17,2,FALSE)*Q43)+(VLOOKUP($R$2,[4]Prices!$J$3:$K$17,2,FALSE)*R43)+(VLOOKUP($S$2,[4]Prices!$J$3:$K$17,2,FALSE)*S43)+(VLOOKUP($T$2,[4]Prices!$J$3:$K$17,2,FALSE)*T43)+(VLOOKUP($U$2,[4]Prices!$J$3:$K$17,2,FALSE)*U43)+(VLOOKUP($V$2,[4]Prices!$J$3:$K$17,2,FALSE)*V43)+(VLOOKUP($W$2,[4]Prices!$J$3:$K$17,2,FALSE)*W43)+(VLOOKUP($X$2,[4]Prices!$J$3:$K$17,2,FALSE)*X43)+(VLOOKUP($Y$2,[4]Prices!$J$3:$K$17,2,FALSE)*Y43)+(VLOOKUP($Z$2,[4]Prices!$J$3:$K$17,2,FALSE)*Z43)+(VLOOKUP($AA$2,[4]Prices!$J$3:$K$17,2,FALSE)*AA43)+(VLOOKUP($AB$2,[4]Prices!$J$3:$K$17,2,FALSE)*AB43)+M43 -> 2314000 | AF43: =AD43-AE43 -> 0 | AH43: =AD43+AG43 -> 0 | AI43: =AH43/M43 -> 0 | AJ43: =AH43/AC43 -> 0
... A114: 112 | I114: UGOMENDE | J114: SER | K114: PH | L114: SEC003922 | M114: =IFERROR(VLOOKUP($L114,[3]Consolidated!$C$9:$AC$452,27,0),0) -> 7721400 | N114: =IFERROR(VLOOKUP($L114,[3]Consolidated!$C$9:$AC$452,5,0),0) -> 35 | AC114: =(VLOOKUP($O$2,[4]Prices!$E$3:$K$17,2,FALSE)*O114)+(VLOOKUP($P$2,[4]Prices!$J$3:$K$17,2,FALSE)*P114)+(VLOOKUP($Q$2,[4]Prices!$J$3:$K$17,2,FALSE)*Q114)+(VLOOKUP($R$2,[4]Prices!$J$3:$K$17,2,FALSE)*R114)+(VLOOKUP($S$2,[4]Prices!$J$3:$K$17,2,FALSE)*S114)+(VLOOKUP($T$2,[4]Prices!$J$3:$K$17,2,FALSE)*T114)+(VLOOKUP($U$2,[4]Prices!$J$3:$K$17,2,FALSE)*U114)+(VLOOKUP($V$2,[4]Prices!$J$3:$K$17,2,FALSE)*V114)+(VLOOKUP($W$2,[4]Prices!$J$3:$K$17,2,FALSE)*W114)+(VLOOKUP($X$2,[4]Prices!$J$3:$K$17,2,FALSE)*X114)+(VLOOKUP($Y$2,[4]Prices!$J$3:$K$17,2,FALSE)*Y114)+(VLOOKUP($Z$2,[4]Prices!$J$3:$K$17,2,FALSE)*Z114)+(VLOOKUP($AA$2,[4]Prices!$J$3:$K$17,2,FALSE)*AA114)+(VLOOKUP($AB$2,[4]Prices!$J$3:$K$17,2,FALSE)*AB114)+M114 -> 7721400 | AF114: =AD114-AE114 -> 0 | AH114: =AD114+AG114 -> 0 | AI114: =AH114/M114 -> 0 | AJ114: =AH114/AC114 -> 0
A115: 113 | I115: Issa Lukmon Taiwo | J115: SWR | K115: Agege | L115: LAC3005 | M115: =IFERROR(VLOOKUP($L115,[3]Consolidated!$C$9:$AC$452,27,0),0) -> 29059500 | N115: =IFERROR(VLOOKUP($L115,[3]Consolidated!$C$9:$AC$452,5,0),0) -> 151 | AC115: =(VLOOKUP($O$2,[4]Prices!$E$3:$K$17,2,FALSE)*O115)+(VLOOKUP($P$2,[4]Prices!$J$3:$K$17,2,FALSE)*P115)+(VLOOKUP($Q$2,[4]Prices!$J$3:$K$17,2,FALSE)*Q115)+(VLOOKUP($R$2,[4]Prices!$J$3:$K$17,2,FALSE)*R115)+(VLOOKUP($S$2,[4]Prices!$J$3:$K$17,2,FALSE)*S115)+(VLOOKUP($T$2,[4]Prices!$J$3:$K$17,2,FALSE)*T115)+(VLOOKUP($U$2,[4]Prices!$J$3:$K$17,2,FALSE)*U115)+(VLOOKUP($V$2,[4]Prices!$J$3:$K$17,2,FALSE)*V115)+(VLOOKUP($W$2,[4]Prices!$J$3:$K$17,2,FALSE)*W115)+(VLOOKUP($X$2,[4]Prices!$J$3:$K$17,2,FALSE)*X115)+(VLOOKUP($Y$2,[4]Prices!$J$3:$K$17,2,FALSE)*Y115)+(VLOOKUP($Z$2,[4]Prices!$J$3:$K$17,2,FALSE)*Z115)+(VLOOKUP($AA$2,[4]Prices!$J$3:$K$17,2,FALSE)*AA115)+(VLOOKUP($AB$2,[4]Prices!$J$3:$K$17,2,FALSE)*AB115)+M115 -> 29059500 | AD115: 5298000 | AF115: =AD115-AE115 -> 5298000 | AH115: =AD115+AG115 -> 5298000 | AI115: =AH115/M115 -> 0.18231559 | AJ115: =AH115/AC115 -> 0.18231559
A116: 114 | I116: Oreofe Store (RME) | J116: SWR | K116: Agege | L116: LAC1611 | M116: =IFERROR(VLOOKUP($L116,[3]Consolidated!$C$9:$AC$452,27,0),0) -> 9265000 | N116: =IFERROR(VLOOKUP($L116,[3]Consolidated!$C$9:$AC$452,5,0),0) -> 48 | AC116: =(VLOOKUP($O$2,[4]Prices!$E$3:$K$17,2,FALSE)*O116)+(VLOOKUP($P$2,[4]Prices!$J$3:$K$17,2,FALSE)*P116)+(VLOOKUP($Q$2,[4]Prices!$J$3:$K$17,2,FALSE)*Q116)+(VLOOKUP($R$2,[4]Prices!$J$3:$K$17,2,FALSE)*R116)+(VLOOKUP($S$2,[4]Prices!$J$3:$K$17,2,FALSE)*S116)+(VLOOKUP($T$2,[4]Prices!$J$3:$K$17,2,FALSE)*T116)+(VLOOKUP($U$2,[4]Prices!$J$3:$K$17,2,FALSE)*U116)+(VLOOKUP($V$2,[4]Prices!$J$3:$K$17,2,FALSE)*V116)+(VLOOKUP($W$2,[4]Prices!$J$3:$K$17,2,FALSE)*W116)+(VLOOKUP($X$2,[4]Prices!$J$3:$K$17,2,FALSE)*X116)+(VLOOKUP($Y$2,[4]Prices!$J$3:$K$17,2,FALSE)*Y116)+(VLOOKUP($Z$2,[4]Prices!$J$3:$K$17,2,FALSE)*Z116)+(VLOOKUP($AA$2,[4]Prices!$J$3:$K$17,2,FALSE)*AA116)+(VLOOKUP($AB$2,[4]Prices!$J$3:$K$17,2,FALSE)*AB116)+M116 -> 9265000 | AD116: 1882500 | AF116: =AD116-AE116 -> 1882500 | AH116: =AD116+AG116 -> 1882500 | AI116: =AH116/M116 -> 0.20318403 | AJ116: =AH116/AC116 -> 0.20318403
A117: 115 | I117: Amah Store (RME) | J117: SWR | K117: Agege | L117: LAC0312 | M117: =IFERROR(VLOOKUP($L117,[3]Consolidated!$C$9:$AC$452,27,0),0) -> 0 | N117: =IFERROR(VLOOKUP($L117,[3]Consolidated!$C$9:$AC$452,5,0),0) -> 0 | AC117: =(VLOOKUP($O$2,[4]Prices!$E$3:$K$17,2,FALSE)*O117)+(VLOOKUP($P$2,[4]Prices!$J$3:$K$17,2,FALSE)*P117)+(VLOOKUP($Q$2,[4]Prices!$J$3:$K$17,2,FALSE)*Q117)+(VLOOKUP($R$2,[4]Prices!$J$3:$K$17,2,FALSE)*R117)+(VLOOKUP($S$2,[4]Prices!$J$3:$K$17,2,FALSE)*S117)+(VLOOKUP($T$2,[4]Prices!$J$3:$K$17,2,FALSE)*T117)+(VLOOKUP($U$2,[4]Prices!$J$3:$K$17,2,FALSE)*U117)+(VLOOKUP($V$2,[4]Prices!$J$3:$K$17,2,FALSE)*V117)+(VLOOKUP($W$2,[4]Prices!$J$3:$K$17,2,FALSE)*W117)+(VLOOKUP($X$2,[4]Prices!$J$3:$K$17,2,FALSE)*X117)+(VLOOKUP($Y$2,[4]Prices!$J$3:$K$17,2,FALSE)*Y117)+(VLOOKUP($Z$2,[4]Prices!$J$3:$K$17,2,FALSE)*Z117)+(VLOOKUP($AA$2,[4]Prices!$J$3:$K$17,2,FALSE)*AA117)+(VLOOKUP($AB$2,[4]Prices!$J$3:$K$17,2,FALSE)*AB117)+M117 -> 0 | AD117: 0 | AF117: =AD117-AE117 -> 0 | AH117: =AD117+AG117 -> 0 | AI117: =AH117/M117 -> #DIV/0! | AJ117: =AH117/AC117 -> #DIV/0!
A118: 116 | I118: maman moji | J118: SWR | K118: Agege | L118: LAC0173 | M118: =IFERROR(VLOOKUP($L118,[3]Consolidated!$C$9:$AC$452,27,0),0) -> 4464000 | N118: =IFERROR(VLOOKUP($L118,[3]Consolidated!$C$9:$AC$452,5,0),0) -> 22 | AC118: =(VLOOKUP($O$2,[4]Prices!$E$3:$K$17,2,FALSE)*O118)+(VLOOKUP($P$2,[4]Prices!$J$3:$K$17,2,FALSE)*P118)+(VLOOKUP($Q$2,[4]Prices!$J$3:$K$17,2,FALSE)*Q118)+(VLOOKUP($R$2,[4]Prices!$J$3:$K$17,2,FALSE)*R118)+(VLOOKUP($S$2,[4]Prices!$J$3:$K$17,2,FALSE)*S118)+(VLOOKUP($T$2,[4]Prices!$J$3:$K$17,2,FALSE)*T118)+(VLOOKUP($U$2,[4]Prices!$J$3:$K$17,2,FALSE)*U118)+(VLOOKUP($V$2,[4]Prices!$J$3:$K$17,2,FALSE)*V118)+(VLOOKUP($W$2,[4]Prices!$J$3:$K$17,2,FALSE)*W118)+(VLOOKUP($X$2,[4]Prices!$J$3:$K$17,2,FALSE)*X118)+(VLOOKUP($Y$2,[4]Prices!$J$3:$K$17,2,FALSE)*Y118)+(VLOOKUP($Z$2,[4]Prices!$J$3:$K$17,2,FALSE)*Z118)+(VLOOKUP($AA$2,[4]Prices!$J$3:$K$17,2,FALSE)*AA118)+(VLOOKUP($AB$2,[4]Prices!$J$3:$K$17,2,FALSE)*AB118)+M118 -> 4464000 | AD118: 709750 | AF118: =AD118-AE118 -> 709750 | AH118: =AD118+AG118 -> 709750 | AI118: =AH118/M118 -> 0.15899418 | AJ118: =AH118/AC118 -> 0.15899418
A119: 117 | I119: Jay Investment | J119: SWR | K119: Agege | L119: LAC3836 | M119: =IFERROR(VLOOKUP($L119,[3]Consolidated!$C$9:$AC$452,27,0),0) -> 5022500 | N119: =IFERROR(VLOOKUP($L119,[3]Consolidated!$C$9:$AC$452,5,0),0) -> 26 | AC119: =(VLOOKUP($O$2,[4]Prices!$E$3:$K$17,2,FALSE)*O119)+(VLOOKUP($P$2,[4]Prices!$J$3:$K$17,2,FALSE)*P119)+(VLOOKUP($Q$2,[4]Prices!$J$3:$K$17,2,FALSE)*Q119)+(VLOOKUP($R$2,[4]Prices!$J$3:$K$17,2,FALSE)*R119)+(VLOOKUP($S$2,[4]Prices!$J$3:$K$17,2,FALSE)*S119)+(VLOOKUP($T$2,[4]Prices!$J$3:$K$17,2,FALSE)*T119)+(VLOOKUP($U$2,[4]Prices!$J$3:$K$17,2,FALSE)*U119)+(VLOOKUP($V$2,[4]Prices!$J$3:$K$17,2,FALSE)*V119)+(VLOOKUP($W$2,[4]Prices!$J$3:$K$17,2,FALSE)*W119)+(VLOOKUP($X$2,[4]Prices!$J$3:$K$17,2,FALSE)*X119)+(VLOOKUP($Y$2,[4]Prices!$J$3:$K$17,2,FALSE)*Y119)+(VLOOKUP($Z$2,[4]Prices!$J$3:$K$17,2,FALSE)*Z119)+(VLOOKUP($AA$2,[4]Prices!$J$3:$K$17,2,FALSE)*AA119)+(VLOOKUP($AB$2,[4]Prices!$J$3:$K$17,2,FALSE)*AB119)+M119 -> 5022500 | AD119: 825000 | AF119: =AD119-AE119 -> 825000 | AH119: =AD119+AG119 -> 825000 | AI119: =AH119/M119 -> 0.16426083 | AJ119: =AH119/AC119 -> 0.16426083
A120: 118 | I120: Oluwadamilare Unique Venture | J120: SWR | K120: Agege | L120: LAC3902 | M120: =IFERROR(VLOOKUP($L120,[3]Consolidated!$C$9:$AC$452,27,0),0) -> 5232500 | N120: =IFERROR(VLOOKUP($L120,[3]Consolidated!$C$9:$AC$452,5,0),0) -> 26 | AC120: =(VLOOKUP($O$2,[4]Prices!$E$3:$K$17,2,FALSE)*O120)+(VLOOKUP($P$2,[4]Prices!$J$3:$K$17,2,FALSE)*P120)+(VLOOKUP($Q$2,[4]Prices!$J$3:$K$17,2,FALSE)*Q120)+(VLOOKUP($R$2,[4]Prices!$J$3:$K$17,2,FALSE)*R120)+(VLOOKUP($S$2,[4]Prices!$J$3:$K$17,2,FALSE)*S120)+(VLOOKUP($T$2,[4]Prices!$J$3:$K$17,2,FALSE)*T120)+(VLOOKUP($U$2,[4]Prices!$J$3:$K$17,2,FALSE)*U120)+(VLOOKUP($V$2,[4]Prices!$J$3:$K$17,2,FALSE)*V120)+(VLOOKUP($W$2,[4]Prices!$J$3:$K$17,2,FALSE)*W120)+(VLOOKUP($X$2,[4]Prices!$J$3:$K$17,2,FALSE)*X120)+(VLOOKUP($Y$2,[4]Prices!$J$3:$K$17,2,FALSE)*Y120)+(VLOOKUP($Z$2,[4]Prices!$J$3:$K$17,2,FALSE)*Z120)+(VLOOKUP($AA$2,[4]Prices!$J$3:$K$17,2,FALSE)*AA120)+(VLOOKUP($AB$2,[4]Prices!$J$3:$K$17,2,FALSE)*AB120)+M120 -> 5232500 | AD120: 0 | AF120: =AD120-AE120 -> 0 | AH120: =AD120+AG120 -> 0 | AI120: =AH120/M120 -> 0 | AJ120: =AH120/AC120 -> 0
A121: 119 | I121: Samuel Bankole | J121: SWR | K121: Agege | L121: LAC3975 | M121: =IFERROR(VLOOKUP($L121,[3]Consolidated!$C$9:$AC$452,27,0),0) -> 11372000 | N121: =IFERROR(VLOOKUP($L121,[3]Consolidated!$C$9:$AC$452,5,0),0) -> 55 | AC121: =(VLOOKUP($O$2,[4]Prices!$E$3:$K$17,2,FALSE)*O121)+(VLOOKUP($P$2,[4]Prices!$J$3:$K$17,2,FALSE)*P121)+(VLOOKUP($Q$2,[4]Prices!$J$3:$K$17,2,FALSE)*Q121)+(VLOOKUP($R$2,[4]Prices!$J$3:$K$17,2,FALSE)*R121)+(VLOOKUP($S$2,[4]Prices!$J$3:$K$17,2,FALSE)*S121)+(VLOOKUP($T$2,[4]Prices!$J$3:$K$17,2,FALSE)*T121)+(VLOOKUP($U$2,[4]Prices!$J$3:$K$17,2,FALSE)*U121)+(VLOOKUP($V$2,[4]Prices!$J$3:$K$17,2,FALSE)*V121)+(VLOOKUP($W$2,[4]Prices!$J$3:$K$17,2,FALSE)*W121)+(VLOOKUP($X$2,[4]Prices!$J$3:$K$17,2,FALSE)*X121)+(VLOOKUP($Y$2,[4]Prices!$J$3:$K$17,2,FALSE)*Y121)+(VLOOKUP($Z$2,[4]Prices!$J$3:$K$17,2,FALSE)*Z121)+(VLOOKUP($AA$2,[4]Prices!$J$3:$K$17,2,FALSE)*AA121)+(VLOOKUP($AB$2,[4]Prices!$J$3:$K$17,2,FALSE)*AB121)+M121 -> 11372000 | AD121: 1736000 | AF121: =AD121-AE121 -> 1736000 | AH121: =AD121+AG121 -> 1736000 | AI121: =AH121/M121 -> 0.15265565 | AJ121: =AH121/AC121 -> 0.15265565
A122: 120 | I122: Suwanik Store (RME) | J122: SWR | K122: Agege | L122: LAC0313 | M122: =IFERROR(VLOOKUP($L122,[3]Consolidated!$C$9:$AC$452,27,0),0) -> 0 | N122: =IFERROR(VLOOKUP($L122,[3]Consolidated!$C$9:$AC$452,5,0),0) -> 0 | AC122: =(VLOOKUP($O$2,[4]Prices!$E$3:$K$17,2,FALSE)*O122)+(VLOOKUP($P$2,[4]Prices!$J$3:$K$17,2,FALSE)*P122)+(VLOOKUP($Q$2,[4]Prices!$J$3:$K$17,2,FALSE)*Q122)+(VLOOKUP($R$2,[4]Prices!$J$3:$K$17,2,FALSE)*R122)+(VLOOKUP($S$2,[4]Prices!$J$3:$K$17,2,FALSE)*S122)+(VLOOKUP($T$2,[4]Prices!$J$3:$K$17,2,FALSE)*T122)+(VLOOKUP($U$2,[4]Prices!$J$3:$K$17,2,FALSE)*U122)+(VLOOKUP($V$2,[4]Prices!$J$3:$K$17,2,FALSE)*V122)+(VLOOKUP($W$2,[4]Prices!$J$3:$K$17,2,FALSE)*W122)+(VLOOKUP($X$2,[4]Prices!$J$3:$K$17,2,FALSE)*X122)+(VLOOKUP($Y$2,[4]Prices!$J$3:$K$17,2,FALSE)*Y122)+(VLOOKUP($Z$2,[4]Prices!$J$3:$K$17,2,FALSE)*Z122)+(VLOOKUP($AA$2,[4]Prices!$J$3:$K$17,2,FALSE)*AA122)+(VLOOKUP($AB$2,[4]Prices!$J$3:$K$17,2,FALSE)*AB122)+M122 -> 0 | AD122: 0 | AF122: =AD122-AE122 -> 0 | AH122: =AD122+AG122 -> 0 | AI122: =AH122/M122 -> #DIV/0! | AJ122: =AH122/AC122 -> #DIV/0!
A123: 121 | I123: Iya Ebube | J123: SWR | K123: Agege | L123: LAC4187 | M123: =IFERROR(VLOOKUP($L123,[3]Consolidated!$C$9:$AC$452,27,0),0) -> 4142500 | N123: =IFERROR(VLOOKUP($L123,[3]Consolidated!$C$9:$AC$452,5,0),0) -> 20 | AC123: =(VLOOKUP($O$2,[4]Prices!$E$3:$K$17,2,FALSE)*O123)+(VLOOKUP($P$2,[4]Prices!$J$3:$K$17,2,FALSE)*P123)+(VLOOKUP($Q$2,[4]Prices!$J$3:$K$17,2,FALSE)*Q123)+(VLOOKUP($R$2,[4]Prices!$J$3:$K$17,2,FALSE)*R123)+(VLOOKUP($S$2,[4]Prices!$J$3:$K$17,2,FALSE)*S123)+(VLOOKUP($T$2,[4]Prices!$J$3:$K$17,2,FALSE)*T123)+(VLOOKUP($U$2,[4]Prices!$J$3:$K$17,2,FALSE)*U123)+(VLOOKUP($V$2,[4]Prices!$J$3:$K$17,2,FALSE)*V123)+(VLOOKUP($W$2,[4]Prices!$J$3:$K$17,2,FALSE)*W123)+(VLOOKUP($X$2,[4]Prices!$J$3:$K$17,2,FALSE)*X123)+(VLOOKUP($Y$2,[4]Prices!$J$3:$K$17,2,FALSE)*Y123)+(VLOOKUP($Z$2,[4]Prices!$J$3:$K$17,2,FALSE)*Z123)+(VLOOKUP($AA$2,[4]Prices!$J$3:$K$17,2,FALSE)*AA123)+(VLOOKUP($AB$2,[4]Prices!$J$3:$K$17,2,FALSE)*AB123)+M123 -> 4142500 | AD123: 825000 | AF123: =AD123-AE123 -> 825000 | AH123: =AD123+AG123 -> 825000 | AI123: =AH123/M123 -> 0.1991551 | AJ123: =AH123/AC123 -> 0.1991551
A124: 122 | I124: Shivarest vnture Ltd | J124: SWR | K124: Agege | L124: LAC3667 | M124: =IFERROR(VLOOKUP($L124,[3]Consolidated!$C$9:$AC$452,27,0),0) -> 0 | N124: =IFERROR(VLOOKUP($L124,[3]Consolidated!$C$9:$AC$452,5,0),0) -> 0 | AC124: =(VLOOKUP($O$2,[4]Prices!$E$3:$K$17,2,FALSE)*O124)+(VLOOKUP($P$2,[4]Prices!$J$3:$K$17,2,FALSE)*P124)+(VLOOKUP($Q$2,[4]Prices!$J$3:$K$17,2,FALSE)*Q124)+(VLOOKUP($R$2,[4]Prices!$J$3:$K$17,2,FALSE)*R124)+(VLOOKUP($S$2,[4]Prices!$J$3:$K$17,2,FALSE)*S124)+(VLOOKUP($T$2,[4]Prices!$J$3:$K$17,2,FALSE)*T124)+(VLOOKUP($U$2,[4]Prices!$J$3:$K$17,2,FALSE)*U124)+(VLOOKUP($V$2,[4]Prices!$J$3:$K$17,2,FALSE)*V124)+(VLOOKUP($W$2,[4]Prices!$J$3:$K$17,2,FALSE)*W124)+(VLOOKUP($X$2,[4]Prices!$J$3:$K$17,2,FALSE)*X124)+(VLOOKUP($Y$2,[4]Prices!$J$3:$K$17,2,FALSE)*Y124)+(VLOOKUP($Z$2,[4]Prices!$J$3:$K$17,2,FALSE)*Z124)+(VLOOKUP($AA$2,[4]Prices!$J$3:$K$17,2,FALSE)*AA124)+(VLOOKUP($AB$2,[4]Prices!$J$3:$K$17,2,FALSE)*AB124)+M124 -> 0 | AD124: 0 | AF124: =AD124-AE124 -> 0 | AH124: =AD124+AG124 -> 0 | AI124: =AH124/M124 -> #DIV/0! | AJ124: =AH124/AC124 -> #DIV/0!
A125: 123 | I125: Over to God Stores (RME) | J125: SWR | K125: Agege | L125: LAC1567 | M125: =IFERROR(VLOOKUP($L125,[3]Consolidated!$C$9:$AC$452,27,0),0) -> 23345500 | N125: =IFERROR(VLOOKUP($L125,[3]Consolidated!$C$9:$AC$452,5,0),0) -> 121 | AC125: =(VLOOKUP($O$2,[4]Prices!$E$3:$K$17,2,FALSE)*O125)+(VLOOKUP($P$2,[4]Prices!$J$3:$K$17,2,FALSE)*P125)+(VLOOKUP($Q$2,[4]Prices!$J$3:$K$17,2,FALSE)*Q125)+(VLOOKUP($R$2,[4]Prices!$J$3:$K$17,2,FALSE)*R125)+(VLOOKUP($S$2,[4]Prices!$J$3:$K$17,2,FALSE)*S125)+(VLOOKUP($T$2,[4]Prices!$J$3:$K$17,2,FALSE)*T125)+(VLOOKUP($U$2,[4]Prices!$J$3:$K$17,2,FALSE)*U125)+(VLOOKUP($V$2,[4]Prices!$J$3:$K$17,2,FALSE)*V125)+(VLOOKUP($W$2,[4]Prices!$J$3:$K$17,2,FALSE)*W125)+(VLOOKUP($X$2,[4]Prices!$J$3:$K$17,2,FALSE)*X125)+(VLOOKUP($Y$2,[4]Prices!$J$3:$K$17,2,FALSE)*Y125)+(VLOOKUP($Z$2,[4]Prices!$J$3:$K$17,2,FALSE)*Z125)+(VLOOKUP($AA$2,[4]Prices!$J$3:$K$17,2,FALSE)*AA125)+(VLOOKUP($AB$2,[4]Prices!$J$3:$K$17,2,FALSE)*AB125)+M125 -> 23345500 | AD125: 4806000 | AF125: =AD125-AE125 -> 4806000 | AH125: =AD125+AG125 -> 4806000 | AI125: =AH125/M125 -> 0.20586409 | AJ125: =AH125/AC125 -> 0.20586409
A126: 124 | I126: Akingbade Folukemi | J126: SWR | K126: Akure | L126: SWC2877 | M126: =IFERROR(VLOOKUP($L126,[3]Consolidated!$C$9:$AC$452,27,0),0) -> 5230000 | N126: =IFERROR(VLOOKUP($L126,[3]Consolidated!$C$9:$AC$452,5,0),0) -> 20 | AC126: =(VLOOKUP($O$2,[4]Prices!$E$3:$K$17,2,FALSE)*O126)+(VLOOKUP($P$2,[4]Prices!$J$3:$K$17,2,FALSE)*P126)+(VLOOKUP($Q$2,[4]Prices!$J$3:$K$17,2,FALSE)*Q126)+(VLOOKUP($R$2,[4]Prices!$J$3:$K$17,2,FALSE)*R126)+(VLOOKUP($S$2,[4]Prices!$J$3:$K$17,2,FALSE)*S126)+(VLOOKUP($T$2,[4]Prices!$J$3:$K$17,2,FALSE)*T126)+(VLOOKUP($U$2,[4]Prices!$J$3:$K$17,2,FALSE)*U126)+(VLOOKUP($V$2,[4]Prices!$J$3:$K$17,2,FALSE)*V126)+(VLOOKUP($W$2,[4]Prices!$J$3:$K$17,2,FALSE)*W126)+(VLOOKUP($X$2,[4]Prices!$J$3:$K$17,2,FALSE)*X126)+(VLOOKUP($Y$2,[4]Prices!$J$3:$K$17,2,FALSE)*Y126)+(VLOOKUP($Z$2,[4]Prices!$J$3:$K$17,2,FALSE)*Z126)+(VLOOKUP($AA$2,[4]Prices!$J$3:$K$17,2,FALSE)*AA126)+(VLOOKUP($AB$2,[4]Prices!$J$3:$K$17,2,FALSE)*AB126)+M126 -> 5230000 | AD126: 842100 | AF126: =AD126-AE126 -> 842100 | AH126: =AD126+AG126 -> 842100 | AI126: =AH126/M126 -> 0.16101338 | AJ126: =AH126/AC126 -> 0.16101338
... A133: 131 | I133: Desmond Ubeh | J133: SWR | K133: Akure | L133: SWC0882 | M133: =IFERROR(VLOOKUP($L133,[3]Consolidated!$C$9:$AC$452,27,0),0) -> 39225000 | N133: =IFERROR(VLOOKUP($L133,[3]Consolidated!$C$9:$AC$452,5,0),0) -> 150 | AC133: =(VLOOKUP($O$2,[4]Prices!$E$3:$K$17,2,FALSE)*O133)+(VLOOKUP($P$2,[4]Prices!$J$3:$K$17,2,FALSE)*P133)+(VLOOKUP($Q$2,[4]Prices!$J$3:$K$17,2,FALSE)*Q133)+(VLOOKUP($R$2,[4]Prices!$J$3:$K$17,2,FALSE)*R133)+(VLOOKUP($S$2,[4]Prices!$J$3:$K$17,2,FALSE)*S133)+(VLOOKUP($T$2,[4]Prices!$J$3:$K$17,2,FALSE)*T133)+(VLOOKUP($U$2,[4]Prices!$J$3:$K$17,2,FALSE)*U133)+(VLOOKUP($V$2,[4]Prices!$J$3:$K$17,2,FALSE)*V133)+(VLOOKUP($W$2,[4]Prices!$J$3:$K$17,2,FALSE)*W133)+(VLOOKUP($X$2,[4]Prices!$J$3:$K$17,2,FALSE)*X133)+(VLOOKUP($Y$2,[4]Prices!$J$3:$K$17,2,FALSE)*Y133)+(VLOOKUP($Z$2,[4]Prices!$J$3:$K$17,2,FALSE)*Z133)+(VLOOKUP($AA$2,[4]Prices!$J$3:$K$17,2,FALSE)*AA133)+(VLOOKUP($AB$2,[4]Prices!$J$3:$K$17,2,FALSE)*AB133)+M133 -> 39225000 | AD133: 4612250 | AF133: =AD133-AE133 -> 4612250 | AH133: =AD133+AG133 -> 4612250 | AI133: =AH133/M133 -> 0.11758445 | AJ133: =AH133/AC133 -> 0.11758445
A134: 132 | I134: Donas Stores | J134: SWR | K134: Akure | L134: SWC0874 | M134: =IFERROR(VLOOKUP($L134,[3]Consolidated!$C$9:$AC$452,27,0),0) -> 10460000 | N134: =IFERROR(VLOOKUP($L134,[3]Consolidated!$C$9:$AC$452,5,0),0) -> 40 | AC134: =(VLOOKUP($O$2,[4]Prices!$E$3:$K$17,2,FALSE)*O134)+(VLOOKUP($P$2,[4]Prices!$J$3:$K$17,2,FALSE)*P134)+(VLOOKUP($Q$2,[4]Prices!$J$3:$K$17,2,FALSE)*Q134)+(VLOOKUP($R$2,[4]Prices!$J$3:$K$17,2,FALSE)*R134)+(VLOOKUP($S$2,[4]Prices!$J$3:$K$17,2,FALSE)*S134)+(VLOOKUP($T$2,[4]Prices!$J$3:$K$17,2,FALSE)*T134)+(VLOOKUP($U$2,[4]Prices!$J$3:$K$17,2,FALSE)*U134)+(VLOOKUP($V$2,[4]Prices!$J$3:$K$17,2,FALSE)*V134)+(VLOOKUP($W$2,[4]Prices!$J$3:$K$17,2,FALSE)*W134)+(VLOOKUP($X$2,[4]Prices!$J$3:$K$17,2,FALSE)*X134)+(VLOOKUP($Y$2,[4]Prices!$J$3:$K$17,2,FALSE)*Y134)+(VLOOKUP($Z$2,[4]Prices!$J$3:$K$17,2,FALSE)*Z134)+(VLOOKUP($AA$2,[4]Prices!$J$3:$K$17,2,FALSE)*AA134)+(VLOOKUP($AB$2,[4]Prices!$J$3:$K$17,2,FALSE)*AB134)+M134 -> 10460000 | AD134: 0 | AF134: =AD134-AE134 -> 0 | AG134: 3000000 | AH134: =AD134+AG134 -> 3000000 | AI134: =AH134/M134 -> 0.28680688 | AJ134: =AH134/AC134 -> 0.28680688 | AK134: Customer has cleared all outstanding debt. Delay in repayment is as a result of the Owo massacre that impacted his assigned TSA.
A135: 133 | I135: Samtex Supermart | J135: SWR | K135: Akure | L135: SWC0873 | M135: =IFERROR(VLOOKUP($L135,[3]Consolidated!$C$9:$AC$452,27,0),0) -> 10460000 | N135: =IFERROR(VLOOKUP($L135,[3]Consolidated!$C$9:$AC$452,5,0),0) -> 40 | AC135: =(VLOOKUP($O$2,[4]Prices!$E$3:$K$17,2,FALSE)*O135)+(VLOOKUP($P$2,[4]Prices!$J$3:$K$17,2,FALSE)*P135)+(VLOOKUP($Q$2,[4]Prices!$J$3:$K$17,2,FALSE)*Q135)+(VLOOKUP($R$2,[4]Prices!$J$3:$K$17,2,FALSE)*R135)+(VLOOKUP($S$2,[4]Prices!$J$3:$K$17,2,FALSE)*S135)+(VLOOKUP($T$2,[4]Prices!$J$3:$K$17,2,FALSE)*T135)+(VLOOKUP($U$2,[4]Prices!$J$3:$K$17,2,FALSE)*U135)+(VLOOKUP($V$2,[4]Prices!$J$3:$K$17,2,FALSE)*V135)+(VLOOKUP($W$2,[4]Prices!$J$3:$K$17,2,FALSE)*W135)+(VLOOKUP($X$2,[4]Prices!$J$3:$K$17,2,FALSE)*X135)+(VLOOKUP($Y$2,[4]Prices!$J$3:$K$17,2,FALSE)*Y135)+(VLOOKUP($Z$2,[4]Prices!$J$3:$K$17,2,FALSE)*Z135)+(VLOOKUP($AA$2,[4]Prices!$J$3:$K$17,2,FALSE)*AA135)+(VLOOKUP($AB$2,[4]Prices!$J$3:$K$17,2,FALSE)*AB135)+M135 -> 10460000 | AD135: 998000 | AF135: =AD135-AE135 -> 998000 | AH135: =AD135+AG135 -> 998000 | AI135: =AH135/M135 -> 0.09541109 | AJ135: =AH135/AC135 -> 0.09541109
A136: 134 | I136: Pioneer Stores (stockist) | J136: SWR | K136: Akure | L136: WCFA000685 | M136: =IFERROR(VLOOKUP($L136,[3]Consolidated!$C$9:$AC$452,27,0),0) -> 11767500 | N136: =IFERROR(VLOOKUP($L136,[3]Consolidated!$C$9:$AC$452,5,0),0) -> 45 | AC136: =(VLOOKUP($O$2,[4]Prices!$E$3:$K$17,2,FALSE)*O136)+(VLOOKUP($P$2,[4]Prices!$J$3:$K$17,2,FALSE)*P136)+(VLOOKUP($Q$2,[4]Prices!$J$3:$K$17,2,FALSE)*Q136)+(VLOOKUP($R$2,[4]Prices!$J$3:$K$17,2,FALSE)*R136)+(VLOOKUP($S$2,[4]Prices!$J$3:$K$17,2,FALSE)*S136)+(VLOOKUP($T$2,[4]Prices!$J$3:$K$17,2,FALSE)*T136)+(VLOOKUP($U$2,[4]Prices!$J$3:$K$17,2,FALSE)*U136)+(VLOOKUP($V$2,[4]Prices!$J$3:$K$17,2,FALSE)*V136)+(VLOOKUP($W$2,[4]Prices!$J$3:$K$17,2,FALSE)*W136)+(VLOOKUP($X$2,[4]Prices!$J$3:$K$17,2,FALSE)*X136)+(VLOOKUP($Y$2,[4]Prices!$J$3:$K$17,2,FALSE)*Y136)+(VLOOKUP($Z$2,[4]Prices!$J$3:$K$17,2,FALSE)*Z136)+(VLOOKUP($AA$2,[4]Prices!$J$3:$K$17,2,FALSE)*AA136)+(VLOOKUP($AB$2,[4]Prices!$J$3:$K$17,2,FALSE)*AB136)+M136 -> 11767500 | AD136: 1815000 | AF136: =AD136-AE136 -> 1815000 | AH136: =AD136+AG136 -> 1815000 | AI136: =AH136/M136 -> 0.15423837 | AJ136: =AH136/AC136 -> 0.15423837
A137: 135 | I137: Famous Onome (stockist) | J137: SWR | K137: Akure | L137: WCFA000683 | M137: =IFERROR(VLOOKUP($L137,[3]Consolidated!$C$9:$AC$452,27,0),0) -> 16997500 | N137: =IFERROR(VLOOKUP($L137,[3]Consolidated!$C$9:$AC$452,5,0),0) -> 65 | AC137: =(VLOOKUP($O$2,[4]Prices!$E$3:$K$17,2,FALSE)*O137)+(VLOOKUP($P$2,[4]Prices!$J$3:$K$17,2,FALSE)*P137)+(VLOOKUP($Q$2,[4]Prices!$J$3:$K$17,2,FALSE)*Q137)+(VLOOKUP($R$2,[4]Prices!$J$3:$K$17,2,FALSE)*R137)+(VLOOKUP($S$2,[4]Prices!$J$3:$K$17,2,FALSE)*S137)+(VLOOKUP($T$2,[4]Prices!$J$3:$K$17,2,FALSE)*T137)+(VLOOKUP($U$2,[4]Prices!$J$3:$K$17,2,FALSE)*U137)+(VLOOKUP($V$2,[4]Prices!$J$3:$K$17,2,FALSE)*V137)+(VLOOKUP($W$2,[4]Prices!$J$3:$K$17,2,FALSE)*W137)+(VLOOKUP($X$2,[4]Prices!$J$3:$K$17,2,FALSE)*X137)+(VLOOKUP($Y$2,[4]Prices!$J$3:$K$17,2,FALSE)*Y137)+(VLOOKUP($Z$2,[4]Prices!$J$3:$K$17,2,FALSE)*Z137)+(VLOOKUP($AA$2,[4]Prices!$J$3:$K$17,2,FALSE)*AA137)+(VLOOKUP($AB$2,[4]Prices!$J$3:$K$17,2,FALSE)*AB137)+M137 -> 16997500 | AD137: 2598000 | AF137: =AD137-AE137 -> 2598000 | AH137: =AD137+AG137 -> 2598000 | AI137: =AH137/M137 -> 0.15284601 | AJ137: =AH137/AC137 -> 0.15284601
A138: 136 | I138: Stephen Supermart | J138: SWR | K138: Akure | L138: SWC0881 | M138: =IFERROR(VLOOKUP($L138,[3]Consolidated!$C$9:$AC$452,27,0),0) -> 33995000 | N138: =IFERROR(VLOOKUP($L138,[3]Consolidated!$C$9:$AC$452,5,0),0) -> 130 | AC138: =(VLOOKUP($O$2,[4]Prices!$E$3:$K$17,2,FALSE)*O138)+(VLOOKUP($P$2,[4]Prices!$J$3:$K$17,2,FALSE)*P138)+(VLOOKUP($Q$2,[4]Prices!$J$3:$K$17,2,FALSE)*Q138)+(VLOOKUP($R$2,[4]Prices!$J$3:$K$17,2,FALSE)*R138)+(VLOOKUP($S$2,[4]Prices!$J$3:$K$17,2,FALSE)*S138)+(VLOOKUP($T$2,[4]Prices!$J$3:$K$17,2,FALSE)*T138)+(VLOOKUP($U$2,[4]Prices!$J$3:$K$17,2,FALSE)*U138)+(VLOOKUP($V$2,[4]Prices!$J$3:$K$17,2,FALSE)*V138)+(VLOOKUP($W$2,[4]Prices!$J$3:$K$17,2,FALSE)*W138)+(VLOOKUP($X$2,[4]Prices!$J$3:$K$17,2,FALSE)*X138)+(VLOOKUP($Y$2,[4]Prices!$J$3:$K$17,2,FALSE)*Y138)+(VLOOKUP($Z$2,[4]Prices!$J$3:$K$17,2,FALSE)*Z138)+(VLOOKUP($AA$2,[4]Prices!$J$3:$K$17,2,FALSE)*AA138)+(VLOOKUP($AB$2,[4]Prices!$J$3:$K$17,2,FALSE)*AB138)+M138 -> 33995000 | AD138: 4240300 | AF138: =AD138-AE138 -> 4240300 | AH138: =AD138+AG138 -> 4240300 | AI138: =AH138/M138 -> 0.12473305 | AJ138: =AH138/AC138 -> 0.12473305
A139: 137 | I139: Muritala Store | J139: SWR | K139: Akure | L139: SWC2927 | M139: =IFERROR(VLOOKUP($L139,[3]Consolidated!$C$9:$AC$452,27,0),0) -> 4707000 | N139: =IFERROR(VLOOKUP($L139,[3]Consolidated!$C$9:$AC$452,5,0),0) -> 18 | AC139: =(VLOOKUP($O$2,[4]Prices!$E$3:$K$17,2,FALSE)*O139)+(VLOOKUP($P$2,[4]Prices!$J$3:$K$17,2,FALSE)*P139)+(VLOOKUP($Q$2,[4]Prices!$J$3:$K$17,2,FALSE)*Q139)+(VLOOKUP($R$2,[4]Prices!$J$3:$K$17,2,FALSE)*R139)+(VLOOKUP($S$2,[4]Prices!$J$3:$K$17,2,FALSE)*S139)+(VLOOKUP($T$2,[4]Prices!$J$3:$K$17,2,FALSE)*T139)+(VLOOKUP($U$2,[4]Prices!$J$3:$K$17,2,FALSE)*U139)+(VLOOKUP($V$2,[4]Prices!$J$3:$K$17,2,FALSE)*V139)+(VLOOKUP($W$2,[4]Prices!$J$3:$K$17,2,FALSE)*W139)+(VLOOKUP($X$2,[4]Prices!$J$3:$K$17,2,FALSE)*X139)+(VLOOKUP($Y$2,[4]Prices!$J$3:$K$17,2,FALSE)*Y139)+(VLOOKUP($Z$2,[4]Prices!$J$3:$K$17,2,FALSE)*Z139)+(VLOOKUP($AA$2,[4]Prices!$J$3:$K$17,2,FALSE)*AA139)+(VLOOKUP($AB$2,[4]Prices!$J$3:$K$17,2,FALSE)*AB139)+M139 -> 4707000 | AD139: 562500 | AF139: =AD139-AE139 -> 562500 | AH139: =AD139+AG139 -> 562500 | AI139: =AH139/M139 -> 0.11950287 | AJ139: =AH139/AC139 -> 0.11950287
A140: 138 | I140: Chris Chilly Variety Shop | J140: SWR | K140: Akure | L140: SWC2940 | M140: =IFERROR(VLOOKUP($L140,[3]Consolidated!$C$9:$AC$452,27,0),0) -> 6537500 | N140: =IFERROR(VLOOKUP($L140,[3]Consolidated!$C$9:$AC$452,5,0),0) -> 25 | AC140: =(VLOOKUP($O$2,[4]Prices!$E$3:$K$17,2,FALSE)*O140)+(VLOOKUP($P$2,[4]Prices!$J$3:$K$17,2,FALSE)*P140)+(VLOOKUP($Q$2,[4]Prices!$J$3:$K$17,2,FALSE)*Q140)+(VLOOKUP($R$2,[4]Prices!$J$3:$K$17,2,FALSE)*R140)+(VLOOKUP($S$2,[4]Prices!$J$3:$K$17,2,FALSE)*S140)+(VLOOKUP($T$2,[4]Prices!$J$3:$K$17,2,FALSE)*T140)+(VLOOKUP($U$2,[4]Prices!$J$3:$K$17,2,FALSE)*U140)+(VLOOKUP($V$2,[4]Prices!$J$3:$K$17,2,FALSE)*V140)+(VLOOKUP($W$2,[4]Prices!$J$3:$K$17,2,FALSE)*W140)+(VLOOKUP($X$2,[4]Prices!$J$3:$K$17,2,FALSE)*X140)+(VLOOKUP($Y$2,[4]Prices!$J$3:$K$17,2,FALSE)*Y140)+(VLOOKUP($Z$2,[4]Prices!$J$3:$K$17,2,FALSE)*Z140)+(VLOOKUP($AA$2,[4]Prices!$J$3:$K$17,2,FALSE)*AA140)+(VLOOKUP($AB$2,[4]Prices!$J$3:$K$17,2,FALSE)*AB140)+M140 -> 6537500 | AD140: 0 | AF140: =AD140-AE140 -> 0 | AH140: =AD140+AG140 -> 0 | AI140: =AH140/M140 -> 0 | AJ140: =AH140/AC140 -> 0
A141: 139 | I141: Zubair Sunday Inimisi | J141: SWR | K141: Akure | L141: SWC3059 | M141: =IFERROR(VLOOKUP($L141,[3]Consolidated!$C$9:$AC$452,27,0),0) -> 5230000 | N141: =IFERROR(VLOOKUP($L141,[3]Consolidated!$C$9:$AC$452,5,0),0) -> 20 | AC141: =(VLOOKUP($O$2,[4]Prices!$E$3:$K$17,2,FALSE)*O141)+(VLOOKUP($P$2,[4]Prices!$J$3:$K$17,2,FALSE)*P141)+(VLOOKUP($Q$2,[4]Prices!$J$3:$K$17,2,FALSE)*Q141)+(VLOOKUP($R$2,[4]Prices!$J$3:$K$17,2,FALSE)*R141)+(VLOOKUP($S$2,[4]Prices!$J$3:$K$17,2,FALSE)*S141)+(VLOOKUP($T$2,[4]Prices!$J$3:$K$17,2,FALSE)*T141)+(VLOOKUP($U$2,[4]Prices!$J$3:$K$17,2,FALSE)*U141)+(VLOOKUP($V$2,[4]Prices!$J$3:$K$17,2,FALSE)*V141)+(VLOOKUP($W$2,[4]Prices!$J$3:$K$17,2,FALSE)*W141)+(VLOOKUP($X$2,[4]Prices!$J$3:$K$17,2,FALSE)*X141)+(VLOOKUP($Y$2,[4]Prices!$J$3:$K$17,2,FALSE)*Y141)+(VLOOKUP($Z$2,[4]Prices!$J$3:$K$17,2,FALSE)*Z141)+(VLOOKUP($AA$2,[4]Prices!$J$3:$K$17,2,FALSE)*AA141)+(VLOOKUP($AB$2,[4]Prices!$J$3:$K$17,2,FALSE)*AB141)+M141 -> 5230000 | AD141: 461550 | AF141: =AD141-AE141 -> 461550 | AH141: =AD141+AG141 -> 461550 | AI141: =AH141/M141 -> 0.088250478 | AJ141: =AH141/AC141 -> 0.088250478
A142: 140 | I142: Alhaji Yaya | J142: SWR | K142: Festac | L142: LAC3766 | M142: =IFERROR(VLOOKUP($L142,[3]Consolidated!$C$9:$AC$452,27,0),0) -> 3944000 | N142: =IFERROR(VLOOKUP($L142,[3]Consolidated!$C$9:$AC$452,5,0),0) -> 20 | O142: 5 | AC142: =(VLOOKUP($O$2,[4]Prices!$E$3:$K$17,2,FALSE)*O142)+(VLOOKUP($P$2,[4]Prices!$J$3:$K$17,2,FALSE)*P142)+(VLOOKUP($Q$2,[4]Prices!$J$3:$K$17,2,FALSE)*Q142)+(VLOOKUP($R$2,[4]Prices!$J$3:$K$17,2,FALSE)*R142)+(VLOOKUP($S$2,[4]Prices!$J$3:$K$17,2,FALSE)*S142)+(VLOOKUP($T$2,[4]Prices!$J$3:$K$17,2,FALSE)*T142)+(VLOOKUP($U$2,[4]Prices!$J$3:$K$17,2,FALSE)*U142)+(VLOOKUP($V$2,[4]Prices!$J$3:$K$17,2,FALSE)*V142)+(VLOOKUP($W$2,[4]Prices!$J$3:$K$17,2,FALSE)*W142)+(VLOOKUP($X$2,[4]Prices!$J$3:$K$17,2,FALSE)*X142)+(VLOOKUP($Y$2,[4]Prices!$J$3:$K$17,2,FALSE)*Y142)+(VLOOKUP($Z$2,[4]Prices!$J$3:$K$17,2,FALSE)*Z142)+(VLOOKUP($AA$2,[4]Prices!$J$3:$K$17,2,FALSE)*AA142)+(VLOOKUP($AB$2,[4]Prices!$J$3:$K$17,2,FALSE)*AB142)+M142 -> 5249000 | AD142: 2267700 | AF142: =AD142-AE142 -> 2267700 | AG142: 730000 | AH142: =AD142+AG142 -> 2997700 | AI142: =AH142/M142 -> 0.76006592 | AJ142: =AH142/AC142 -> 0.57109926
A143: 141 | I143: MRS OMURHIE | J143: SWR | K143: Festac | L143: LAC0340 | M143: =IFERROR(VLOOKUP($L143,[3]Consolidated!$C$9:$AC$452,27,0),0) -> 16606000 | N143: =IFERROR(VLOOKUP($L143,[3]Consolidated!$C$9:$AC$452,5,0),0) -> 80 | AC143: =(VLOOKUP($O$2,[4]Prices!$E$3:$K$17,2,FALSE)*O143)+(VLOOKUP($P$2,[4]Prices!$J$3:$K$17,2,FALSE)*P143)+(VLOOKUP($Q$2,[4]Prices!$J$3:$K$17,2,FALSE)*Q143)+(VLOOKUP($R$2,[4]Prices!$J$3:$K$17,2,FALSE)*R143)+(VLOOKUP($S$2,[4]Prices!$J$3:$K$17,2,FALSE)*S143)+(VLOOKUP($T$2,[4]Prices!$J$3:$K$17,2,FALSE)*T143)+(VLOOKUP($U$2,[4]Prices!$J$3:$K$17,2,FALSE)*U143)+(VLOOKUP($V$2,[4]Prices!$J$3:$K$17,2,FALSE)*V143)+(VLOOKUP($W$2,[4]Prices!$J$3:$K$17,2,FALSE)*W143)+(VLOOKUP($X$2,[4]Prices!$J$3:$K$17,2,FALSE)*X143)+(VLOOKUP($Y$2,[4]Prices!$J$3:$K$17,2,FALSE)*Y143)+(VLOOKUP($Z$2,[4]Prices!$J$3:$K$17,2,FALSE)*Z143)+(VLOOKUP($AA$2,[4]Prices!$J$3:$K$17,2,FALSE)*AA143)+(VLOOKUP($AB$2,[4]Prices!$J$3:$K$17,2,FALSE)*AB143)+M143 -> 16606000 | AD143: 4111000 | AF143: =AD143-AE143 -> 4111000 | AH143: =AD143+AG143 -> 4111000 | AI143: =AH143/M143 -> 0.24756112 | AJ143: =AH143/AC143 -> 0.24756112
A144: 142 | I144: Daniel Akuru | J144: SWR | K144: Festac | L144: LAC3853 | M144: =IFERROR(VLOOKUP($L144,[3]Consolidated!$C$9:$AC$452,27,0),0) -> 10551500 | N144: =IFERROR(VLOOKUP($L144,[3]Consolidated!$C$9:$AC$452,5,0),0) -> 55 | AC144: =(VLOOKUP($O$2,[4]Prices!$E$3:$K$17,2,FALSE)*O144)+(VLOOKUP($P$2,[4]Prices!$J$3:$K$17,2,FALSE)*P144)+(VLOOKUP($Q$2,[4]Prices!$J$3:$K$17,2,FALSE)*Q144)+(VLOOKUP($R$2,[4]Prices!$J$3:$K$17,2,FALSE)*R144)+(VLOOKUP($S$2,[4]Prices!$J$3:$K$17,2,FALSE)*S144)+(VLOOKUP($T$2,[4]Prices!$J$3:$K$17,2,FALSE)*T144)+(VLOOKUP($U$2,[4]Prices!$J$3:$K$17,2,FALSE)*U144)+(VLOOKUP($V$2,[4]Prices!$J$3:$K$17,2,FALSE)*V144)+(VLOOKUP($W$2,[4]Prices!$J$3:$K$17,2,FALSE)*W144)+(VLOOKUP($X$2,[4]Prices!$J$3:$K$17,2,FALSE)*X144)+(VLOOKUP($Y$2,[4]Prices!$J$3:$K$17,2,FALSE)*Y144)+(VLOOKUP($Z$2,[4]Prices!$J$3:$K$17,2,FALSE)*Z144)+(VLOOKUP($AA$2,[4]Prices!$J$3:$K$17,2,FALSE)*AA144)+(VLOOKUP($AB$2,[4]Prices!$J$3:$K$17,2,FALSE)*AB144)+M144 -> 10551500 | AD144: 2607500 | AF144: =AD144-AE144 -> 2607500 | AG144: 4200000 | AH144: =AD144+AG144 -> 6807500 | AI144: =AH144/M144 -> 0.64516893 | AJ144: =AH144/AC144 -> 0.64516893
A145: 143 | I145: TEE JAY Store | J145: SWR | K145: Festac | L145: LAC3847 | M145: =IFERROR(VLOOKUP($L145,[3]Consolidated!$C$9:$AC$452,27,0),0) -> 0 | N145: =IFERROR(VLOOKUP($L145,[3]Consolidated!$C$9:$AC$452,5,0),0) -> 0 | AC145: =(VLOOKUP($O$2,[4]Prices!$E$3:$K$17,2,FALSE)*O145)+(VLOOKUP($P$2,[4]Prices!$J$3:$K$17,2,FALSE)*P145)+(VLOOKUP($Q$2,[4]Prices!$J$3:$K$17,2,FALSE)*Q145)+(VLOOKUP($R$2,[4]Prices!$J$3:$K$17,2,FALSE)*R145)+(VLOOKUP($S$2,[4]Prices!$J$3:$K$17,2,FALSE)*S145)+(VLOOKUP($T$2,[4]Prices!$J$3:$K$17,2,FALSE)*T145)+(VLOOKUP($U$2,[4]Prices!$J$3:$K$17,2,FALSE)*U145)+(VLOOKUP($V$2,[4]Prices!$J$3:$K$17,2,FALSE)*V145)+(VLOOKUP($W$2,[4]Prices!$J$3:$K$17,2,FALSE)*W145)+(VLOOKUP($X$2,[4]Prices!$J$3:$K$17,2,FALSE)*X145)+(VLOOKUP($Y$2,[4]Prices!$J$3:$K$17,2,FALSE)*Y145)+(VLOOKUP($Z$2,[4]Prices!$J$3:$K$17,2,FALSE)*Z145)+(VLOOKUP($AA$2,[4]Prices!$J$3:$K$17,2,FALSE)*AA145)+(VLOOKUP($AB$2,[4]Prices!$J$3:$K$17,2,FALSE)*AB145)+M145 -> 0 | AD145: 0 | AF145: =AD145-AE145 -> 0 | AH145: =AD145+AG145 -> 0 | AI145: =AH145/M145 -> #DIV/0! | AJ145: =AH145/AC145 -> #DIV/0!
A146: 144 | I146: Bright Star Venture | J146: SWR | K146: Festac | L146: LAC3911 | M146: =IFERROR(VLOOKUP($L146,[3]Consolidated!$C$9:$AC$452,27,0),0) -> 0 | N146: =IFERROR(VLOOKUP($L146,[3]Consolidated!$C$9:$AC$452,5,0),0) -> 0 | AC146: =(VLOOKUP($O$2,[4]Prices!$E$3:$K$17,2,FALSE)*O146)+(VLOOKUP($P$2,[4]Prices!$J$3:$K$17,2,FALSE)*P146)+(VLOOKUP($Q$2,[4]Prices!$J$3:$K$17,2,FALSE)*Q146)+(VLOOKUP($R$2,[4]Prices!$J$3:$K$17,2,FALSE)*R146)+(VLOOKUP($S$2,[4]Prices!$J$3:$K$17,2,FALSE)*S146)+(VLOOKUP($T$2,[4]Prices!$J$3:$K$17,2,FALSE)*T146)+(VLOOKUP($U$2,[4]Prices!$J$3:$K$17,2,FALSE)*U146)+(VLOOKUP($V$2,[4]Prices!$J$3:$K$17,2,FALSE)*V146)+(VLOOKUP($W$2,[4]Prices!$J$3:$K$17,2,FALSE)*W146)+(VLOOKUP($X$2,[4]Prices!$J$3:$K$17,2,FALSE)*X146)+(VLOOKUP($Y$2,[4]Prices!$J$3:$K$17,2,FALSE)*Y146)+(VLOOKUP($Z$2,[4]Prices!$J$3:$K$17,2,FALSE)*Z146)+(VLOOKUP($AA$2,[4]Prices!$J$3:$K$17,2,FALSE)*AA146)+(VLOOKUP($AB$2,[4]Prices!$J$3:$K$17,2,FALSE)*AB146)+M146 -> 0 | AD146: 0 | AF146: =AD146-AE146 -> 0 | AH146: =AD146+AG146 -> 0 | AI146: =AH146/M146 -> #DIV/0! | AJ146: =AH146/AC146 -> #DIV/0!
A147: 145 | I147: Blessed Royal DOM | J147: SWR | K147: Festac | L147: LAC3912 | M147: =IFERROR(VLOOKUP($L147,[3]Consolidated!$C$9:$AC$452,27,0),0) -> 3984000 | N147: =IFERROR(VLOOKUP($L147,[3]Consolidated!$C$9:$AC$452,5,0),0) -> 20 | O147: 6 | AC147: =(VLOOKUP($O$2,[4]Prices!$E$3:$K$17,2,FALSE)*O147)+(VLOOKUP($P$2,[4]Prices!$J$3:$K$17,2,FALSE)*P147)+(VLOOKUP($Q$2,[4]Prices!$J$3:$K$17,2,FALSE)*Q147)+(VLOOKUP($R$2,[4]Prices!$J$3:$K$17,2,FALSE)*R147)+(VLOOKUP($S$2,[4]Prices!$J$3:$K$17,2,FALSE)*S147)+(VLOOKUP($T$2,[4]Prices!$J$3:$K$17,2,FALSE)*T147)+(VLOOKUP($U$2,[4]Prices!$J$3:$K$17,2,FALSE)*U147)+(VLOOKUP($V$2,[4]Prices!$J$3:$K$17,2,FALSE)*V147)+(VLOOKUP($W$2,[4]Prices!$J$3:$K$17,2,FALSE)*W147)+(VLOOKUP($X$2,[4]Prices!$J$3:$K$17,2,FALSE)*X147)+(VLOOKUP($Y$2,[4]Prices!$J$3:$K$17,2,FALSE)*Y147)+(VLOOKUP($Z$2,[4]Prices!$J$3:$K$17,2,FALSE)*Z147)+(VLOOKUP($AA$2,[4]Prices!$J$3:$K$17,2,FALSE)*AA147)+(VLOOKUP($AB$2,[4]Prices!$J$3:$K$17,2,FALSE)*AB147)+M147 -> 5550000 | AD147: 2690500 | AF147: =AD147-AE147 -> 2690500 | AG147: 700000 | AH147: =AD147+AG147 -> 3390500 | AI147: =AH147/M147 -> 0.85102912 | AJ147: =AH147/AC147 -> 0.6109009
A148: 146 | I148: Ugwuanyi Chukwudi | J148: SWR | K148: Festac | L148: LAC3913 | M148: =IFERROR(VLOOKUP($L148,[3]Consolidated!$C$9:$AC$452,27,0),0) -> 0 | N148: =IFERROR(VLOOKUP($L148,[3]Consolidated!$C$9:$AC$452,5,0),0) -> 0 | AC148: =(VLOOKUP($O$2,[4]Prices!$E$3:$K$17,2,FALSE)*O148)+(VLOOKUP($P$2,[4]Prices!$J$3:$K$17,2,FALSE)*P148)+(VLOOKUP($Q$2,[4]Prices!$J$3:$K$17,2,FALSE)*Q148)+(VLOOKUP($R$2,[4]Prices!$J$3:$K$17,2,FALSE)*R148)+(VLOOKUP($S$2,[4]Prices!$J$3:$K$17,2,FALSE)*S148)+(VLOOKUP($T$2,[4]Prices!$J$3:$K$17,2,FALSE)*T148)+(VLOOKUP($U$2,[4]Prices!$J$3:$K$17,2,FALSE)*U148)+(VLOOKUP($V$2,[4]Prices!$J$3:$K$17,2,FALSE)*V148)+(VLOOKUP($W$2,[4]Prices!$J$3:$K$17,2,FALSE)*W148)+(VLOOKUP($X$2,[4]Prices!$J$3:$K$17,2,FALSE)*X148)+(VLOOKUP($Y$2,[4]Prices!$J$3:$K$17,2,FALSE)*Y148)+(VLOOKUP($Z$2,[4]Prices!$J$3:$K$17,2,FALSE)*Z148)+(VLOOKUP($AA$2,[4]Prices!$J$3:$K$17,2,FALSE)*AA148)+(VLOOKUP($AB$2,[4]Prices!$J$3:$K$17,2,FALSE)*AB148)+M148 -> 0 | AD148: 0 | AF148: =AD148-AE148 -> 0 | AH148: =AD148+AG148 -> 0 | AI148: =AH148/M148 -> #DIV/0! | AJ148: =AH148/AC148 -> #DIV/0!
A149: 147 | I149: MUMMY NAFISAT - RME | J149: SWR | K149: Ibadan | L149: SWC2872 | M149: =IFERROR(VLOOKUP($L149,[3]Consolidated!$C$9:$AC$452,27,0),0) -> 3371900 | N149: =IFERROR(VLOOKUP($L149,[3]Consolidated!$C$9:$AC$452,5,0),0) -> 17 | AC149: =(VLOOKUP($O$2,[4]Prices!$E$3:$K$17,2,FALSE)*O149)+(VLOOKUP($P$2,[4]Prices!$J$3:$K$17,2,FALSE)*P149)+(VLOOKUP($Q$2,[4]Prices!$J$3:$K$17,2,FALSE)*Q149)+(VLOOKUP($R$2,[4]Prices!$J$3:$K$17,2,FALSE)*R149)+(VLOOKUP($S$2,[4]Prices!$J$3:$K$17,2,FALSE)*S149)+(VLOOKUP($T$2,[4]Prices!$J$3:$K$17,2,FALSE)*T149)+(VLOOKUP($U$2,[4]Prices!$J$3:$K$17,2,FALSE)*U149)+(VLOOKUP($V$2,[4]Prices!$J$3:$K$17,2,FALSE)*V149)+(VLOOKUP($W$2,[4]Prices!$J$3:$K$17,2,FALSE)*W149)+(VLOOKUP($X$2,[4]Prices!$J$3:$K$17,2,FALSE)*X149)+(VLOOKUP($Y$2,[4]Prices!$J$3:$K$17,2,FALSE)*Y149)+(VLOOKUP($Z$2,[4]Prices!$J$3:$K$17,2,FALSE)*Z149)+(VLOOKUP($AA$2,[4]Prices!$J$3:$K$17,2,FALSE)*AA149)+(VLOOKUP($AB$2,[4]Prices!$J$3:$K$17,2,FALSE)*AB149)+M149 -> 3371900 | AD149: 1046000 | AF149: =AD149-AE149 -> 1046000 | AH149: =AD149+AG149 -> 1046000 | AI149: =AH149/M149 -> 0.31021086 | AJ149: =AH149/AC149 -> 0.31021086
A150: 148 | I150: Olaosebikan Stores - RME | J150: SWR | K150: Ibadan | L150: SWC2869 | M150: =IFERROR(VLOOKUP($L150,[3]Consolidated!$C$9:$AC$452,27,0),0) -> 8879517.5 | N150: =IFERROR(VLOOKUP($L150,[3]Consolidated!$C$9:$AC$452,5,0),0) -> 40 | AC150: =(VLOOKUP($O$2,[4]Prices!$E$3:$K$17,2,FALSE)*O150)+(VLOOKUP($P$2,[4]Prices!$J$3:$K$17,2,FALSE)*P150)+(VLOOKUP($Q$2,[4]Prices!$J$3:$K$17,2,FALSE)*Q150)+(VLOOKUP($R$2,[4]Prices!$J$3:$K$17,2,FALSE)*R150)+(VLOOKUP($S$2,[4]Prices!$J$3:$K$17,2,FALSE)*S150)+(VLOOKUP($T$2,[4]Prices!$J$3:$K$17,2,FALSE)*T150)+(VLOOKUP($U$2,[4]Prices!$J$3:$K$17,2,FALSE)*U150)+(VLOOKUP($V$2,[4]Prices!$J$3:$K$17,2,FALSE)*V150)+(VLOOKUP($W$2,[4]Prices!$J$3:$K$17,2,FALSE)*W150)+(VLOOKUP($X$2,[4]Prices!$J$3:$K$17,2,FALSE)*X150)+(VLOOKUP($Y$2,[4]Prices!$J$3:$K$17,2,FALSE)*Y150)+(VLOOKUP($Z$2,[4]Prices!$J$3:$K$17,2,FALSE)*Z150)+(VLOOKUP($AA$2,[4]Prices!$J$3:$K$17,2,FALSE)*AA150)+(VLOOKUP($AB$2,[4]Prices!$J$3:$K$17,2,FALSE)*AB150)+M150 -> 8879517.5 | AD150: 0 | AF150: =AD150-AE150 -> 0 | AH150: =AD150+AG150 -> 0 | AI150: =AH150/M150 -> 0 | AJ150: =AH150/AC150 -> 0
A151: 149 | I151: Iya Bose | J151: SWR | K151: Ibadan | L151: SWC2687 | M151: =IFERROR(VLOOKUP($L151,[3]Consolidated!$C$9:$AC$452,27,0),0) -> 5480750 | N151: =IFERROR(VLOOKUP($L151,[3]Consolidated!$C$9:$AC$452,5,0),0) -> 30 | AC151: =(VLOOKUP($O$2,[4]Prices!$E$3:$K$17,2,FALSE)*O151)+(VLOOKUP($P$2,[4]Prices!$J$3:$K$17,2,FALSE)*P151)+(VLOOKUP($Q$2,[4]Prices!$J$3:$K$17,2,FALSE)*Q151)+(VLOOKUP($R$2,[4]Prices!$J$3:$K$17,2,FALSE)*R151)+(VLOOKUP($S$2,[4]Prices!$J$3:$K$17,2,FALSE)*S151)+(VLOOKUP($T$2,[4]Prices!$J$3:$K$17,2,FALSE)*T151)+(VLOOKUP($U$2,[4]Prices!$J$3:$K$17,2,FALSE)*U151)+(VLOOKUP($V$2,[4]Prices!$J$3:$K$17,2,FALSE)*V151)+(VLOOKUP($W$2,[4]Prices!$J$3:$K$17,2,FALSE)*W151)+(VLOOKUP($X$2,[4]Prices!$J$3:$K$17,2,FALSE)*X151)+(VLOOKUP($Y$2,[4]Prices!$J$3:$K$17,2,FALSE)*Y151)+(VLOOKUP($Z$2,[4]Prices!$J$3:$K$17,2,FALSE)*Z151)+(VLOOKUP($AA$2,[4]Prices!$J$3:$K$17,2,FALSE)*AA151)+(VLOOKUP($AB$2,[4]Prices!$J$3:$K$17,2,FALSE)*AB151)+M151 -> 5480750 | AD151: 0 | AF151: =AD151-AE151 -> 0 | AH151: =AD151+AG151 -> 0 | AI151: =AH151/M151 -> 0 | AJ151: =AH151/AC151 -> 0
A152: 150 | I152: Iya Dada (RME) | J152: SWR | K152: Ibadan | L152: SWC2662 | M152: =IFERROR(VLOOKUP($L152,[3]Consolidated!$C$9:$AC$452,27,0),0) -> 2502000 | N152: =IFERROR(VLOOKUP($L152,[3]Consolidated!$C$9:$AC$452,5,0),0) -> 15 | AC152: =(VLOOKUP($O$2,[4]Prices!$E$3:$K$17,2,FALSE)*O152)+(VLOOKUP($P$2,[4]Prices!$J$3:$K$17,2,FALSE)*P152)+(VLOOKUP($Q$2,[4]Prices!$J$3:$K$17,2,FALSE)*Q152)+(VLOOKUP($R$2,[4]Prices!$J$3:$K$17,2,FALSE)*R152)+(VLOOKUP($S$2,[4]Prices!$J$3:$K$17,2,FALSE)*S152)+(VLOOKUP($T$2,[4]Prices!$J$3:$K$17,2,FALSE)*T152)+(VLOOKUP($U$2,[4]Prices!$J$3:$K$17,2,FALSE)*U152)+(VLOOKUP($V$2,[4]Prices!$J$3:$K$17,2,FALSE)*V152)+(VLOOKUP($W$2,[4]Prices!$J$3:$K$17,2,FALSE)*W152)+(VLOOKUP($X$2,[4]Prices!$J$3:$K$17,2,FALSE)*X152)+(VLOOKUP($Y$2,[4]Prices!$J$3:$K$17,2,FALSE)*Y152)+(VLOOKUP($Z$2,[4]Prices!$J$3:$K$17,2,FALSE)*Z152)+(VLOOKUP($AA$2,[4]Prices!$J$3:$K$17,2,FALSE)*AA152)+(VLOOKUP($AB$2,[4]Prices!$J$3:$K$17,2,FALSE)*AB152)+M152 -> 2502000 | AD152: 0 | AF152: =AD152-AE152 -> 0 | AH152: =AD152+AG152 -> 0 | AI152: =AH152/M152 -> 0 | AJ152: =AH152/AC152 -> 0
A153: 151 | I153: Iya Faruq (RME) | J153: SWR | K153: Ibadan | L153: SWC1812 | M153: =IFERROR(VLOOKUP($L153,[3]Consolidated!$C$9:$AC$452,27,0),0) -> 0 | N153: =IFERROR(VLOOKUP($L153,[3]Consolidated!$C$9:$AC$452,5,0),0) -> 0 | AC153: =(VLOOKUP($O$2,[4]Prices!$E$3:$K$17,2,FALSE)*O153)+(VLOOKUP($P$2,[4]Prices!$J$3:$K$17,2,FALSE)*P153)+(VLOOKUP($Q$2,[4]Prices!$J$3:$K$17,2,FALSE)*Q153)+(VLOOKUP($R$2,[4]Prices!$J$3:$K$17,2,FALSE)*R153)+(VLOOKUP($S$2,[4]Prices!$J$3:$K$17,2,FALSE)*S153)+(VLOOKUP($T$2,[4]Prices!$J$3:$K$17,2,FALSE)*T153)+(VLOOKUP($U$2,[4]Prices!$J$3:$K$17,2,FALSE)*U153)+(VLOOKUP($V$2,[4]Prices!$J$3:$K$17,2,FALSE)*V153)+(VLOOKUP($W$2,[4]Prices!$J$3:$K$17,2,FALSE)*W153)+(VLOOKUP($X$2,[4]Prices!$J$3:$K$17,2,FALSE)*X153)+(VLOOKUP($Y$2,[4]Prices!$J$3:$K$17,2,FALSE)*Y153)+(VLOOKUP($Z$2,[4]Prices!$J$3:$K$17,2,FALSE)*Z153)+(VLOOKUP($AA$2,[4]Prices!$J$3:$K$17,2,FALSE)*AA153)+(VLOOKUP($AB$2,[4]Prices!$J$3:$K$17,2,FALSE)*AB153)+M153 -> 0 | AD153: 0 | AF153: =AD153-AE153 -> 0 | AH153: =AD153+AG153 -> 0 | AI153: =AH153/M153 -> #DIV/0! | AJ153: =AH153/AC153 -> #DIV/0!
A154: 152 | I154: MRS PAUL | J154: SWR | K154: Ibadan | L154: SWC0951 | M154: =IFERROR(VLOOKUP($L154,[3]Consolidated!$C$9:$AC$452,27,0),0) -> 2433600 | N154: =IFERROR(VLOOKUP($L154,[3]Consolidated!$C$9:$AC$452,5,0),0) -> 10 | AC154: =(VLOOKUP($O$2,[4]Prices!$E$3:$K$17,2,FALSE)*O154)+(VLOOKUP($P$2,[4]Prices!$J$3:$K$17,2,FALSE)*P154)+(VLOOKUP($Q$2,[4]Prices!$J$3:$K$17,2,FALSE)*Q154)+(VLOOKUP($R$2,[4]Prices!$J$3:$K$17,2,FALSE)*R154)+(VLOOKUP($S$2,[4]Prices!$J$3:$K$17,2,FALSE)*S154)+(VLOOKUP($T$2,[4]Prices!$J$3:$K$17,2,FALSE)*T154)+(VLOOKUP($U$2,[4]Prices!$J$3:$K$17,2,FALSE)*U154)+(VLOOKUP($V$2,[4]Prices!$J$3:$K$17,2,FALSE)*V154)+(VLOOKUP($W$2,[4]Prices!$J$3:$K$17,2,FALSE)*W154)+(VLOOKUP($X$2,[4]Prices!$J$3:$K$17,2,FALSE)*X154)+(VLOOKUP($Y$2,[4]Prices!$J$3:$K$17,2,FALSE)*Y154)+(VLOOKUP($Z$2,[4]Prices!$J$3:$K$17,2,FALSE)*Z154)+(VLOOKUP($AA$2,[4]Prices!$J$3:$K$17,2,FALSE)*AA154)+(VLOOKUP($AB$2,[4]Prices!$J$3:$K$17,2,FALSE)*AB154)+M154 -> 2433600 | AD154: 847260 | AF154: =AD154-AE154 -> 847260 | AH154: =AD154+AG154 -> 847260 | AI154: =AH154/M154 -> 0.34815089 | AJ154: =AH154/AC154 -> 0.34815089
A155: 153 | I155: Iya Alimot | J155: SWR | K155: Ibadan | L155: SWC1699 | M155: =IFERROR(VLOOKUP($L155,[3]Consolidated!$C$9:$AC$452,27,0),0) -> 6819575 | N155: =IFERROR(VLOOKUP($L155,[3]Consolidated!$C$9:$AC$452,5,0),0) -> 40 | O155: 5 | AC155: =(VLOOKUP($O$2,[4]Prices!$E$3:$K$17,2,FALSE)*O155)+(VLOOKUP($P$2,[4]Prices!$J$3:$K$17,2,FALSE)*P155)+(VLOOKUP($Q$2,[4]Prices!$J$3:$K$17,2,FALSE)*Q155)+(VLOOKUP($R$2,[4]Prices!$J$3:$K$17,2,FALSE)*R155)+(VLOOKUP($S$2,[4]Prices!$J$3:$K$17,2,FALSE)*S155)+(VLOOKUP($T$2,[4]Prices!$J$3:$K$17,2,FALSE)*T155)+(VLOOKUP($U$2,[4]Prices!$J$3:$K$17,2,FALSE)*U155)+(VLOOKUP($V$2,[4]Prices!$J$3:$K$17,2,FALSE)*V155)+(VLOOKUP($W$2,[4]Prices!$J$3:$K$17,2,FALSE)*W155)+(VLOOKUP($X$2,[4]Prices!$J$3:$K$17,2,FALSE)*X155)+(VLOOKUP($Y$2,[4]Prices!$J$3:$K$17,2,FALSE)*Y155)+(VLOOKUP($Z$2,[4]Prices!$J$3:$K$17,2,FALSE)*Z155)+(VLOOKUP($AA$2,[4]Prices!$J$3:$K$17,2,FALSE)*AA155)+(VLOOKUP($AB$2,[4]Prices!$J$3:$K$17,2,FALSE)*AB155)+M155 -> 8124575 | AD155: 4353500 | AF155: =AD155-AE155 -> 4353500 | AG155: 756000 | AH155: =AD155+AG155 -> 5109500 | AI155: =AH155/M155 -> 0.74924024 | AJ155: =AH155/AC155 -> 0.62889443
A156: 154 | I156: Alhaja Adija Kubura | J156: SWR | K156: Ibadan | L156: SWC1052 | M156: =IFERROR(VLOOKUP($L156,[3]Consolidated!$C$9:$AC$452,27,0),0) -> 0 | N156: =IFERROR(VLOOKUP($L156,[3]Consolidated!$C$9:$AC$452,5,0),0) -> 0 | AC156: =(VLOOKUP($O$2,[4]Prices!$E$3:$K$17,2,FALSE)*O156)+(VLOOKUP($P$2,[4]Prices!$J$3:$K$17,2,FALSE)*P156)+(VLOOKUP($Q$2,[4]Prices!$J$3:$K$17,2,FALSE)*Q156)+(VLOOKUP($R$2,[4]Prices!$J$3:$K$17,2,FALSE)*R156)+(VLOOKUP($S$2,[4]Prices!$J$3:$K$17,2,FALSE)*S156)+(VLOOKUP($T$2,[4]Prices!$J$3:$K$17,2,FALSE)*T156)+(VLOOKUP($U$2,[4]Prices!$J$3:$K$17,2,FALSE)*U156)+(VLOOKUP($V$2,[4]Prices!$J$3:$K$17,2,FALSE)*V156)+(VLOOKUP($W$2,[4]Prices!$J$3:$K$17,2,FALSE)*W156)+(VLOOKUP($X$2,[4]Prices!$J$3:$K$17,2,FALSE)*X156)+(VLOOKUP($Y$2,[4]Prices!$J$3:$K$17,2,FALSE)*Y156)+(VLOOKUP($Z$2,[4]Prices!$J$3:$K$17,2,FALSE)*Z156)+(VLOOKUP($AA$2,[4]Prices!$J$3:$K$17,2,FALSE)*AA156)+(VLOOKUP($AB$2,[4]Prices!$J$3:$K$17,2,FALSE)*AB156)+M156 -> 0 | AD156: 0 | AF156: =AD156-AE156 -> 0 | AH156: =AD156+AG156 -> 0 | AI156: =AH156/M156 -> #DIV/0! | AJ156: =AH156/AC156 -> #DIV/0!
A157: 155 | I157: BABA ISA | J157: SWR | K157: Ibadan | L157: SWC1051 | M157: =IFERROR(VLOOKUP($L157,[3]Consolidated!$C$9:$AC$452,27,0),0) -> 1862500 | N157: =IFERROR(VLOOKUP($L157,[3]Consolidated!$C$9:$AC$452,5,0),0) -> 11 | AC157: =(VLOOKUP($O$2,[4]Prices!$E$3:$K$17,2,FALSE)*O157)+(VLOOKUP($P$2,[4]Prices!$J$3:$K$17,2,FALSE)*P157)+(VLOOKUP($Q$2,[4]Prices!$J$3:$K$17,2,FALSE)*Q157)+(VLOOKUP($R$2,[4]Prices!$J$3:$K$17,2,FALSE)*R157)+(VLOOKUP($S$2,[4]Prices!$J$3:$K$17,2,FALSE)*S157)+(VLOOKUP($T$2,[4]Prices!$J$3:$K$17,2,FALSE)*T157)+(VLOOKUP($U$2,[4]Prices!$J$3:$K$17,2,FALSE)*U157)+(VLOOKUP($V$2,[4]Prices!$J$3:$K$17,2,FALSE)*V157)+(VLOOKUP($W$2,[4]Prices!$J$3:$K$17,2,FALSE)*W157)+(VLOOKUP($X$2,[4]Prices!$J$3:$K$17,2,FALSE)*X157)+(VLOOKUP($Y$2,[4]Prices!$J$3:$K$17,2,FALSE)*Y157)+(VLOOKUP($Z$2,[4]Prices!$J$3:$K$17,2,FALSE)*Z157)+(VLOOKUP($AA$2,[4]Prices!$J$3:$K$17,2,FALSE)*AA157)+(VLOOKUP($AB$2,[4]Prices!$J$3:$K$17,2,FALSE)*AB157)+M157 -> 1862500 | AD157: 0 | AF157: =AD157-AE157 -> 0 | AH157: =AD157+AG157 -> 0 | AI157: =AH157/M157 -> 0 | AJ157: =AH157/AC157 -> 0
A158: 156 | I158: Iya Ibeji (Stockiest) | J158: SWR | K158: Ibadan | L158: SWC0865 | M158: =IFERROR(VLOOKUP($L158,[3]Consolidated!$C$9:$AC$452,27,0),0) -> 8610000 | N158: =IFERROR(VLOOKUP($L158,[3]Consolidated!$C$9:$AC$452,5,0),0) -> 45 | AC158: =(VLOOKUP($O$2,[4]Prices!$E$3:$K$17,2,FALSE)*O158)+(VLOOKUP($P$2,[4]Prices!$J$3:$K$17,2,FALSE)*P158)+(VLOOKUP($Q$2,[4]Prices!$J$3:$K$17,2,FALSE)*Q158)+(VLOOKUP($R$2,[4]Prices!$J$3:$K$17,2,FALSE)*R158)+(VLOOKUP($S$2,[4]Prices!$J$3:$K$17,2,FALSE)*S158)+(VLOOKUP($T$2,[4]Prices!$J$3:$K$17,2,FALSE)*T158)+(VLOOKUP($U$2,[4]Prices!$J$3:$K$17,2,FALSE)*U158)+(VLOOKUP($V$2,[4]Prices!$J$3:$K$17,2,FALSE)*V158)+(VLOOKUP($W$2,[4]Prices!$J$3:$K$17,2,FALSE)*W158)+(VLOOKUP($X$2,[4]Prices!$J$3:$K$17,2,FALSE)*X158)+(VLOOKUP($Y$2,[4]Prices!$J$3:$K$17,2,FALSE)*Y158)+(VLOOKUP($Z$2,[4]Prices!$J$3:$K$17,2,FALSE)*Z158)+(VLOOKUP($AA$2,[4]Prices!$J$3:$K$17,2,FALSE)*AA158)+(VLOOKUP($AB$2,[4]Prices!$J$3:$K$17,2,FALSE)*AB158)+M158 -> 8610000 | AD158: 0 | AF158: =AD158-AE158 -> 0 | AH158: =AD158+AG158 -> 0 | AI158: =AH158/M158 -> 0 | AJ158: =AH158/AC158 -> 0
A159: 157 | I159: TEE & KAY | J159: SWR | K159: Ibadan | L159: SWC1685 | M159: =IFERROR(VLOOKUP($L159,[3]Consolidated!$C$9:$AC$452,27,0),0) -> 7483437.5 | N159: =IFERROR(VLOOKUP($L159,[3]Consolidated!$C$9:$AC$452,5,0),0) -> 35 | AC159: =(VLOOKUP($O$2,[4]Prices!$E$3:$K$17,2,FALSE)*O159)+(VLOOKUP($P$2,[4]Prices!$J$3:$K$17,2,FALSE)*P159)+(VLOOKUP($Q$2,[4]Prices!$J$3:$K$17,2,FALSE)*Q159)+(VLOOKUP($R$2,[4]Prices!$J$3:$K$17,2,FALSE)*R159)+(VLOOKUP($S$2,[4]Prices!$J$3:$K$17,2,FALSE)*S159)+(VLOOKUP($T$2,[4]Prices!$J$3:$K$17,2,FALSE)*T159)+(VLOOKUP($U$2,[4]Prices!$J$3:$K$17,2,FALSE)*U159)+(VLOOKUP($V$2,[4]Prices!$J$3:$K$17,2,FALSE)*V159)+(VLOOKUP($W$2,[4]Prices!$J$3:$K$17,2,FALSE)*W159)+(VLOOKUP($X$2,[4]Prices!$J$3:$K$17,2,FALSE)*X159)+(VLOOKUP($Y$2,[4]Prices!$J$3:$K$17,2,FALSE)*Y159)+(VLOOKUP($Z$2,[4]Prices!$J$3:$K$17,2,FALSE)*Z159)+(VLOOKUP($AA$2,[4]Prices!$J$3:$K$17,2,FALSE)*AA159)+(VLOOKUP($AB$2,[4]Prices!$J$3:$K$17,2,FALSE)*AB159)+M159 -> 7483437.5 | AD159: 1804350 | AF159: =AD159-AE159 -> 1804350 | AH159: =AD159+AG159 -> 1804350 | AI159: =AH159/M159 -> 0.24111246 | AJ159: =AH159/AC159 -> 0.24111246
A160: 158 | I160: IYA DAMMY | J160: SWR | K160: Ibadan | L160: SWC1270 | M160: =IFERROR(VLOOKUP($L160,[3]Consolidated!$C$9:$AC$452,27,0),0) -> 0 | N160: =IFERROR(VLOOKUP($L160,[3]Consolidated!$C$9:$AC$452,5,0),0) -> 0 | AC160: =(VLOOKUP($O$2,[4]Prices!$E$3:$K$17,2,FALSE)*O160)+(VLOOKUP($P$2,[4]Prices!$J$3:$K$17,2,FALSE)*P160)+(VLOOKUP($Q$2,[4]Prices!$J$3:$K$17,2,FALSE)*Q160)+(VLOOKUP($R$2,[4]Prices!$J$3:$K$17,2,FALSE)*R160)+(VLOOKUP($S$2,[4]Prices!$J$3:$K$17,2,FALSE)*S160)+(VLOOKUP($T$2,[4]Prices!$J$3:$K$17,2,FALSE)*T160)+(VLOOKUP($U$2,[4]Prices!$J$3:$K$17,2,FALSE)*U160)+(VLOOKUP($V$2,[4]Prices!$J$3:$K$17,2,FALSE)*V160)+(VLOOKUP($W$2,[4]Prices!$J$3:$K$17,2,FALSE)*W160)+(VLOOKUP($X$2,[4]Prices!$J$3:$K$17,2,FALSE)*X160)+(VLOOKUP($Y$2,[4]Prices!$J$3:$K$17,2,FALSE)*Y160)+(VLOOKUP($Z$2,[4]Prices!$J$3:$K$17,2,FALSE)*Z160)+(VLOOKUP($AA$2,[4]Prices!$J$3:$K$17,2,FALSE)*AA160)+(VLOOKUP($AB$2,[4]Prices!$J$3:$K$17,2,FALSE)*AB160)+M160 -> 0 | AD160: 0 | AF160: =AD160-AE160 -> 0 | AH160: =AD160+AG160 -> 0 | AI160: =AH160/M160 -> #DIV/0! | AJ160: =AH160/AC160 -> #DIV/0!
A161: 159 | I161: IYA FOLLY | J161: SWR | K161: Ibadan | L161: SWC1107 | M161: =IFERROR(VLOOKUP($L161,[3]Consolidated!$C$9:$AC$452,27,0),0) -> 6549250 | N161: =IFERROR(VLOOKUP($L161,[3]Consolidated!$C$9:$AC$452,5,0),0) -> 35 | AC161: =(VLOOKUP($O$2,[4]Prices!$E$3:$K$17,2,FALSE)*O161)+(VLOOKUP($P$2,[4]Prices!$J$3:$K$17,2,FALSE)*P161)+(VLOOKUP($Q$2,[4]Prices!$J$3:$K$17,2,FALSE)*Q161)+(VLOOKUP($R$2,[4]Prices!$J$3:$K$17,2,FALSE)*R161)+(VLOOKUP($S$2,[4]Prices!$J$3:$K$17,2,FALSE)*S161)+(VLOOKUP($T$2,[4]Prices!$J$3:$K$17,2,FALSE)*T161)+(VLOOKUP($U$2,[4]Prices!$J$3:$K$17,2,FALSE)*U161)+(VLOOKUP($V$2,[4]Prices!$J$3:$K$17,2,FALSE)*V161)+(VLOOKUP($W$2,[4]Prices!$J$3:$K$17,2,FALSE)*W161)+(VLOOKUP($X$2,[4]Prices!$J$3:$K$17,2,FALSE)*X161)+(VLOOKUP($Y$2,[4]Prices!$J$3:$K$17,2,FALSE)*Y161)+(VLOOKUP($Z$2,[4]Prices!$J$3:$K$17,2,FALSE)*Z161)+(VLOOKUP($AA$2,[4]Prices!$J$3:$K$17,2,FALSE)*AA161)+(VLOOKUP($AB$2,[4]Prices!$J$3:$K$17,2,FALSE)*AB161)+M161 -> 6549250 | AD161: 0 | AF161: =AD161-AE161 -> 0 | AH161: =AD161+AG161 -> 0 | AI161: =AH161/M161 -> 0 | AJ161: =AH161/AC161 -> 0
A162: 160 | I162: IYA NIYI | J162: SWR | K162: Ibadan | L162: SWC0955 | M162: =IFERROR(VLOOKUP($L162,[3]Consolidated!$C$9:$AC$452,27,0),0) -> 6549250 | N162: =IFERROR(VLOOKUP($L162,[3]Consolidated!$C$9:$AC$452,5,0),0) -> 35 | AC162: =(VLOOKUP($O$2,[4]Prices!$E$3:$K$17,2,FALSE)*O162)+(VLOOKUP($P$2,[4]Prices!$J$3:$K$17,2,FALSE)*P162)+(VLOOKUP($Q$2,[4]Prices!$J$3:$K$17,2,FALSE)*Q162)+(VLOOKUP($R$2,[4]Prices!$J$3:$K$17,2,FALSE)*R162)+(VLOOKUP($S$2,[4]Prices!$J$3:$K$17,2,FALSE)*S162)+(VLOOKUP($T$2,[4]Prices!$J$3:$K$17,2,FALSE)*T162)+(VLOOKUP($U$2,[4]Prices!$J$3:$K$17,2,FALSE)*U162)+(VLOOKUP($V$2,[4]Prices!$J$3:$K$17,2,FALSE)*V162)+(VLOOKUP($W$2,[4]Prices!$J$3:$K$17,2,FALSE)*W162)+(VLOOKUP($X$2,[4]Prices!$J$3:$K$17,2,FALSE)*X162)+(VLOOKUP($Y$2,[4]Prices!$J$3:$K$17,2,FALSE)*Y162)+(VLOOKUP($Z$2,[4]Prices!$J$3:$K$17,2,FALSE)*Z162)+(VLOOKUP($AA$2,[4]Prices!$J$3:$K$17,2,FALSE)*AA162)+(VLOOKUP($AB$2,[4]Prices!$J$3:$K$17,2,FALSE)*AB162)+M162 -> 6549250 | AD162: 1804350 | AF162: =AD162-AE162 -> 1804350 | AH162: =AD162+AG162 -> 1804350 | AI162: =AH162/M162 -> 0.27550483 | AJ162: =AH162/AC162 -> 0.27550483
A163: 161 | I163: Alhaja Alaranse (Stockiest) | J163: SWR | K163: Ibadan | L163: RCP000045 | M163: =IFERROR(VLOOKUP($L163,[3]Consolidated!$C$9:$AC$452,27,0),0) -> 0 | N163: =IFERROR(VLOOKUP($L163,[3]Consolidated!$C$9:$AC$452,5,0),0) -> 0 | AC163: =(VLOOKUP($O$2,[4]Prices!$E$3:$K$17,2,FALSE)*O163)+(VLOOKUP($P$2,[4]Prices!$J$3:$K$17,2,FALSE)*P163)+(VLOOKUP($Q$2,[4]Prices!$J$3:$K$17,2,FALSE)*Q163)+(VLOOKUP($R$2,[4]Prices!$J$3:$K$17,2,FALSE)*R163)+(VLOOKUP($S$2,[4]Prices!$J$3:$K$17,2,FALSE)*S163)+(VLOOKUP($T$2,[4]Prices!$J$3:$K$17,2,FALSE)*T163)+(VLOOKUP($U$2,[4]Prices!$J$3:$K$17,2,FALSE)*U163)+(VLOOKUP($V$2,[4]Prices!$J$3:$K$17,2,FALSE)*V163)+(VLOOKUP($W$2,[4]Prices!$J$3:$K$17,2,FALSE)*W163)+(VLOOKUP($X$2,[4]Prices!$J$3:$K$17,2,FALSE)*X163)+(VLOOKUP($Y$2,[4]Prices!$J$3:$K$17,2,FALSE)*Y163)+(VLOOKUP($Z$2,[4]Prices!$J$3:$K$17,2,FALSE)*Z163)+(VLOOKUP($AA$2,[4]Prices!$J$3:$K$17,2,FALSE)*AA163)+(VLOOKUP($AB$2,[4]Prices!$J$3:$K$17,2,FALSE)*AB163)+M163 -> 0 | AD163: 0 | AF163: =AD163-AE163 -> 0 | AH163: =AD163+AG163 -> 0 | AI163: =AH163/M163 -> #DIV/0! | AJ163: =AH163/AC163 -> #DIV/0!
A164: 162 | I164: MRS ALAYO (RME) | J164: SWR | K164: Ibadan | L164: SWC1845 | M164: =IFERROR(VLOOKUP($L164,[3]Consolidated!$C$9:$AC$452,27,0),0) -> 3992835 | N164: =IFERROR(VLOOKUP($L164,[3]Consolidated!$C$9:$AC$452,5,0),0) -> 20 | AC164: =(VLOOKUP($O$2,[4]Prices!$E$3:$K$17,2,FALSE)*O164)+(VLOOKUP($P$2,[4]Prices!$J$3:$K$17,2,FALSE)*P164)+(VLOOKUP($Q$2,[4]Prices!$J$3:$K$17,2,FALSE)*Q164)+(VLOOKUP($R$2,[4]Prices!$J$3:$K$17,2,FALSE)*R164)+(VLOOKUP($S$2,[4]Prices!$J$3:$K$17,2,FALSE)*S164)+(VLOOKUP($T$2,[4]Prices!$J$3:$K$17,2,FALSE)*T164)+(VLOOKUP($U$2,[4]Prices!$J$3:$K$17,2,FALSE)*U164)+(VLOOKUP($V$2,[4]Prices!$J$3:$K$17,2,FALSE)*V164)+(VLOOKUP($W$2,[4]Prices!$J$3:$K$17,2,FALSE)*W164)+(VLOOKUP($X$2,[4]Prices!$J$3:$K$17,2,FALSE)*X164)+(VLOOKUP($Y$2,[4]Prices!$J$3:$K$17,2,FALSE)*Y164)+(VLOOKUP($Z$2,[4]Prices!$J$3:$K$17,2,FALSE)*Z164)+(VLOOKUP($AA$2,[4]Prices!$J$3:$K$17,2,FALSE)*AA164)+(VLOOKUP($AB$2,[4]Prices!$J$3:$K$17,2,FALSE)*AB164)+M164 -> 3992835 | AD164: 1846000 | AF164: =AD164-AE164 -> 1846000 | AG164: 869000 | AH164: =AD164+AG164 -> 2715000 | AI164: =AH164/M164 -> 0.67996799 | AJ164: =AH164/AC164 -> 0.67996799
A165: 163 | I165: MADAM GOODLUCK | J165: SWR | K165: Ibadan | L165: SWC2242 | M165: =IFERROR(VLOOKUP($L165,[3]Consolidated!$C$9:$AC$452,27,0),0) -> 2917810 | N165: =IFERROR(VLOOKUP($L165,[3]Consolidated!$C$9:$AC$452,5,0),0) -> 15 | AC165: =(VLOOKUP($O$2,[4]Prices!$E$3:$K$17,2,FALSE)*O165)+(VLOOKUP($P$2,[4]Prices!$J$3:$K$17,2,FALSE)*P165)+(VLOOKUP($Q$2,[4]Prices!$J$3:$K$17,2,FALSE)*Q165)+(VLOOKUP($R$2,[4]Prices!$J$3:$K$17,2,FALSE)*R165)+(VLOOKUP($S$2,[4]Prices!$J$3:$K$17,2,FALSE)*S165)+(VLOOKUP($T$2,[4]Prices!$J$3:$K$17,2,FALSE)*T165)+(VLOOKUP($U$2,[4]Prices!$J$3:$K$17,2,FALSE)*U165)+(VLOOKUP($V$2,[4]Prices!$J$3:$K$17,2,FALSE)*V165)+(VLOOKUP($W$2,[4]Prices!$J$3:$K$17,2,FALSE)*W165)+(VLOOKUP($X$2,[4]Prices!$J$3:$K$17,2,FALSE)*X165)+(VLOOKUP($Y$2,[4]Prices!$J$3:$K$17,2,FALSE)*Y165)+(VLOOKUP($Z$2,[4]Prices!$J$3:$K$17,2,FALSE)*Z165)+(VLOOKUP($AA$2,[4]Prices!$J$3:$K$17,2,FALSE)*AA165)+(VLOOKUP($AB$2,[4]Prices!$J$3:$K$17,2,FALSE)*AB165)+M165 -> 2917810 | AD165: 993700 | AF165: =AD165-AE165 -> 993700 | AH165: =AD165+AG165 -> 993700 | AI165: =AH165/M165 -> 0.34056364 | AJ165: =AH165/AC165 -> 0.34056364
A166: 164 | I166: AWOBAJO STORE | J166: SWR | K166: Ibadan | L166: SWC2935 | M166: =IFERROR(VLOOKUP($L166,[3]Consolidated!$C$9:$AC$452,27,0),0) -> 12399500 | N166: =IFERROR(VLOOKUP($L166,[3]Consolidated!$C$9:$AC$452,5,0),0) -> 60 | AC166: =(VLOOKUP($O$2,[4]Prices!$E$3:$K$17,2,FALSE)*O166)+(VLOOKUP($P$2,[4]Prices!$J$3:$K$17,2,FALSE)*P166)+(VLOOKUP($Q$2,[4]Prices!$J$3:$K$17,2,FALSE)*Q166)+(VLOOKUP($R$2,[4]Prices!$J$3:$K$17,2,FALSE)*R166)+(VLOOKUP($S$2,[4]Prices!$J$3:$K$17,2,FALSE)*S166)+(VLOOKUP($T$2,[4]Prices!$J$3:$K$17,2,FALSE)*T166)+(VLOOKUP($U$2,[4]Prices!$J$3:$K$17,2,FALSE)*U166)+(VLOOKUP($V$2,[4]Prices!$J$3:$K$17,2,FALSE)*V166)+(VLOOKUP($W$2,[4]Prices!$J$3:$K$17,2,FALSE)*W166)+(VLOOKUP($X$2,[4]Prices!$J$3:$K$17,2,FALSE)*X166)+(VLOOKUP($Y$2,[4]Prices!$J$3:$K$17,2,FALSE)*Y166)+(VLOOKUP($Z$2,[4]Prices!$J$3:$K$17,2,FALSE)*Z166)+(VLOOKUP($AA$2,[4]Prices!$J$3:$K$17,2,FALSE)*AA166)+(VLOOKUP($AB$2,[4]Prices!$J$3:$K$17,2,FALSE)*AB166)+M166 -> 12399500 | AD166: 4262450 | AF166: =AD166-AE166 -> 4262450 | AH166: =AD166+AG166 -> 4262450 | AI166: =AH166/M166 -> 0.34375983 | AJ166: =AH166/AC166 -> 0.34375983
A167: 165 | I167: Mummy Pius | J167: SWR | K167: Ibadan | L167: SWC2962 | M167: =IFERROR(VLOOKUP($L167,[3]Consolidated!$C$9:$AC$452,27,0),0) -> 2246500 | N167: =IFERROR(VLOOKUP($L167,[3]Consolidated!$C$9:$AC$452,5,0),0) -> 11 | AC167: =(VLOOKUP($O$2,[4]Prices!$E$3:$K$17,2,FALSE)*O167)+(VLOOKUP($P$2,[4]Prices!$J$3:$K$17,2,FALSE)*P167)+(VLOOKUP($Q$2,[4]Prices!$J$3:$K$17,2,FALSE)*Q167)+(VLOOKUP($R$2,[4]Prices!$J$3:$K$17,2,FALSE)*R167)+(VLOOKUP($S$2,[4]Prices!$J$3:$K$17,2,FALSE)*S167)+(VLOOKUP($T$2,[4]Prices!$J$3:$K$17,2,FALSE)*T167)+(VLOOKUP($U$2,[4]Prices!$J$3:$K$17,2,FALSE)*U167)+(VLOOKUP($V$2,[4]Prices!$J$3:$K$17,2,FALSE)*V167)+(VLOOKUP($W$2,[4]Prices!$J$3:$K$17,2,FALSE)*W167)+(VLOOKUP($X$2,[4]Prices!$J$3:$K$17,2,FALSE)*X167)+(VLOOKUP($Y$2,[4]Prices!$J$3:$K$17,2,FALSE)*Y167)+(VLOOKUP($Z$2,[4]Prices!$J$3:$K$17,2,FALSE)*Z167)+(VLOOKUP($AA$2,[4]Prices!$J$3:$K$17,2,FALSE)*AA167)+(VLOOKUP($AB$2,[4]Prices!$J$3:$K$17,2,FALSE)*AB167)+M167 -> 2246500 | AD167: 0 | AF167: =AD167-AE167 -> 0 | AH167: =AD167+AG167 -> 0 | AI167: =AH167/M167 -> 0 | AJ167: =AH167/AC167 -> 0
A168: 166 | I168: Morufat Ayoola | J168: SWR | K168: Ilorin | L168: SWC2816 | M168: =IFERROR(VLOOKUP($L168,[3]Consolidated!$C$9:$AC$452,27,0),0) -> 1937600 | N168: =IFERROR(VLOOKUP($L168,[3]Consolidated!$C$9:$AC$452,5,0),0) -> 10 | AC168: =(VLOOKUP($O$2,[4]Prices!$E$3:$K$17,2,FALSE)*O168)+(VLOOKUP($P$2,[4]Prices!$J$3:$K$17,2,FALSE)*P168)+(VLOOKUP($Q$2,[4]Prices!$J$3:$K$17,2,FALSE)*Q168)+(VLOOKUP($R$2,[4]Prices!$J$3:$K$17,2,FALSE)*R168)+(VLOOKUP($S$2,[4]Prices!$J$3:$K$17,2,FALSE)*S168)+(VLOOKUP($T$2,[4]Prices!$J$3:$K$17,2,FALSE)*T168)+(VLOOKUP($U$2,[4]Prices!$J$3:$K$17,2,FALSE)*U168)+(VLOOKUP($V$2,[4]Prices!$J$3:$K$17,2,FALSE)*V168)+(VLOOKUP($W$2,[4]Prices!$J$3:$K$17,2,FALSE)*W168)+(VLOOKUP($X$2,[4]Prices!$J$3:$K$17,2,FALSE)*X168)+(VLOOKUP($Y$2,[4]Prices!$J$3:$K$17,2,FALSE)*Y168)+(VLOOKUP($Z$2,[4]Prices!$J$3:$K$17,2,FALSE)*Z168)+(VLOOKUP($AA$2,[4]Prices!$J$3:$K$17,2,FALSE)*AA168)+(VLOOKUP($AB$2,[4]Prices!$J$3:$K$17,2,FALSE)*AB168)+M168 -> 1937600 | AD168: 661900 | AF168: =AD168-AE168 -> 661900 | AH168: =AD168+AG168 -> 661900 | AI168: =AH168/M168 -> 0.34160818 | AJ168: =AH168/AC168 -> 0.34160818
A169: 167 | I169: Iya Blessing | J169: SWR | K169: Ilorin | L169: SWC2338 | M169: =IFERROR(VLOOKUP($L169,[3]Consolidated!$C$9:$AC$452,27,0),0) -> 8596050 | N169: =IFERROR(VLOOKUP($L169,[3]Consolidated!$C$9:$AC$452,5,0),0) -> 40 | AC169: =(VLOOKUP($O$2,[4]Prices!$E$3:$K$17,2,FALSE)*O169)+(VLOOKUP($P$2,[4]Prices!$J$3:$K$17,2,FALSE)*P169)+(VLOOKUP($Q$2,[4]Prices!$J$3:$K$17,2,FALSE)*Q169)+(VLOOKUP($R$2,[4]Prices!$J$3:$K$17,2,FALSE)*R169)+(VLOOKUP($S$2,[4]Prices!$J$3:$K$17,2,FALSE)*S169)+(VLOOKUP($T$2,[4]Prices!$J$3:$K$17,2,FALSE)*T169)+(VLOOKUP($U$2,[4]Prices!$J$3:$K$17,2,FALSE)*U169)+(VLOOKUP($V$2,[4]Prices!$J$3:$K$17,2,FALSE)*V169)+(VLOOKUP($W$2,[4]Prices!$J$3:$K$17,2,FALSE)*W169)+(VLOOKUP($X$2,[4]Prices!$J$3:$K$17,2,FALSE)*X169)+(VLOOKUP($Y$2,[4]Prices!$J$3:$K$17,2,FALSE)*Y169)+(VLOOKUP($Z$2,[4]Prices!$J$3:$K$17,2,FALSE)*Z169)+(VLOOKUP($AA$2,[4]Prices!$J$3:$K$17,2,FALSE)*AA169)+(VLOOKUP($AB$2,[4]Prices!$J$3:$K$17,2,FALSE)*AB169)+M169 -> 8596050 | AD169: 1267750 | AF169: =AD169-AE169 -> 1267750 | AH169: =AD169+AG169 -> 1267750 | AI169: =AH169/M169 -> 0.14748053 | AJ169: =AH169/AC169 -> 0.14748053
A170: 168 | I170: Iya Fathia | J170: SWR | K170: Ilorin | L170: SWC2337 | M170: =IFERROR(VLOOKUP($L170,[3]Consolidated!$C$9:$AC$452,27,0),0) -> 8359400 | N170: =IFERROR(VLOOKUP($L170,[3]Consolidated!$C$9:$AC$452,5,0),0) -> 40 | AC170: =(VLOOKUP($O$2,[4]Prices!$E$3:$K$17,2,FALSE)*O170)+(VLOOKUP($P$2,[4]Prices!$J$3:$K$17,2,FALSE)*P170)+(VLOOKUP($Q$2,[4]Prices!$J$3:$K$17,2,FALSE)*Q170)+(VLOOKUP($R$2,[4]Prices!$J$3:$K$17,2,FALSE)*R170)+(VLOOKUP($S$2,[4]Prices!$J$3:$K$17,2,FALSE)*S170)+(VLOOKUP($T$2,[4]Prices!$J$3:$K$17,2,FALSE)*T170)+(VLOOKUP($U$2,[4]Prices!$J$3:$K$17,2,FALSE)*U170)+(VLOOKUP($V$2,[4]Prices!$J$3:$K$17,2,FALSE)*V170)+(VLOOKUP($W$2,[4]Prices!$J$3:$K$17,2,FALSE)*W170)+(VLOOKUP($X$2,[4]Prices!$J$3:$K$17,2,FALSE)*X170)+(VLOOKUP($Y$2,[4]Prices!$J$3:$K$17,2,FALSE)*Y170)+(VLOOKUP($Z$2,[4]Prices!$J$3:$K$17,2,FALSE)*Z170)+(VLOOKUP($AA$2,[4]Prices!$J$3:$K$17,2,FALSE)*AA170)+(VLOOKUP($AB$2,[4]Prices!$J$3:$K$17,2,FALSE)*AB170)+M170 -> 8359400 | AD170: 1319050 | AF170: =AD170-AE170 -> 1319050 | AH170: =AD170+AG170 -> 1319050 | AI170: =AH170/M170 -> 0.15779243 | AJ170: =AH170/AC170 -> 0.15779243
A171: 169 | I171: L&B Stores | J171: SWR | K171: Ilorin | L171: SWC2336 | M171: =IFERROR(VLOOKUP($L171,[3]Consolidated!$C$9:$AC$452,27,0),0) -> 0 | N171: =IFERROR(VLOOKUP($L171,[3]Consolidated!$C$9:$AC$452,5,0),0) -> 0 | AC171: =(VLOOKUP($O$2,[4]Prices!$E$3:$K$17,2,FALSE)*O171)+(VLOOKUP($P$2,[4]Prices!$J$3:$K$17,2,FALSE)*P171)+(VLOOKUP($Q$2,[4]Prices!$J$3:$K$17,2,FALSE)*Q171)+(VLOOKUP($R$2,[4]Prices!$J$3:$K$17,2,FALSE)*R171)+(VLOOKUP($S$2,[4]Prices!$J$3:$K$17,2,FALSE)*S171)+(VLOOKUP($T$2,[4]Prices!$J$3:$K$17,2,FALSE)*T171)+(VLOOKUP($U$2,[4]Prices!$J$3:$K$17,2,FALSE)*U171)+(VLOOKUP($V$2,[4]Prices!$J$3:$K$17,2,FALSE)*V171)+(VLOOKUP($W$2,[4]Prices!$J$3:$K$17,2,FALSE)*W171)+(VLOOKUP($X$2,[4]Prices!$J$3:$K$17,2,FALSE)*X171)+(VLOOKUP($Y$2,[4]Prices!$J$3:$K$17,2,FALSE)*Y171)+(VLOOKUP($Z$2,[4]Prices!$J$3:$K$17,2,FALSE)*Z171)+(VLOOKUP($AA$2,[4]Prices!$J$3:$K$17,2,FALSE)*AA171)+(VLOOKUP($AB$2,[4]Prices!$J$3:$K$17,2,FALSE)*AB171)+M171 -> 0 | AD171: 0 | AF171: =AD171-AE171 -> 0 | AH171: =AD171+AG171 -> 0 | AI171: =AH171/M171 -> #DIV/0! | AJ171: =AH171/AC171 -> #DIV/0!
A172: 170 | I172: Omo Eko | J172: SWR | K172: Ilorin | L172: SWC0049 | M172: =IFERROR(VLOOKUP($L172,[3]Consolidated!$C$9:$AC$452,27,0),0) -> 0 | N172: =IFERROR(VLOOKUP($L172,[3]Consolidated!$C$9:$AC$452,5,0),0) -> 0 | AC172: =(VLOOKUP($O$2,[4]Prices!$E$3:$K$17,2,FALSE)*O172)+(VLOOKUP($P$2,[4]Prices!$J$3:$K$17,2,FALSE)*P172)+(VLOOKUP($Q$2,[4]Prices!$J$3:$K$17,2,FALSE)*Q172)+(VLOOKUP($R$2,[4]Prices!$J$3:$K$17,2,FALSE)*R172)+(VLOOKUP($S$2,[4]Prices!$J$3:$K$17,2,FALSE)*S172)+(VLOOKUP($T$2,[4]Prices!$J$3:$K$17,2,FALSE)*T172)+(VLOOKUP($U$2,[4]Prices!$J$3:$K$17,2,FALSE)*U172)+(VLOOKUP($V$2,[4]Prices!$J$3:$K$17,2,FALSE)*V172)+(VLOOKUP($W$2,[4]Prices!$J$3:$K$17,2,FALSE)*W172)+(VLOOKUP($X$2,[4]Prices!$J$3:$K$17,2,FALSE)*X172)+(VLOOKUP($Y$2,[4]Prices!$J$3:$K$17,2,FALSE)*Y172)+(VLOOKUP($Z$2,[4]Prices!$J$3:$K$17,2,FALSE)*Z172)+(VLOOKUP($AA$2,[4]Prices!$J$3:$K$17,2,FALSE)*AA172)+(VLOOKUP($AB$2,[4]Prices!$J$3:$K$17,2,FALSE)*AB172)+M172 -> 0 | AD172: 0 | AF172: =AD172-AE172 -> 0 | AH172: =AD172+AG172 -> 0 | AI172: =AH172/M172 -> #DIV/0! | AJ172: =AH172/AC172 -> #DIV/0!
A173: 171 | I173: Iya Abedeen | J173: SWR | K173: Ilorin | L173: SWC0045 | M173: =IFERROR(VLOOKUP($L173,[3]Consolidated!$C$9:$AC$452,27,0),0) -> 1558640 | N173: =IFERROR(VLOOKUP($L173,[3]Consolidated!$C$9:$AC$452,5,0),0) -> 10 | AC173: =(VLOOKUP($O$2,[4]Prices!$E$3:$K$17,2,FALSE)*O173)+(VLOOKUP($P$2,[4]Prices!$J$3:$K$17,2,FALSE)*P173)+(VLOOKUP($Q$2,[4]Prices!$J$3:$K$17,2,FALSE)*Q173)+(VLOOKUP($R$2,[4]Prices!$J$3:$K$17,2,FALSE)*R173)+(VLOOKUP($S$2,[4]Prices!$J$3:$K$17,2,FALSE)*S173)+(VLOOKUP($T$2,[4]Prices!$J$3:$K$17,2,FALSE)*T173)+(VLOOKUP($U$2,[4]Prices!$J$3:$K$17,2,FALSE)*U173)+(VLOOKUP($V$2,[4]Prices!$J$3:$K$17,2,FALSE)*V173)+(VLOOKUP($W$2,[4]Prices!$J$3:$K$17,2,FALSE)*W173)+(VLOOKUP($X$2,[4]Prices!$J$3:$K$17,2,FALSE)*X173)+(VLOOKUP($Y$2,[4]Prices!$J$3:$K$17,2,FALSE)*Y173)+(VLOOKUP($Z$2,[4]Prices!$J$3:$K$17,2,FALSE)*Z173)+(VLOOKUP($AA$2,[4]Prices!$J$3:$K$17,2,FALSE)*AA173)+(VLOOKUP($AB$2,[4]Prices!$J$3:$K$17,2,FALSE)*AB173)+M173 -> 1558640 | AD173: 0 | AF173: =AD173-AE173 -> 0 | AH173: =AD173+AG173 -> 0 | AI173: =AH173/M173 -> 0 | AJ173: =AH173/AC173 -> 0
